Workbook
Name CUSTOMER: TBLDATACUSTOMER[NAMA CUSTOMER]
Name CUSTOMER: TBLDATACUSTOMER[NAMA CUSTOMER]
Name CUSTOMER: TBLDATACUSTOMER[NAMA CUSTOMER]
Name KODE: TBLBAHANKELUAR[TAHUN]
Name KODEPRODUK: [1]!TBLREKAPBAHAN[KODE PRODUK]
Name MITRA: TBLDATAMITRAEPC[NAMA MITRA]
Name MITRA: TBLDATAMITRAEPC[NAMA MITRA]
Name MITRA: TBLDATAMITRAEPC[NAMA MITRA]
Name NOMORPRODUK: TBLBAHANKELUAR[TAHUN]
Name ZAMBI_AYAM: [2]ZAMBI!#REF!

Sheet DATA MITRA
A1: DATA MITRA EPC
A4: KODE MITRA | B4: NAMA MITRA | C4: NAMA PEREKRUT | D4: NO HP/WA | E4: Column1
A5: =LEFT(TBLDATAMITRAEPC[[#This Row],[NAMA MITRA]],1)&IFERROR(MID(TBLDATAMITRAEPC[[#This Row],[NAMA MITRA]],FIND(" ",TBLDATAMITRAEPC[[#This Row],[NAMA MITRA]],1)+1,1),"")&IFERROR(MID(TBLDATAMITRAEPC[[#This Row],[NAMA MITRA]],FIND(" ",TBLDATAMITRAEPC[[#This Row],[NAMA MITRA]],FIND(" ",TBLDATAMITRAEPC[[#This Row],[NAMA MITRA]],1)+1)+1,1),"")&IFERROR(MID(TBLDATAMITRAEPC[[#This Row],[NAMA MITRA]],FIND(" ",TBLDATAMITRAEPC[[#This Row],[NAMA MITRA]],FIND(" ",TBLDATAMITRAEPC[[#This Row],[NAMA MITRA]],FIND(" ",TBLDATAMITRAEPC[[#This Row],[NAMA MITRA]],1)+1)+1)+1,1),"")&IFERROR(MID(TBLDATAMITRAEPC[[#This Row],[NAMA MITRA]],FIND(" ",TBLDATAMITRAEPC[[#This Row],[NAMA MITRA]],FIND(" ",TBLDATAMITRAEPC[[#This Row],[NAMA MITRA]],FIND(" ",TBLDATAMITRAEPC[[#This Row],[NAMA MITRA]],FIND(" ",TBLDATAMITRAEPC[[#This Row],[NAMA MITRA]],1)+1)+1)+1)+1,1),"") -> A | B5: ANGEL | C5: NURUL HIDAYATU SAMSIAH
A6: =LEFT(TBLDATAMITRAEPC[[#This Row],[NAMA MITRA]],1)&IFERROR(MID(TBLDATAMITRAEPC[[#This Row],[NAMA MITRA]],FIND(" ",TBLDATAMITRAEPC[[#This Row],[NAMA MITRA]],1)+1,1),"")&IFERROR(MID(TBLDATAMITRAEPC[[#This Row],[NAMA MITRA]],FIND(" ",TBLDATAMITRAEPC[[#This Row],[NAMA MITRA]],FIND(" ",TBLDATAMITRAEPC[[#This Row],[NAMA MITRA]],1)+1)+1,1),"")&IFERROR(MID(TBLDATAMITRAEPC[[#This Row],[NAMA MITRA]],FIND(" ",TBLDATAMITRAEPC[[#This Row],[NAMA MITRA]],FIND(" ",TBLDATAMITRAEPC[[#This Row],[NAMA MITRA]],FIND(" ",TBLDATAMITRAEPC[[#This Row],[NAMA MITRA]],1)+1)+1)+1,1),"")&IFERROR(MID(TBLDATAMITRAEPC[[#This Row],[NAMA MITRA]],FIND(" ",TBLDATAMITRAEPC[[#This Row],[NAMA MITRA]],FIND(" ",TBLDATAMITRAEPC[[#This Row],[NAMA MITRA]],FIND(" ",TBLDATAMITRAEPC[[#This Row],[NAMA MITRA]],FIND(" ",TBLDATAMITRAEPC[[#This Row],[NAMA MITRA]],1)+1)+1)+1)+1,1),"") -> A | B6: ANI | C6: NURUL HIDAYATU SAMSIAH
A7: =LEFT(TBLDATAMITRAEPC[[#This Row],[NAMA MITRA]],1)&IFERROR(MID(TBLDATAMITRAEPC[[#This Row],[NAMA MITRA]],FIND(" ",TBLDATAMITRAEPC[[#This Row],[NAMA MITRA]],1)+1,1),"")&IFERROR(MID(TBLDATAMITRAEPC[[#This Row],[NAMA MITRA]],FIND(" ",TBLDATAMITRAEPC[[#This Row],[NAMA MITRA]],FIND(" ",TBLDATAMITRAEPC[[#This Row],[NAMA MITRA]],1)+1)+1,1),"")&IFERROR(MID(TBLDATAMITRAEPC[[#This Row],[NAMA MITRA]],FIND(" ",TBLDATAMITRAEPC[[#This Row],[NAMA MITRA]],FIND(" ",TBLDATAMITRAEPC[[#This Row],[NAMA MITRA]],FIND(" ",TBLDATAMITRAEPC[[#This Row],[NAMA MITRA]],1)+1)+1)+1,1),"")&IFERROR(MID(TBLDATAMITRAEPC[[#This Row],[NAMA MITRA]],FIND(" ",TBLDATAMITRAEPC[[#This Row],[NAMA MITRA]],FIND(" ",TBLDATAMITRAEPC[[#This Row],[NAMA MITRA]],FIND(" ",TBLDATAMITRAEPC[[#This Row],[NAMA MITRA]],FIND(" ",TBLDATAMITRAEPC[[#This Row],[NAMA MITRA]],1)+1)+1)+1)+1,1),"") -> CG | B7: CAHYA GALLERY | C7: CAHYA GALLERY
A8: =LEFT(TBLDATAMITRAEPC[[#This Row],[NAMA MITRA]],1)&IFERROR(MID(TBLDATAMITRAEPC[[#This Row],[NAMA MITRA]],FIND(" ",TBLDATAMITRAEPC[[#This Row],[NAMA MITRA]],1)+1,1),"")&IFERROR(MID(TBLDATAMITRAEPC[[#This Row],[NAMA MITRA]],FIND(" ",TBLDATAMITRAEPC[[#This Row],[NAMA MITRA]],FIND(" ",TBLDATAMITRAEPC[[#This Row],[NAMA MITRA]],1)+1)+1,1),"")&IFERROR(MID(TBLDATAMITRAEPC[[#This Row],[NAMA MITRA]],FIND(" ",TBLDATAMITRAEPC[[#This Row],[NAMA MITRA]],FIND(" ",TBLDATAMITRAEPC[[#This Row],[NAMA MITRA]],FIND(" ",TBLDATAMITRAEPC[[#This Row],[NAMA MITRA]],1)+1)+1)+1,1),"")&IFERROR(MID(TBLDATAMITRAEPC[[#This Row],[NAMA MITRA]],FIND(" ",TBLDATAMITRAEPC[[#This Row],[NAMA MITRA]],FIND(" ",TBLDATAMITRAEPC[[#This Row],[NAMA MITRA]],FIND(" ",TBLDATAMITRAEPC[[#This Row],[NAMA MITRA]],FIND(" ",TBLDATAMITRAEPC[[#This Row],[NAMA MITRA]],1)+1)+1)+1)+1,1),"") -> D | B8: DANI | C8: NURUL HIDAYATU SAMSIAH
A9: =LEFT(TBLDATAMITRAEPC[[#This Row],[NAMA MITRA]],1)&IFERROR(MID(TBLDATAMITRAEPC[[#This Row],[NAMA MITRA]],FIND(" ",TBLDATAMITRAEPC[[#This Row],[NAMA MITRA]],1)+1,1),"")&IFERROR(MID(TBLDATAMITRAEPC[[#This Row],[NAMA MITRA]],FIND(" ",TBLDATAMITRAEPC[[#This Row],[NAMA MITRA]],FIND(" ",TBLDATAMITRAEPC[[#This Row],[NAMA MITRA]],1)+1)+1,1),"")&IFERROR(MID(TBLDATAMITRAEPC[[#This Row],[NAMA MITRA]],FIND(" ",TBLDATAMITRAEPC[[#This Row],[NAMA MITRA]],FIND(" ",TBLDATAMITRAEPC[[#This Row],[NAMA MITRA]],FIND(" ",TBLDATAMITRAEPC[[#This Row],[NAMA MITRA]],1)+1)+1)+1,1),"")&IFERROR(MID(TBLDATAMITRAEPC[[#This Row],[NAMA MITRA]],FIND(" ",TBLDATAMITRAEPC[[#This Row],[NAMA MITRA]],FIND(" ",TBLDATAMITRAEPC[[#This Row],[NAMA MITRA]],FIND(" ",TBLDATAMITRAEPC[[#This Row],[NAMA MITRA]],FIND(" ",TBLDATAMITRAEPC[[#This Row],[NAMA MITRA]],1)+1)+1)+1)+1,1),"") -> D | B9: DENI | C9: NURUL HIDAYATU SAMSIAH
A10: =LEFT(TBLDATAMITRAEPC[[#This Row],[NAMA MITRA]],1)&IFERROR(MID(TBLDATAMITRAEPC[[#This Row],[NAMA MITRA]],FIND(" ",TBLDATAMITRAEPC[[#This Row],[NAMA MITRA]],1)+1,1),"")&IFERROR(MID(TBLDATAMITRAEPC[[#This Row],[NAMA MITRA]],FIND(" ",TBLDATAMITRAEPC[[#This Row],[NAMA MITRA]],FIND(" ",TBLDATAMITRAEPC[[#This Row],[NAMA MITRA]],1)+1)+1,1),"")&IFERROR(MID(TBLDATAMITRAEPC[[#This Row],[NAMA MITRA]],FIND(" ",TBLDATAMITRAEPC[[#This Row],[NAMA MITRA]],FIND(" ",TBLDATAMITRAEPC[[#This Row],[NAMA MITRA]],FIND(" ",TBLDATAMITRAEPC[[#This Row],[NAMA MITRA]],1)+1)+1)+1,1),"")&IFERROR(MID(TBLDATAMITRAEPC[[#This Row],[NAMA MITRA]],FIND(" ",TBLDATAMITRAEPC[[#This Row],[NAMA MITRA]],FIND(" ",TBLDATAMITRAEPC[[#This Row],[NAMA MITRA]],FIND(" ",TBLDATAMITRAEPC[[#This Row],[NAMA MITRA]],FIND(" ",TBLDATAMITRAEPC[[#This Row],[NAMA MITRA]],1)+1)+1)+1)+1,1),"") -> DZ | B10: DEWI ZAKIYAH | C10: NURUL HIDAYATU SAMSIAH
A11: =LEFT(TBLDATAMITRAEPC[[#This Row],[NAMA MITRA]],1)&IFERROR(MID(TBLDATAMITRAEPC[[#This Row],[NAMA MITRA]],FIND(" ",TBLDATAMITRAEPC[[#This Row],[NAMA MITRA]],1)+1,1),"")&IFERROR(MID(TBLDATAMITRAEPC[[#This Row],[NAMA MITRA]],FIND(" ",TBLDATAMITRAEPC[[#This Row],[NAMA MITRA]],FIND(" ",TBLDATAMITRAEPC[[#This Row],[NAMA MITRA]],1)+1)+1,1),"")&IFERROR(MID(TBLDATAMITRAEPC[[#This Row],[NAMA MITRA]],FIND(" ",TBLDATAMITRAEPC[[#This Row],[NAMA MITRA]],FIND(" ",TBLDATAMITRAEPC[[#This Row],[NAMA MITRA]],FIND(" ",TBLDATAMITRAEPC[[#This Row],[NAMA MITRA]],1)+1)+1)+1,1),"")&IFERROR(MID(TBLDATAMITRAEPC[[#This Row],[NAMA MITRA]],FIND(" ",TBLDATAMITRAEPC[[#This Row],[NAMA MITRA]],FIND(" ",TBLDATAMITRAEPC[[#This Row],[NAMA MITRA]],FIND(" ",TBLDATAMITRAEPC[[#This Row],[NAMA MITRA]],FIND(" ",TBLDATAMITRAEPC[[#This Row],[NAMA MITRA]],1)+1)+1)+1)+1,1),"") -> G | B11: GALIH | C11: NURUL HIDAYATU SAMSIAH
A12: =LEFT(TBLDATAMITRAEPC[[#This Row],[NAMA MITRA]],1)&IFERROR(MID(TBLDATAMITRAEPC[[#This Row],[NAMA MITRA]],FIND(" ",TBLDATAMITRAEPC[[#This Row],[NAMA MITRA]],1)+1,1),"")&IFERROR(MID(TBLDATAMITRAEPC[[#This Row],[NAMA MITRA]],FIND(" ",TBLDATAMITRAEPC[[#This Row],[NAMA MITRA]],FIND(" ",TBLDATAMITRAEPC[[#This Row],[NAMA MITRA]],1)+1)+1,1),"")&IFERROR(MID(TBLDATAMITRAEPC[[#This Row],[NAMA MITRA]],FIND(" ",TBLDATAMITRAEPC[[#This Row],[NAMA MITRA]],FIND(" ",TBLDATAMITRAEPC[[#This Row],[NAMA MITRA]],FIND(" ",TBLDATAMITRAEPC[[#This Row],[NAMA MITRA]],1)+1)+1)+1,1),"")&IFERROR(MID(TBLDATAMITRAEPC[[#This Row],[NAMA MITRA]],FIND(" ",TBLDATAMITRAEPC[[#This Row],[NAMA MITRA]],FIND(" ",TBLDATAMITRAEPC[[#This Row],[NAMA MITRA]],FIND(" ",TBLDATAMITRAEPC[[#This Row],[NAMA MITRA]],FIND(" ",TBLDATAMITRAEPC[[#This Row],[NAMA MITRA]],1)+1)+1)+1)+1,1),"") -> H | B12: HANI | C12: NURUL HIDAYATU SAMSIAH
A13: =LEFT(TBLDATAMITRAEPC[[#This Row],[NAMA MITRA]],1)&IFERROR(MID(TBLDATAMITRAEPC[[#This Row],[NAMA MITRA]],FIND(" ",TBLDATAMITRAEPC[[#This Row],[NAMA MITRA]],1)+1,1),"")&IFERROR(MID(TBLDATAMITRAEPC[[#This Row],[NAMA MITRA]],FIND(" ",TBLDATAMITRAEPC[[#This Row],[NAMA MITRA]],FIND(" ",TBLDATAMITRAEPC[[#This Row],[NAMA MITRA]],1)+1)+1,1),"")&IFERROR(MID(TBLDATAMITRAEPC[[#This Row],[NAMA MITRA]],FIND(" ",TBLDATAMITRAEPC[[#This Row],[NAMA MITRA]],FIND(" ",TBLDATAMITRAEPC[[#This Row],[NAMA MITRA]],FIND(" ",TBLDATAMITRAEPC[[#This Row],[NAMA MITRA]],1)+1)+1)+1,1),"")&IFERROR(MID(TBLDATAMITRAEPC[[#This Row],[NAMA MITRA]],FIND(" ",TBLDATAMITRAEPC[[#This Row],[NAMA MITRA]],FIND(" ",TBLDATAMITRAEPC[[#This Row],[NAMA MITRA]],FIND(" ",TBLDATAMITRAEPC[[#This Row],[NAMA MITRA]],FIND(" ",TBLDATAMITRAEPC[[#This Row],[NAMA MITRA]],1)+1)+1)+1)+1,1),"") -> IS | B13: IIS SUGIARTI | C13: NURUL HIDAYATU SAMSIAH
A14: =LEFT(TBLDATAMITRAEPC[[#This Row],[NAMA MITRA]],1)&IFERROR(MID(TBLDATAMITRAEPC[[#This Row],[NAMA MITRA]],FIND(" ",TBLDATAMITRAEPC[[#This Row],[NAMA MITRA]],1)+1,1),"")&IFERROR(MID(TBLDATAMITRAEPC[[#This Row],[NAMA MITRA]],FIND(" ",TBLDATAMITRAEPC[[#This Row],[NAMA MITRA]],FIND(" ",TBLDATAMITRAEPC[[#This Row],[NAMA MITRA]],1)+1)+1,1),"")&IFERROR(MID(TBLDATAMITRAEPC[[#This Row],[NAMA MITRA]],FIND(" ",TBLDATAMITRAEPC[[#This Row],[NAMA MITRA]],FIND(" ",TBLDATAMITRAEPC[[#This Row],[NAMA MITRA]],FIND(" ",TBLDATAMITRAEPC[[#This Row],[NAMA MITRA]],1)+1)+1)+1,1),"")&IFERROR(MID(TBLDATAMITRAEPC[[#This Row],[NAMA MITRA]],FIND(" ",TBLDATAMITRAEPC[[#This Row],[NAMA MITRA]],FIND(" ",TBLDATAMITRAEPC[[#This Row],[NAMA MITRA]],FIND(" ",TBLDATAMITRAEPC[[#This Row],[NAMA MITRA]],FIND(" ",TBLDATAMITRAEPC[[#This Row],[NAMA MITRA]],1)+1)+1)+1)+1,1),"") -> I | B14: INTAN | C14: DENI
A15: =LEFT(TBLDATAMITRAEPC[[#This Row],[NAMA MITRA]],1)&IFERROR(MID(TBLDATAMITRAEPC[[#This Row],[NAMA MITRA]],FIND(" ",TBLDATAMITRAEPC[[#This Row],[NAMA MITRA]],1)+1,1),"")&IFERROR(MID(TBLDATAMITRAEPC[[#This Row],[NAMA MITRA]],FIND(" ",TBLDATAMITRAEPC[[#This Row],[NAMA MITRA]],FIND(" ",TBLDATAMITRAEPC[[#This Row],[NAMA MITRA]],1)+1)+1,1),"")&IFERROR(MID(TBLDATAMITRAEPC[[#This Row],[NAMA MITRA]],FIND(" ",TBLDATAMITRAEPC[[#This Row],[NAMA MITRA]],FIND(" ",TBLDATAMITRAEPC[[#This Row],[NAMA MITRA]],FIND(" ",TBLDATAMITRAEPC[[#This Row],[NAMA MITRA]],1)+1)+1)+1,1),"")&IFERROR(MID(TBLDATAMITRAEPC[[#This Row],[NAMA MITRA]],FIND(" ",TBLDATAMITRAEPC[[#This Row],[NAMA MITRA]],FIND(" ",TBLDATAMITRAEPC[[#This Row],[NAMA MITRA]],FIND(" ",TBLDATAMITRAEPC[[#This Row],[NAMA MITRA]],FIND(" ",TBLDATAMITRAEPC[[#This Row],[NAMA MITRA]],1)+1)+1)+1)+1,1),"") -> IF | B15: ISA FEFEN | C15: NURUL HIDAYATU SAMSIAH
A16: =LEFT(TBLDATAMITRAEPC[[#This Row],[NAMA MITRA]],1)&IFERROR(MID(TBLDATAMITRAEPC[[#This Row],[NAMA MITRA]],FIND(" ",TBLDATAMITRAEPC[[#This Row],[NAMA MITRA]],1)+1,1),"")&IFERROR(MID(TBLDATAMITRAEPC[[#This Row],[NAMA MITRA]],FIND(" ",TBLDATAMITRAEPC[[#This Row],[NAMA MITRA]],FIND(" ",TBLDATAMITRAEPC[[#This Row],[NAMA MITRA]],1)+1)+1,1),"")&IFERROR(MID(TBLDATAMITRAEPC[[#This Row],[NAMA MITRA]],FIND(" ",TBLDATAMITRAEPC[[#This Row],[NAMA MITRA]],FIND(" ",TBLDATAMITRAEPC[[#This Row],[NAMA MITRA]],FIND(" ",TBLDATAMITRAEPC[[#This Row],[NAMA MITRA]],1)+1)+1)+1,1),"")&IFERROR(MID(TBLDATAMITRAEPC[[#This Row],[NAMA MITRA]],FIND(" ",TBLDATAMITRAEPC[[#This Row],[NAMA MITRA]],FIND(" ",TBLDATAMITRAEPC[[#This Row],[NAMA MITRA]],FIND(" ",TBLDATAMITRAEPC[[#This Row],[NAMA MITRA]],FIND(" ",TBLDATAMITRAEPC[[#This Row],[NAMA MITRA]],1)+1)+1)+1)+1,1),"") -> KC | B16: KEDAI CERIA | C16: NURUL HIDAYATU SAMSIAH
... A19: =LEFT(TBLDATAMITRAEPC[[#This Row],[NAMA MITRA]],1)&IFERROR(MID(TBLDATAMITRAEPC[[#This Row],[NAMA MITRA]],FIND(" ",TBLDATAMITRAEPC[[#This Row],[NAMA MITRA]],1)+1,1),"")&IFERROR(MID(TBLDATAMITRAEPC[[#This Row],[NAMA MITRA]],FIND(" ",TBLDATAMITRAEPC[[#This Row],[NAMA MITRA]],FIND(" ",TBLDATAMITRAEPC[[#This Row],[NAMA MITRA]],1)+1)+1,1),"")&IFERROR(MID(TBLDATAMITRAEPC[[#This Row],[NAMA MITRA]],FIND(" ",TBLDATAMITRAEPC[[#This Row],[NAMA MITRA]],FIND(" ",TBLDATAMITRAEPC[[#This Row],[NAMA MITRA]],FIND(" ",TBLDATAMITRAEPC[[#This Row],[NAMA MITRA]],1)+1)+1)+1,1),"")&IFERROR(MID(TBLDATAMITRAEPC[[#This Row],[NAMA MITRA]],FIND(" ",TBLDATAMITRAEPC[[#This Row],[NAMA MITRA]],FIND(" ",TBLDATAMITRAEPC[[#This Row],[NAMA MITRA]],FIND(" ",TBLDATAMITRAEPC[[#This Row],[NAMA MITRA]],FIND(" ",TBLDATAMITRAEPC[[#This Row],[NAMA MITRA]],1)+1)+1)+1)+1,1),"") -> NP | B19: NUR PANTI | C19: NURUL HIDAYATU SAMSIAH
A20: =LEFT(TBLDATAMITRAEPC[[#This Row],[NAMA MITRA]],1)&IFERROR(MID(TBLDATAMITRAEPC[[#This Row],[NAMA MITRA]],FIND(" ",TBLDATAMITRAEPC[[#This Row],[NAMA MITRA]],1)+1,1),"")&IFERROR(MID(TBLDATAMITRAEPC[[#This Row],[NAMA MITRA]],FIND(" ",TBLDATAMITRAEPC[[#This Row],[NAMA MITRA]],FIND(" ",TBLDATAMITRAEPC[[#This Row],[NAMA MITRA]],1)+1)+1,1),"")&IFERROR(MID(TBLDATAMITRAEPC[[#This Row],[NAMA MITRA]],FIND(" ",TBLDATAMITRAEPC[[#This Row],[NAMA MITRA]],FIND(" ",TBLDATAMITRAEPC[[#This Row],[NAMA MITRA]],FIND(" ",TBLDATAMITRAEPC[[#This Row],[NAMA MITRA]],1)+1)+1)+1,1),"")&IFERROR(MID(TBLDATAMITRAEPC[[#This Row],[NAMA MITRA]],FIND(" ",TBLDATAMITRAEPC[[#This Row],[NAMA MITRA]],FIND(" ",TBLDATAMITRAEPC[[#This Row],[NAMA MITRA]],FIND(" ",TBLDATAMITRAEPC[[#This Row],[NAMA MITRA]],FIND(" ",TBLDATAMITRAEPC[[#This Row],[NAMA MITRA]],1)+1)+1)+1)+1,1),"") -> NHS | B20: NURUL HIDAYATU SAMSIAH | C20: NURUL HIDAYATU SAMSIAH | D20: 085746323192
A21: =LEFT(TBLDATAMITRAEPC[[#This Row],[NAMA MITRA]],1)&IFERROR(MID(TBLDATAMITRAEPC[[#This Row],[NAMA MITRA]],FIND(" ",TBLDATAMITRAEPC[[#This Row],[NAMA MITRA]],1)+1,1),"")&IFERROR(MID(TBLDATAMITRAEPC[[#This Row],[NAMA MITRA]],FIND(" ",TBLDATAMITRAEPC[[#This Row],[NAMA MITRA]],FIND(" ",TBLDATAMITRAEPC[[#This Row],[NAMA MITRA]],1)+1)+1,1),"")&IFERROR(MID(TBLDATAMITRAEPC[[#This Row],[NAMA MITRA]],FIND(" ",TBLDATAMITRAEPC[[#This Row],[NAMA MITRA]],FIND(" ",TBLDATAMITRAEPC[[#This Row],[NAMA MITRA]],FIND(" ",TBLDATAMITRAEPC[[#This Row],[NAMA MITRA]],1)+1)+1)+1,1),"")&IFERROR(MID(TBLDATAMITRAEPC[[#This Row],[NAMA MITRA]],FIND(" ",TBLDATAMITRAEPC[[#This Row],[NAMA MITRA]],FIND(" ",TBLDATAMITRAEPC[[#This Row],[NAMA MITRA]],FIND(" ",TBLDATAMITRAEPC[[#This Row],[NAMA MITRA]],FIND(" ",TBLDATAMITRAEPC[[#This Row],[NAMA MITRA]],1)+1)+1)+1)+1,1),"") -> Q | B21: QEQEL | C21: NURUL HIDAYATU SAMSIAH
A22: =LEFT(TBLDATAMITRAEPC[[#This Row],[NAMA MITRA]],1)&IFERROR(MID(TBLDATAMITRAEPC[[#This Row],[NAMA MITRA]],FIND(" ",TBLDATAMITRAEPC[[#This Row],[NAMA MITRA]],1)+1,1),"")&IFERROR(MID(TBLDATAMITRAEPC[[#This Row],[NAMA MITRA]],FIND(" ",TBLDATAMITRAEPC[[#This Row],[NAMA MITRA]],FIND(" ",TBLDATAMITRAEPC[[#This Row],[NAMA MITRA]],1)+1)+1,1),"")&IFERROR(MID(TBLDATAMITRAEPC[[#This Row],[NAMA MITRA]],FIND(" ",TBLDATAMITRAEPC[[#This Row],[NAMA MITRA]],FIND(" ",TBLDATAMITRAEPC[[#This Row],[NAMA MITRA]],FIND(" ",TBLDATAMITRAEPC[[#This Row],[NAMA MITRA]],1)+1)+1)+1,1),"")&IFERROR(MID(TBLDATAMITRAEPC[[#This Row],[NAMA MITRA]],FIND(" ",TBLDATAMITRAEPC[[#This Row],[NAMA MITRA]],FIND(" ",TBLDATAMITRAEPC[[#This Row],[NAMA MITRA]],FIND(" ",TBLDATAMITRAEPC[[#This Row],[NAMA MITRA]],FIND(" ",TBLDATAMITRAEPC[[#This Row],[NAMA MITRA]],1)+1)+1)+1)+1,1),"") -> RDA | B22: RENI DWI ANGGRAINI | C22: NURUL HIDAYATU SAMSIAH
A23: =LEFT(TBLDATAMITRAEPC[[#This Row],[NAMA MITRA]],1)&IFERROR(MID(TBLDATAMITRAEPC[[#This Row],[NAMA MITRA]],FIND(" ",TBLDATAMITRAEPC[[#This Row],[NAMA MITRA]],1)+1,1),"")&IFERROR(MID(TBLDATAMITRAEPC[[#This Row],[NAMA MITRA]],FIND(" ",TBLDATAMITRAEPC[[#This Row],[NAMA MITRA]],FIND(" ",TBLDATAMITRAEPC[[#This Row],[NAMA MITRA]],1)+1)+1,1),"")&IFERROR(MID(TBLDATAMITRAEPC[[#This Row],[NAMA MITRA]],FIND(" ",TBLDATAMITRAEPC[[#This Row],[NAMA MITRA]],FIND(" ",TBLDATAMITRAEPC[[#This Row],[NAMA MITRA]],FIND(" ",TBLDATAMITRAEPC[[#This Row],[NAMA MITRA]],1)+1)+1)+1,1),"")&IFERROR(MID(TBLDATAMITRAEPC[[#This Row],[NAMA MITRA]],FIND(" ",TBLDATAMITRAEPC[[#This Row],[NAMA MITRA]],FIND(" ",TBLDATAMITRAEPC[[#This Row],[NAMA MITRA]],FIND(" ",TBLDATAMITRAEPC[[#This Row],[NAMA MITRA]],FIND(" ",TBLDATAMITRAEPC[[#This Row],[NAMA MITRA]],1)+1)+1)+1)+1,1),"") -> R | B23: RIA | C23: NURUL HIDAYATU SAMSIAH
A24: =LEFT(TBLDATAMITRAEPC[[#This Row],[NAMA MITRA]],1)&IFERROR(MID(TBLDATAMITRAEPC[[#This Row],[NAMA MITRA]],FIND(" ",TBLDATAMITRAEPC[[#This Row],[NAMA MITRA]],1)+1,1),"")&IFERROR(MID(TBLDATAMITRAEPC[[#This Row],[NAMA MITRA]],FIND(" ",TBLDATAMITRAEPC[[#This Row],[NAMA MITRA]],FIND(" ",TBLDATAMITRAEPC[[#This Row],[NAMA MITRA]],1)+1)+1,1),"")&IFERROR(MID(TBLDATAMITRAEPC[[#This Row],[NAMA MITRA]],FIND(" ",TBLDATAMITRAEPC[[#This Row],[NAMA MITRA]],FIND(" ",TBLDATAMITRAEPC[[#This Row],[NAMA MITRA]],FIND(" ",TBLDATAMITRAEPC[[#This Row],[NAMA MITRA]],1)+1)+1)+1,1),"")&IFERROR(MID(TBLDATAMITRAEPC[[#This Row],[NAMA MITRA]],FIND(" ",TBLDATAMITRAEPC[[#This Row],[NAMA MITRA]],FIND(" ",TBLDATAMITRAEPC[[#This Row],[NAMA MITRA]],FIND(" ",TBLDATAMITRAEPC[[#This Row],[NAMA MITRA]],FIND(" ",TBLDATAMITRAEPC[[#This Row],[NAMA MITRA]],1)+1)+1)+1)+1,1),"") -> RD | B24: RINDA DWI | C24: NURUL HIDAYATU SAMSIAH
A25: =LEFT(TBLDATAMITRAEPC[[#This Row],[NAMA MITRA]],1)&IFERROR(MID(TBLDATAMITRAEPC[[#This Row],[NAMA MITRA]],FIND(" ",TBLDATAMITRAEPC[[#This Row],[NAMA MITRA]],1)+1,1),"")&IFERROR(MID(TBLDATAMITRAEPC[[#This Row],[NAMA MITRA]],FIND(" ",TBLDATAMITRAEPC[[#This Row],[NAMA MITRA]],FIND(" ",TBLDATAMITRAEPC[[#This Row],[NAMA MITRA]],1)+1)+1,1),"")&IFERROR(MID(TBLDATAMITRAEPC[[#This Row],[NAMA MITRA]],FIND(" ",TBLDATAMITRAEPC[[#This Row],[NAMA MITRA]],FIND(" ",TBLDATAMITRAEPC[[#This Row],[NAMA MITRA]],FIND(" ",TBLDATAMITRAEPC[[#This Row],[NAMA MITRA]],1)+1)+1)+1,1),"")&IFERROR(MID(TBLDATAMITRAEPC[[#This Row],[NAMA MITRA]],FIND(" ",TBLDATAMITRAEPC[[#This Row],[NAMA MITRA]],FIND(" ",TBLDATAMITRAEPC[[#This Row],[NAMA MITRA]],FIND(" ",TBLDATAMITRAEPC[[#This Row],[NAMA MITRA]],FIND(" ",TBLDATAMITRAEPC[[#This Row],[NAMA MITRA]],1)+1)+1)+1)+1,1),"") -> M | B25: MANDA | C25: NURUL HIDAYATU SAMSIAH
A26: =LEFT(TBLDATAMITRAEPC[[#This Row],[NAMA MITRA]],1)&IFERROR(MID(TBLDATAMITRAEPC[[#This Row],[NAMA MITRA]],FIND(" ",TBLDATAMITRAEPC[[#This Row],[NAMA MITRA]],1)+1,1),"")&IFERROR(MID(TBLDATAMITRAEPC[[#This Row],[NAMA MITRA]],FIND(" ",TBLDATAMITRAEPC[[#This Row],[NAMA MITRA]],FIND(" ",TBLDATAMITRAEPC[[#This Row],[NAMA MITRA]],1)+1)+1,1),"")&IFERROR(MID(TBLDATAMITRAEPC[[#This Row],[NAMA MITRA]],FIND(" ",TBLDATAMITRAEPC[[#This Row],[NAMA MITRA]],FIND(" ",TBLDATAMITRAEPC[[#This Row],[NAMA MITRA]],FIND(" ",TBLDATAMITRAEPC[[#This Row],[NAMA MITRA]],1)+1)+1)+1,1),"")&IFERROR(MID(TBLDATAMITRAEPC[[#This Row],[NAMA MITRA]],FIND(" ",TBLDATAMITRAEPC[[#This Row],[NAMA MITRA]],FIND(" ",TBLDATAMITRAEPC[[#This Row],[NAMA MITRA]],FIND(" ",TBLDATAMITRAEPC[[#This Row],[NAMA MITRA]],FIND(" ",TBLDATAMITRAEPC[[#This Row],[NAMA MITRA]],1)+1)+1)+1)+1,1),"") -> R | B26: RISTA | C26: NURUL HIDAYATU SAMSIAH
A27: =LEFT(TBLDATAMITRAEPC[[#This Row],[NAMA MITRA]],1)&IFERROR(MID(TBLDATAMITRAEPC[[#This Row],[NAMA MITRA]],FIND(" ",TBLDATAMITRAEPC[[#This Row],[NAMA MITRA]],1)+1,1),"")&IFERROR(MID(TBLDATAMITRAEPC[[#This Row],[NAMA MITRA]],FIND(" ",TBLDATAMITRAEPC[[#This Row],[NAMA MITRA]],FIND(" ",TBLDATAMITRAEPC[[#This Row],[NAMA MITRA]],1)+1)+1,1),"")&IFERROR(MID(TBLDATAMITRAEPC[[#This Row],[NAMA MITRA]],FIND(" ",TBLDATAMITRAEPC[[#This Row],[NAMA MITRA]],FIND(" ",TBLDATAMITRAEPC[[#This Row],[NAMA MITRA]],FIND(" ",TBLDATAMITRAEPC[[#This Row],[NAMA MITRA]],1)+1)+1)+1,1),"")&IFERROR(MID(TBLDATAMITRAEPC[[#This Row],[NAMA MITRA]],FIND(" ",TBLDATAMITRAEPC[[#This Row],[NAMA MITRA]],FIND(" ",TBLDATAMITRAEPC[[#This Row],[NAMA MITRA]],FIND(" ",TBLDATAMITRAEPC[[#This Row],[NAMA MITRA]],FIND(" ",TBLDATAMITRAEPC[[#This Row],[NAMA MITRA]],1)+1)+1)+1)+1,1),"") -> R | B27: ROIK | C27: NURUL HIDAYATU SAMSIAH
A28: =LEFT(TBLDATAMITRAEPC[[#This Row],[NAMA MITRA]],1)&IFERROR(MID(TBLDATAMITRAEPC[[#This Row],[NAMA MITRA]],FIND(" ",TBLDATAMITRAEPC[[#This Row],[NAMA MITRA]],1)+1,1),"")&IFERROR(MID(TBLDATAMITRAEPC[[#This Row],[NAMA MITRA]],FIND(" ",TBLDATAMITRAEPC[[#This Row],[NAMA MITRA]],FIND(" ",TBLDATAMITRAEPC[[#This Row],[NAMA MITRA]],1)+1)+1,1),"")&IFERROR(MID(TBLDATAMITRAEPC[[#This Row],[NAMA MITRA]],FIND(" ",TBLDATAMITRAEPC[[#This Row],[NAMA MITRA]],FIND(" ",TBLDATAMITRAEPC[[#This Row],[NAMA MITRA]],FIND(" ",TBLDATAMITRAEPC[[#This Row],[NAMA MITRA]],1)+1)+1)+1,1),"")&IFERROR(MID(TBLDATAMITRAEPC[[#This Row],[NAMA MITRA]],FIND(" ",TBLDATAMITRAEPC[[#This Row],[NAMA MITRA]],FIND(" ",TBLDATAMITRAEPC[[#This Row],[NAMA MITRA]],FIND(" ",TBLDATAMITRAEPC[[#This Row],[NAMA MITRA]],FIND(" ",TBLDATAMITRAEPC[[#This Row],[NAMA MITRA]],1)+1)+1)+1)+1,1),"") -> UDL | B28: ULFA DWI LESTARI | C28: NURUL HIDAYATU SAMSIAH
A29: =LEFT(TBLDATAMITRAEPC[[#This Row],[NAMA MITRA]],1)&IFERROR(MID(TBLDATAMITRAEPC[[#This Row],[NAMA MITRA]],FIND(" ",TBLDATAMITRAEPC[[#This Row],[NAMA MITRA]],1)+1,1),"")&IFERROR(MID(TBLDATAMITRAEPC[[#This Row],[NAMA MITRA]],FIND(" ",TBLDATAMITRAEPC[[#This Row],[NAMA MITRA]],FIND(" ",TBLDATAMITRAEPC[[#This Row],[NAMA MITRA]],1)+1)+1,1),"")&IFERROR(MID(TBLDATAMITRAEPC[[#This Row],[NAMA MITRA]],FIND(" ",TBLDATAMITRAEPC[[#This Row],[NAMA MITRA]],FIND(" ",TBLDATAMITRAEPC[[#This Row],[NAMA MITRA]],FIND(" ",TBLDATAMITRAEPC[[#This Row],[NAMA MITRA]],1)+1)+1)+1,1),"")&IFERROR(MID(TBLDATAMITRAEPC[[#This Row],[NAMA MITRA]],FIND(" ",TBLDATAMITRAEPC[[#This Row],[NAMA MITRA]],FIND(" ",TBLDATAMITRAEPC[[#This Row],[NAMA MITRA]],FIND(" ",TBLDATAMITRAEPC[[#This Row],[NAMA MITRA]],FIND(" ",TBLDATAMITRAEPC[[#This Row],[NAMA MITRA]],1)+1)+1)+1)+1,1),"") -> V | B29: VEBRI | C29: NURUL HIDAYATU SAMSIAH
A30: =LEFT(TBLDATAMITRAEPC[[#This Row],[NAMA MITRA]],1)&IFERROR(MID(TBLDATAMITRAEPC[[#This Row],[NAMA MITRA]],FIND(" ",TBLDATAMITRAEPC[[#This Row],[NAMA MITRA]],1)+1,1),"")&IFERROR(MID(TBLDATAMITRAEPC[[#This Row],[NAMA MITRA]],FIND(" ",TBLDATAMITRAEPC[[#This Row],[NAMA MITRA]],FIND(" ",TBLDATAMITRAEPC[[#This Row],[NAMA MITRA]],1)+1)+1,1),"")&IFERROR(MID(TBLDATAMITRAEPC[[#This Row],[NAMA MITRA]],FIND(" ",TBLDATAMITRAEPC[[#This Row],[NAMA MITRA]],FIND(" ",TBLDATAMITRAEPC[[#This Row],[NAMA MITRA]],FIND(" ",TBLDATAMITRAEPC[[#This Row],[NAMA MITRA]],1)+1)+1)+1,1),"")&IFERROR(MID(TBLDATAMITRAEPC[[#This Row],[NAMA MITRA]],FIND(" ",TBLDATAMITRAEPC[[#This Row],[NAMA MITRA]],FIND(" ",TBLDATAMITRAEPC[[#This Row],[NAMA MITRA]],FIND(" ",TBLDATAMITRAEPC[[#This Row],[NAMA MITRA]],FIND(" ",TBLDATAMITRAEPC[[#This Row],[NAMA MITRA]],1)+1)+1)+1)+1,1),"") -> V | B30: VITA | C30: NURUL HIDAYATU SAMSIAH
B32: LEFT([@[NAMA RESELLER]];1)
B33: IFERROR(MID([@[NAMA RESELLER]];FIND(" ";[@[NAMA RESELLER]];1)+1;1);"")
B34: IFERROR(MID([@[NAMA RESELLER]];FIND(" ";[@[NAMA RESELLER]];FIND(" ";[@[NAMA RESELLER]];1)+1)+1;1);"")
B35: IFERROR(MID([@[NAMA RESELLER]];FIND(" ";[@[NAMA RESELLER]];FIND(" ";[@[NAMA RESELLER]];FIND(" ";[@[NAMA RESELLER]];1)+1)+1)+1;1);"")
B36: IFERROR(MID([@[NAMA RESELLER]];FIND(" ";[@[NAMA RESELLER]];FIND(" ";[@[NAMA RESELLER]];FIND(" ";[@[NAMA RESELLER]];FIND(" ";[@[NAMA RESELLER]];1)+1)+1)+1)+1;1);"")

Sheet DATA CUSTOMER
A3: NAMA CUSTOMER | B3: NO HP | C3: ALAMAT KIRIM | D3: NAMA MITRA | E3: NAMA PEREKRUT
A4: ABIDZAR | C4: RAMBIPUJI | D4: CAHYA GALLERY | E4: NURUL HIDAYATU SAMSIAH
A5: ABIL | C5: LOJEJER | D5: DANI | E5: NURUL HIDAYATU SAMSIAH
A6: ADE | C6: AJUNG | D6: NURUL HIDAYATU SAMSIAH | E6: NURUL HIDAYATU SAMSIAH
A7: ADE CG | C7: AJUNG | D7: CAHYA GALLERY | E7: NURUL HIDAYATU SAMSIAH
A8: ADEL | C8: PANTI | D8: NURUL HIDAYATU SAMSIAH | E8: NURUL HIDAYATU SAMSIAH
A9: ADEL CG | C9: PANTI | D9: CAHYA GALLERY | E9: NURUL HIDAYATU SAMSIAH
A10: ADIF CG | C10: SATREAN | D10: CAHYA GALLERY | E10: NURUL HIDAYATU SAMSIAH
A11: ADMIN | C11: SEJATI | D11: NURUL HIDAYATU SAMSIAH | E11: NURUL HIDAYATU SAMSIAH
A12: ADMIN CG | C12: SEJATI | D12: CAHYA GALLERY | E12: NURUL HIDAYATU SAMSIAH
A13: AFFAN | C13: PANTI | D13: NURUL HIDAYATU SAMSIAH | E13: NURUL HIDAYATU SAMSIAH
A14: AFFAN CG | C14: PANTI | D14: CAHYA GALLERY | E14: NURUL HIDAYATU SAMSIAH
A15: AGUNG | C15: PANTI | D15: DENI | E15: NURUL HIDAYATU SAMSIAH
... A50: BU URIP ANI | C50: TALANGSARI | D50: ANI | E50: NURUL HIDAYATU SAMSIAH
A51: BU ZULIATI | D51: NURUL HIDAYATU SAMSIAH | E51: NURUL HIDAYATU SAMSIAH
A52: CAHYO CG | C52: AJUNG | D52: CAHYA GALLERY | E52: NURUL HIDAYATU SAMSIAH
A53: CG | C53: PANTI | D53: CAHYA GALLERY | E53: NURUL HIDAYATU SAMSIAH
A54: CICI CG | C54: PETUNG | D54: CAHYA GALLERY | E54: NURUL HIDAYATU SAMSIAH
A55: CIK EN WA | C55: SEJATI | D55: NURUL HIDAYATU SAMSIAH | E55: NURUL HIDAYATU SAMSIAH
A56: CIK EN WA CG | C56: SEJATI | D56: CAHYA GALLERY | E56: NURUL HIDAYATU SAMSIAH
A57: CINDY CG | C57: PANTI | D57: CAHYA GALLERY | E57: NURUL HIDAYATU SAMSIAH
A58: CINDY NUR | C58: PANTI | D58: NUR PANTI | E58: NURUL HIDAYATU SAMSIAH
A59: DENI | C59: PANTI | D59: DENI | E59: NURUL HIDAYATU SAMSIAH
A60: DEWI | C60: PANTI | D60: DENI | E60: NURUL HIDAYATU SAMSIAH
A61: DEWI ZAKIYAH | C61: BANGSAL | D61: DEWI ZAKIYAH | E61: NURUL HIDAYATU SAMSIAH
A62: DEWI ZAKIYAH NURUL | C62: BANGSAL | D62: NURUL HIDAYATU SAMSIAH | E62: NURUL HIDAYATU SAMSIAH
A63: DIDIN | C63: GELUNDENGAN | D63: NURUL HIDAYATU SAMSIAH | E63: NURUL HIDAYATU SAMSIAH
... A230: ZULAIKHA CG | C230: PERUMNAS PANTI | D230: CAHYA GALLERY | E230: NURUL HIDAYATU SAMSIAH

Sheet KATALOG
B3: NAMA PRODUK | C3: MODAL KEMBALI KE PERUSAHAAN PRODUK OFF LINE | D3: BUDGET KOMISI RESELLER | E3: MODAL SETELAH DITAMBAH BUDGET KOMISI | F3: HARGA JUAL | G3: SELISIH/LABA BERSIH TOKO | H3: LABA MITRA 5 % | I3: LABA KIRIM 5 % | J3: LABA BERSIH
B4: BURGER MEDIUM DAGING SAPI | C4: =VLOOKUP(TBLKATALOG[[#This Row],[NAMA PRODUK]],[4]!TBLMODAL[[NAMA MENU]:[MODAL KEMBALI KE PERUSAHAAN PRODUK OFF LINE]],2,FALSE) -> 11837.889 | D4: =SUM(TBLKATALOG[[#This Row],[LABA MITRA 5 %]:[LABA KIRIM 5 %]]) -> 1183.7889 | E4: =C4+D4 -> 13021.678 | F4: 15000 | G4: =F4-E4 -> 1978.3222 | H4: =0.05*C4 -> 591.89444 | I4: =0.05*C4 -> 591.89444 | J4: =TBLKATALOG[[#This Row],[HARGA JUAL]]-TBLKATALOG[[#This Row],[MODAL SETELAH DITAMBAH BUDGET KOMISI]] -> 1978.3222
B5: BURGER MEDIUM DAGING SAPI DOUBLE BEEF | C5: =VLOOKUP(TBLKATALOG[[#This Row],[NAMA PRODUK]],[4]!TBLMODAL[[NAMA MENU]:[MODAL KEMBALI KE PERUSAHAAN PRODUK OFF LINE]],2,FALSE) -> 15662.889 | D5: =SUM(TBLKATALOG[[#This Row],[LABA MITRA 5 %]:[LABA KIRIM 5 %]]) -> 1566.2889 | E5: =C5+D5 -> 17229.178 | F5: 20000 | G5: =F5-E5 -> 2770.8222 | H5: =0.05*C5 -> 783.14444 | I5: =0.05*C5 -> 783.14444 | J5: =TBLKATALOG[[#This Row],[HARGA JUAL]]-TBLKATALOG[[#This Row],[MODAL SETELAH DITAMBAH BUDGET KOMISI]] -> 2770.8222
B6: BURGER MEDIUM DAGING SAPI TANPA SAYUR | C6: =VLOOKUP(TBLKATALOG[[#This Row],[NAMA PRODUK]],[4]!TBLMODAL[[NAMA MENU]:[MODAL KEMBALI KE PERUSAHAAN PRODUK OFF LINE]],2,FALSE) -> 11049 | D6: =SUM(TBLKATALOG[[#This Row],[LABA MITRA 5 %]:[LABA KIRIM 5 %]]) -> 1104.9 | E6: =C6+D6 -> 12153.9 | F6: 15000 | G6: =F6-E6 -> 2846.1 | H6: =0.05*C6 -> 552.45 | I6: =0.05*C6 -> 552.45 | J6: =TBLKATALOG[[#This Row],[HARGA JUAL]]-TBLKATALOG[[#This Row],[MODAL SETELAH DITAMBAH BUDGET KOMISI]] -> 2846.1
B7: BURGER MEDIUM NUGGET AYAM | C7: =VLOOKUP(TBLKATALOG[[#This Row],[NAMA PRODUK]],[4]!TBLMODAL[[NAMA MENU]:[MODAL KEMBALI KE PERUSAHAAN PRODUK OFF LINE]],2,FALSE) -> 11679.556 | D7: =SUM(TBLKATALOG[[#This Row],[LABA MITRA 5 %]:[LABA KIRIM 5 %]]) -> 1167.9556 | E7: =C7+D7 -> 12847.511 | F7: 15000 | G7: =F7-E7 -> 2152.4889 | H7: =0.05*C7 -> 583.97778 | I7: =0.05*C7 -> 583.97778 | J7: =TBLKATALOG[[#This Row],[HARGA JUAL]]-TBLKATALOG[[#This Row],[MODAL SETELAH DITAMBAH BUDGET KOMISI]] -> 2152.4889
B8: BURGER MEDIUM NUGGET AYAM TANPA SAYUR | C8: =VLOOKUP(TBLKATALOG[[#This Row],[NAMA PRODUK]],[4]!TBLMODAL[[NAMA MENU]:[MODAL KEMBALI KE PERUSAHAAN PRODUK OFF LINE]],2,FALSE) -> 12224 | D8: =SUM(TBLKATALOG[[#This Row],[LABA MITRA 5 %]:[LABA KIRIM 5 %]]) -> 1222.4 | E8: =C8+D8 -> 13446.4 | F8: 15000 | G8: =F8-E8 -> 1553.6 | H8: =0.05*C8 -> 611.2 | I8: =0.05*C8 -> 611.2 | J8: =TBLKATALOG[[#This Row],[HARGA JUAL]]-TBLKATALOG[[#This Row],[MODAL SETELAH DITAMBAH BUDGET KOMISI]] -> 1553.6
B9: KEBAB AYAM (KECIL) | C9: =VLOOKUP(TBLKATALOG[[#This Row],[NAMA PRODUK]],[4]!TBLMODAL[[NAMA MENU]:[MODAL KEMBALI KE PERUSAHAAN PRODUK OFF LINE]],2,FALSE) -> 6711.6667 | D9: =SUM(TBLKATALOG[[#This Row],[LABA MITRA 5 %]:[LABA KIRIM 5 %]]) -> 671.16667 | E9: =C9+D9 -> 7382.8333 | F9: 9000 | G9: =F9-E9 -> 1617.1667 | H9: =0.05*C9 -> 335.58333 | I9: =0.05*C9 -> 335.58333 | J9: =TBLKATALOG[[#This Row],[HARGA JUAL]]-TBLKATALOG[[#This Row],[MODAL SETELAH DITAMBAH BUDGET KOMISI]] -> 1617.1667
B10: KEBAB AYAM (KECIL) PEDAS | C10: =VLOOKUP(TBLKATALOG[[#This Row],[NAMA PRODUK]],[4]!TBLMODAL[[NAMA MENU]:[MODAL KEMBALI KE PERUSAHAAN PRODUK OFF LINE]],2,FALSE) -> 7057.6667 | D10: =SUM(TBLKATALOG[[#This Row],[LABA MITRA 5 %]:[LABA KIRIM 5 %]]) -> 705.76667 | E10: =C10+D10 -> 7763.4333 | F10: 9000 | G10: =F10-E10 -> 1236.5667 | H10: =0.05*C10 -> 352.88333 | I10: =0.05*C10 -> 352.88333 | J10: =TBLKATALOG[[#This Row],[HARGA JUAL]]-TBLKATALOG[[#This Row],[MODAL SETELAH DITAMBAH BUDGET KOMISI]] -> 1236.5667
B11: KEBAB AYAM (KECIL) TANPA SAYUR | C11: =VLOOKUP(TBLKATALOG[[#This Row],[NAMA PRODUK]],[4]!TBLMODAL[[NAMA MENU]:[MODAL KEMBALI KE PERUSAHAAN PRODUK OFF LINE]],2,FALSE) -> 6074.1667 | D11: =SUM(TBLKATALOG[[#This Row],[LABA MITRA 5 %]:[LABA KIRIM 5 %]]) -> 607.41667 | E11: =C11+D11 -> 6681.5833 | F11: 9000 | G11: =F11-E11 -> 2318.4167 | H11: =0.05*C11 -> 303.70833 | I11: =0.05*C11 -> 303.70833 | J11: =TBLKATALOG[[#This Row],[HARGA JUAL]]-TBLKATALOG[[#This Row],[MODAL SETELAH DITAMBAH BUDGET KOMISI]] -> 2318.4167
B12: KEBAB AYAM (KECIL) TANPA SAYUR PEDAS | C12: =VLOOKUP(TBLKATALOG[[#This Row],[NAMA PRODUK]],[4]!TBLMODAL[[NAMA MENU]:[MODAL KEMBALI KE PERUSAHAAN PRODUK OFF LINE]],2,FALSE) -> 6420.1667 | D12: =SUM(TBLKATALOG[[#This Row],[LABA MITRA 5 %]:[LABA KIRIM 5 %]]) -> 642.01667 | E12: =C12+D12 -> 7062.1833 | F12: 9000 | G12: =F12-E12 -> 1937.8167 | H12: =0.05*C12 -> 321.00833 | I12: =0.05*C12 -> 321.00833 | J12: =TBLKATALOG[[#This Row],[HARGA JUAL]]-TBLKATALOG[[#This Row],[MODAL SETELAH DITAMBAH BUDGET KOMISI]] -> 1937.8167
B13: KEBAB AYAM + SOSIZ (KECIL) | C13: =VLOOKUP(TBLKATALOG[[#This Row],[NAMA PRODUK]],[4]!TBLMODAL[[NAMA MENU]:[MODAL KEMBALI KE PERUSAHAAN PRODUK OFF LINE]],2,FALSE) -> 6122.193 | D13: =SUM(TBLKATALOG[[#This Row],[LABA MITRA 5 %]:[LABA KIRIM 5 %]]) -> 612.2193 | E13: =C13+D13 -> 6734.4123 | F13: 9000 | G13: =F13-E13 -> 2265.5877 | H13: =0.05*C13 -> 306.10965 | I13: =0.05*C13 -> 306.10965 | J13: =TBLKATALOG[[#This Row],[HARGA JUAL]]-TBLKATALOG[[#This Row],[MODAL SETELAH DITAMBAH BUDGET KOMISI]] -> 2265.5877
B14: KEBAB AYAM + SOSIZ (KECIL) PEDAS | C14: =VLOOKUP(TBLKATALOG[[#This Row],[NAMA PRODUK]],[4]!TBLMODAL[[NAMA MENU]:[MODAL KEMBALI KE PERUSAHAAN PRODUK OFF LINE]],2,FALSE) -> 6192.193 | D14: =SUM(TBLKATALOG[[#This Row],[LABA MITRA 5 %]:[LABA KIRIM 5 %]]) -> 619.2193 | E14: =C14+D14 -> 6811.4123 | F14: 9000 | G14: =F14-E14 -> 2188.5877 | H14: =0.05*C14 -> 309.60965 | I14: =0.05*C14 -> 309.60965 | J14: =TBLKATALOG[[#This Row],[HARGA JUAL]]-TBLKATALOG[[#This Row],[MODAL SETELAH DITAMBAH BUDGET KOMISI]] -> 2188.5877
B15: KEBAB AYAM + SOSIZ (KECIL) TANPA SAYUR EKSTRA AYAM | C15: =VLOOKUP(TBLKATALOG[[#This Row],[NAMA PRODUK]],[4]!TBLMODAL[[NAMA MENU]:[MODAL KEMBALI KE PERUSAHAAN PRODUK OFF LINE]],2,FALSE) -> 5972.193 | D15: =SUM(TBLKATALOG[[#This Row],[LABA MITRA 5 %]:[LABA KIRIM 5 %]]) -> 597.2193 | E15: =C15+D15 -> 6569.4123 | F15: 9000 | G15: =F15-E15 -> 2430.5877 | H15: =0.05*C15 -> 298.60965 | I15: =0.05*C15 -> 298.60965 | J15: =TBLKATALOG[[#This Row],[HARGA JUAL]]-TBLKATALOG[[#This Row],[MODAL SETELAH DITAMBAH BUDGET KOMISI]] -> 2430.5877
... B68: ZAMBI 10 CM SOSIZ+AYAM | C68: =VLOOKUP(TBLKATALOG[[#This Row],[NAMA PRODUK]],[4]!TBLMODAL[[NAMA MENU]:[MODAL KEMBALI KE PERUSAHAAN PRODUK OFF LINE]],2,FALSE) -> 5951.9406 | D68: =SUM(TBLKATALOG[[#This Row],[LABA MITRA 5 %]:[LABA KIRIM 5 %]]) -> 595.19406 | E68: =C68+D68 -> 6547.1346 | F68: 8000 | G68: =F68-E68 -> 1452.8654 | H68: =0.05*C68 -> 297.59703 | I68: =0.05*C68 -> 297.59703 | J68: =TBLKATALOG[[#This Row],[HARGA JUAL]]-TBLKATALOG[[#This Row],[MODAL SETELAH DITAMBAH BUDGET KOMISI]] -> 1452.8654

Sheet REKAP BAHAN
A4: NAMA BAHAN | B4: MODAL | C4: ISI | D4: MODAL SATUAN | E4: STOK | F4: MASUK | G4: KELUAR | H4: SISA STOK | I4: NILAI SISA STOK
A5: SAOS TOMAT GRAM | B5: 20000 | C5: 1000 | D5: =TBLREKAPBAHAN[[#This Row],[MODAL]]/TBLREKAPBAHAN[[#This Row],[ISI]] -> 20 | E5: 1000 | F5: =SUMIF(TBLBAHANMASUK[NAMA BAHAN],TBLREKAPBAHAN[[#This Row],[NAMA BAHAN]],TBLBAHANMASUK[MASUK]) -> 2000 | G5: =SUMIF(TBLBAHANKELUAR[NAMA BAHAN],TBLREKAPBAHAN[[#This Row],[NAMA BAHAN]],TBLBAHANKELUAR[TOTAL BAHAN KELUAR]) -> 835 | H5: =TBLREKAPBAHAN[[#This Row],[STOK]]+TBLREKAPBAHAN[[#This Row],[MASUK]]-TBLREKAPBAHAN[[#This Row],[KELUAR]] -> 2165 | I5: =TBLREKAPBAHAN[[#This Row],[MODAL SATUAN]]*TBLREKAPBAHAN[[#This Row],[SISA STOK]] -> 43300
A6: SAOS SAMBAL GRAM | B6: 18000 | C6: 1000 | D6: =TBLREKAPBAHAN[[#This Row],[MODAL]]/TBLREKAPBAHAN[[#This Row],[ISI]] -> 18 | E6: 40 | F6: =SUMIF(TBLBAHANMASUK[NAMA BAHAN],TBLREKAPBAHAN[[#This Row],[NAMA BAHAN]],TBLBAHANMASUK[MASUK]) -> 3000 | G6: =SUMIF(TBLBAHANKELUAR[NAMA BAHAN],TBLREKAPBAHAN[[#This Row],[NAMA BAHAN]],TBLBAHANKELUAR[TOTAL BAHAN KELUAR]) -> 1380 | H6: =TBLREKAPBAHAN[[#This Row],[STOK]]+TBLREKAPBAHAN[[#This Row],[MASUK]]-TBLREKAPBAHAN[[#This Row],[KELUAR]] -> 1660 | I6: =TBLREKAPBAHAN[[#This Row],[MODAL SATUAN]]*TBLREKAPBAHAN[[#This Row],[SISA STOK]] -> 29880
A7: SAOS BBQ GRAM | B7: 12000 | C7: 250 | D7: =TBLREKAPBAHAN[[#This Row],[MODAL]]/TBLREKAPBAHAN[[#This Row],[ISI]] -> 48 | E7: 149 | F7: =SUMIF(TBLBAHANMASUK[NAMA BAHAN],TBLREKAPBAHAN[[#This Row],[NAMA BAHAN]],TBLBAHANMASUK[MASUK]) -> 1000 | G7: =SUMIF(TBLBAHANKELUAR[NAMA BAHAN],TBLREKAPBAHAN[[#This Row],[NAMA BAHAN]],TBLBAHANKELUAR[TOTAL BAHAN KELUAR]) -> 847 | H7: =TBLREKAPBAHAN[[#This Row],[STOK]]+TBLREKAPBAHAN[[#This Row],[MASUK]]-TBLREKAPBAHAN[[#This Row],[KELUAR]] -> 302 | I7: =TBLREKAPBAHAN[[#This Row],[MODAL SATUAN]]*TBLREKAPBAHAN[[#This Row],[SISA STOK]] -> 14496
A8: MAYONAIS GRAM | B8: 50000 | C8: 1000 | D8: =TBLREKAPBAHAN[[#This Row],[MODAL]]/TBLREKAPBAHAN[[#This Row],[ISI]] -> 50 | E8: 903 | F8: =SUMIF(TBLBAHANMASUK[NAMA BAHAN],TBLREKAPBAHAN[[#This Row],[NAMA BAHAN]],TBLBAHANMASUK[MASUK]) -> 2000 | G8: =SUMIF(TBLBAHANKELUAR[NAMA BAHAN],TBLREKAPBAHAN[[#This Row],[NAMA BAHAN]],TBLBAHANKELUAR[TOTAL BAHAN KELUAR]) -> 2270 | H8: =TBLREKAPBAHAN[[#This Row],[STOK]]+TBLREKAPBAHAN[[#This Row],[MASUK]]-TBLREKAPBAHAN[[#This Row],[KELUAR]] -> 633 | I8: =TBLREKAPBAHAN[[#This Row],[MODAL SATUAN]]*TBLREKAPBAHAN[[#This Row],[SISA STOK]] -> 31650
A9: SAOS SPAGHETI GRAM | B9: 12000 | C9: 250 | D9: =TBLREKAPBAHAN[[#This Row],[MODAL]]/TBLREKAPBAHAN[[#This Row],[ISI]] -> 48 | E9: 479 | F9: =SUMIF(TBLBAHANMASUK[NAMA BAHAN],TBLREKAPBAHAN[[#This Row],[NAMA BAHAN]],TBLBAHANMASUK[MASUK]) -> 2250 | G9: =SUMIF(TBLBAHANKELUAR[NAMA BAHAN],TBLREKAPBAHAN[[#This Row],[NAMA BAHAN]],TBLBAHANKELUAR[TOTAL BAHAN KELUAR]) -> 1387 | H9: =TBLREKAPBAHAN[[#This Row],[STOK]]+TBLREKAPBAHAN[[#This Row],[MASUK]]-TBLREKAPBAHAN[[#This Row],[KELUAR]] -> 1342 | I9: =TBLREKAPBAHAN[[#This Row],[MODAL SATUAN]]*TBLREKAPBAHAN[[#This Row],[SISA STOK]] -> 64416
A10: SAOS TOMAT SACHET | B10: 7000 | C10: 24 | D10: =TBLREKAPBAHAN[[#This Row],[MODAL]]/TBLREKAPBAHAN[[#This Row],[ISI]] -> 291.66667 | E10: 84 | F10: =SUMIF(TBLBAHANMASUK[NAMA BAHAN],TBLREKAPBAHAN[[#This Row],[NAMA BAHAN]],TBLBAHANMASUK[MASUK]) -> 48 | G10: =SUMIF(TBLBAHANKELUAR[NAMA BAHAN],TBLREKAPBAHAN[[#This Row],[NAMA BAHAN]],TBLBAHANKELUAR[TOTAL BAHAN KELUAR]) -> 114 | H10: =TBLREKAPBAHAN[[#This Row],[STOK]]+TBLREKAPBAHAN[[#This Row],[MASUK]]-TBLREKAPBAHAN[[#This Row],[KELUAR]] -> 18 | I10: =TBLREKAPBAHAN[[#This Row],[MODAL SATUAN]]*TBLREKAPBAHAN[[#This Row],[SISA STOK]] -> 5250
A11: SAOS SAMBAL SACHET | B11: 8000 | C11: 24 | D11: =TBLREKAPBAHAN[[#This Row],[MODAL]]/TBLREKAPBAHAN[[#This Row],[ISI]] -> 333.33333 | E11: 41 | F11: =SUMIF(TBLBAHANMASUK[NAMA BAHAN],TBLREKAPBAHAN[[#This Row],[NAMA BAHAN]],TBLBAHANMASUK[MASUK]) -> 72 | G11: =SUMIF(TBLBAHANKELUAR[NAMA BAHAN],TBLREKAPBAHAN[[#This Row],[NAMA BAHAN]],TBLBAHANKELUAR[TOTAL BAHAN KELUAR]) -> 74 | H11: =TBLREKAPBAHAN[[#This Row],[STOK]]+TBLREKAPBAHAN[[#This Row],[MASUK]]-TBLREKAPBAHAN[[#This Row],[KELUAR]] -> 39 | I11: =TBLREKAPBAHAN[[#This Row],[MODAL SATUAN]]*TBLREKAPBAHAN[[#This Row],[SISA STOK]] -> 13000
A12: KEJU SLICE MEDIUM SACHET | B12: 16000 | C12: 12 | D12: =TBLREKAPBAHAN[[#This Row],[MODAL]]/TBLREKAPBAHAN[[#This Row],[ISI]] -> 1333.3333 | E12: 27 | F12: =SUMIF(TBLBAHANMASUK[NAMA BAHAN],TBLREKAPBAHAN[[#This Row],[NAMA BAHAN]],TBLBAHANMASUK[MASUK]) -> 22 | G12: =SUMIF(TBLBAHANKELUAR[NAMA BAHAN],TBLREKAPBAHAN[[#This Row],[NAMA BAHAN]],TBLBAHANKELUAR[TOTAL BAHAN KELUAR]) -> 37 | H12: =TBLREKAPBAHAN[[#This Row],[STOK]]+TBLREKAPBAHAN[[#This Row],[MASUK]]-TBLREKAPBAHAN[[#This Row],[KELUAR]] -> 12 | I12: =TBLREKAPBAHAN[[#This Row],[MODAL SATUAN]]*TBLREKAPBAHAN[[#This Row],[SISA STOK]] -> 16000
A13: KEJU MOZZARELLA | B13: 90000 | C13: 500 | D13: =TBLREKAPBAHAN[[#This Row],[MODAL]]/TBLREKAPBAHAN[[#This Row],[ISI]] -> 180 | E13: 6 | F13: =SUMIF(TBLBAHANMASUK[NAMA BAHAN],TBLREKAPBAHAN[[#This Row],[NAMA BAHAN]],TBLBAHANMASUK[MASUK]) -> 1000 | G13: =SUMIF(TBLBAHANKELUAR[NAMA BAHAN],TBLREKAPBAHAN[[#This Row],[NAMA BAHAN]],TBLBAHANKELUAR[TOTAL BAHAN KELUAR]) -> 802 | H13: =TBLREKAPBAHAN[[#This Row],[STOK]]+TBLREKAPBAHAN[[#This Row],[MASUK]]-TBLREKAPBAHAN[[#This Row],[KELUAR]] -> 204 | I13: =TBLREKAPBAHAN[[#This Row],[MODAL SATUAN]]*TBLREKAPBAHAN[[#This Row],[SISA STOK]] -> 36720
A14: NUGGET AYAM | B14: 22000 | C14: 6 | D14: =TBLREKAPBAHAN[[#This Row],[MODAL]]/TBLREKAPBAHAN[[#This Row],[ISI]] -> 3666.6667 | E14: 0 | F14: =SUMIF(TBLBAHANMASUK[NAMA BAHAN],TBLREKAPBAHAN[[#This Row],[NAMA BAHAN]],TBLBAHANMASUK[MASUK]) -> 0 | G14: =SUMIF(TBLBAHANKELUAR[NAMA BAHAN],TBLREKAPBAHAN[[#This Row],[NAMA BAHAN]],TBLBAHANKELUAR[TOTAL BAHAN KELUAR]) -> 0 | H14: =TBLREKAPBAHAN[[#This Row],[STOK]]+TBLREKAPBAHAN[[#This Row],[MASUK]]-TBLREKAPBAHAN[[#This Row],[KELUAR]] -> 0 | I14: =TBLREKAPBAHAN[[#This Row],[MODAL SATUAN]]*TBLREKAPBAHAN[[#This Row],[SISA STOK]] -> 0
A15: SOSIZ BATANG | B15: 35000 | C15: 38 | D15: =TBLREKAPBAHAN[[#This Row],[MODAL]]/TBLREKAPBAHAN[[#This Row],[ISI]] -> 921.05263 | E15: 7 | F15: =SUMIF(TBLBAHANMASUK[NAMA BAHAN],TBLREKAPBAHAN[[#This Row],[NAMA BAHAN]],TBLBAHANMASUK[MASUK]) -> 192 | G15: =SUMIF(TBLBAHANKELUAR[NAMA BAHAN],TBLREKAPBAHAN[[#This Row],[NAMA BAHAN]],TBLBAHANKELUAR[TOTAL BAHAN KELUAR]) -> 141 | H15: =TBLREKAPBAHAN[[#This Row],[STOK]]+TBLREKAPBAHAN[[#This Row],[MASUK]]-TBLREKAPBAHAN[[#This Row],[KELUAR]] -> 58 | I15: =TBLREKAPBAHAN[[#This Row],[MODAL SATUAN]]*TBLREKAPBAHAN[[#This Row],[SISA STOK]] -> 53421.053
A16: AYAM SUWIR | B16: 45000 | C16: 400 | D16: =TBLREKAPBAHAN[[#This Row],[MODAL]]/TBLREKAPBAHAN[[#This Row],[ISI]] -> 112.5 | E16: 1593 | F16: =SUMIF(TBLBAHANMASUK[NAMA BAHAN],TBLREKAPBAHAN[[#This Row],[NAMA BAHAN]],TBLBAHANMASUK[MASUK]) -> 2800 | G16: =SUMIF(TBLBAHANKELUAR[NAMA BAHAN],TBLREKAPBAHAN[[#This Row],[NAMA BAHAN]],TBLBAHANKELUAR[TOTAL BAHAN KELUAR]) -> 3943 | H16: =TBLREKAPBAHAN[[#This Row],[STOK]]+TBLREKAPBAHAN[[#This Row],[MASUK]]-TBLREKAPBAHAN[[#This Row],[KELUAR]] -> 450 | I16: =TBLREKAPBAHAN[[#This Row],[MODAL SATUAN]]*TBLREKAPBAHAN[[#This Row],[SISA STOK]] -> 50625
... A71: PERASA JAGUNG MANIS | B71: 5500 | C71: 100 | D71: =TBLREKAPBAHAN[[#This Row],[MODAL]]/TBLREKAPBAHAN[[#This Row],[ISI]] -> 55 | E71: 0 | F71: =SUMIF(TBLBAHANMASUK[NAMA BAHAN],TBLREKAPBAHAN[[#This Row],[NAMA BAHAN]],TBLBAHANMASUK[MASUK]) -> 100 | G71: =SUMIF(TBLBAHANKELUAR[NAMA BAHAN],TBLREKAPBAHAN[[#This Row],[NAMA BAHAN]],TBLBAHANKELUAR[TOTAL BAHAN KELUAR]) -> 0 | H71: =TBLREKAPBAHAN[[#This Row],[STOK]]+TBLREKAPBAHAN[[#This Row],[MASUK]]-TBLREKAPBAHAN[[#This Row],[KELUAR]] -> 100 | I71: =TBLREKAPBAHAN[[#This Row],[MODAL SATUAN]]*TBLREKAPBAHAN[[#This Row],[SISA STOK]] -> 5500

Sheet DATA BAHAN MASUK
A1: CASH VALUE DAN LABA
A2: CAHYA GALLERY FOOD & BEVERAGE
A4: TAHUN | B4: BULAN | C4: TANGGAL | D4: NAMA BAHAN | E4: MODAL | F4: ISI | G4: MODAL SATUAN | H4: MASUK | I4: NILAI MASUK | J4: HARGA ASLI | K4: QTY | L4: MODAL ASLI | M4: QTY MASUK | N4: NILAI MASUK ASLI | O4: CASHBACK BELANJA
A5: 2026 | B5: JUNI | C5: 46190 | D5: SAOS SAMBAL GRAM | E5: =VLOOKUP(TBLBAHANMASUK[[#This Row],[NAMA BAHAN]],TBLREKAPBAHAN[[NAMA BAHAN]:[MODAL SATUAN]],2,FALSE) -> 18000 | F5: =VLOOKUP(TBLBAHANMASUK[[#This Row],[NAMA BAHAN]],TBLREKAPBAHAN[[NAMA BAHAN]:[MODAL SATUAN]],3,FALSE) -> 1000 | G5: =VLOOKUP(TBLBAHANMASUK[[#This Row],[NAMA BAHAN]],TBLREKAPBAHAN[[NAMA BAHAN]:[MODAL SATUAN]],4,FALSE) -> 18 | H5: 1000 | I5: =TBLBAHANMASUK[[#This Row],[MODAL SATUAN]]*TBLBAHANMASUK[[#This Row],[MASUK]] -> 18000 | J5: 17500 | K5: =TBLBAHANMASUK[[#This Row],[ISI]] -> 1000 | L5: =TBLBAHANMASUK[[#This Row],[HARGA ASLI]]/TBLBAHANMASUK[[#This Row],[QTY]] -> 17.5 | M5: =TBLBAHANMASUK[[#This Row],[MASUK]] -> 1000 | N5: =TBLBAHANMASUK[[#This Row],[MODAL ASLI]]*TBLBAHANMASUK[[#This Row],[QTY MASUK]] -> 17500 | O5: =TBLBAHANMASUK[[#This Row],[NILAI MASUK]]-TBLBAHANMASUK[[#This Row],[NILAI MASUK ASLI]] -> 500
A6: 2026 | B6: JUNI | C6: 46190 | D6: SAOS TOMAT SACHET | E6: =VLOOKUP(TBLBAHANMASUK[[#This Row],[NAMA BAHAN]],TBLREKAPBAHAN[[NAMA BAHAN]:[MODAL SATUAN]],2,FALSE) -> 7000 | F6: =VLOOKUP(TBLBAHANMASUK[[#This Row],[NAMA BAHAN]],TBLREKAPBAHAN[[NAMA BAHAN]:[MODAL SATUAN]],3,FALSE) -> 24 | G6: =VLOOKUP(TBLBAHANMASUK[[#This Row],[NAMA BAHAN]],TBLREKAPBAHAN[[NAMA BAHAN]:[MODAL SATUAN]],4,FALSE) -> 291.66667 | H6: 24 | I6: =TBLBAHANMASUK[[#This Row],[MODAL SATUAN]]*TBLBAHANMASUK[[#This Row],[MASUK]] -> 7000 | J6: 6900 | K6: =TBLBAHANMASUK[[#This Row],[ISI]] -> 24 | L6: =TBLBAHANMASUK[[#This Row],[HARGA ASLI]]/TBLBAHANMASUK[[#This Row],[QTY]] -> 287.5 | M6: =TBLBAHANMASUK[[#This Row],[MASUK]] -> 24 | N6: =TBLBAHANMASUK[[#This Row],[MODAL ASLI]]*TBLBAHANMASUK[[#This Row],[QTY MASUK]] -> 6900 | O6: =TBLBAHANMASUK[[#This Row],[NILAI MASUK]]-TBLBAHANMASUK[[#This Row],[NILAI MASUK ASLI]] -> 100
A7: 2026 | B7: JUNI | C7: 46190 | D7: SAOS SPAGHETI GRAM | E7: =VLOOKUP(TBLBAHANMASUK[[#This Row],[NAMA BAHAN]],TBLREKAPBAHAN[[NAMA BAHAN]:[MODAL SATUAN]],2,FALSE) -> 12000 | F7: =VLOOKUP(TBLBAHANMASUK[[#This Row],[NAMA BAHAN]],TBLREKAPBAHAN[[NAMA BAHAN]:[MODAL SATUAN]],3,FALSE) -> 250 | G7: =VLOOKUP(TBLBAHANMASUK[[#This Row],[NAMA BAHAN]],TBLREKAPBAHAN[[NAMA BAHAN]:[MODAL SATUAN]],4,FALSE) -> 48 | H7: 500 | I7: =TBLBAHANMASUK[[#This Row],[MODAL SATUAN]]*TBLBAHANMASUK[[#This Row],[MASUK]] -> 24000 | J7: 9800 | K7: =TBLBAHANMASUK[[#This Row],[ISI]] -> 250 | L7: =TBLBAHANMASUK[[#This Row],[HARGA ASLI]]/TBLBAHANMASUK[[#This Row],[QTY]] -> 39.2 | M7: =TBLBAHANMASUK[[#This Row],[MASUK]] -> 500 | N7: =TBLBAHANMASUK[[#This Row],[MODAL ASLI]]*TBLBAHANMASUK[[#This Row],[QTY MASUK]] -> 19600 | O7: =TBLBAHANMASUK[[#This Row],[NILAI MASUK]]-TBLBAHANMASUK[[#This Row],[NILAI MASUK ASLI]] -> 4400
A8: 2026 | B8: JUNI | C8: 46190 | D8: SAOS BBQ GRAM | E8: =VLOOKUP(TBLBAHANMASUK[[#This Row],[NAMA BAHAN]],TBLREKAPBAHAN[[NAMA BAHAN]:[MODAL SATUAN]],2,FALSE) -> 12000 | F8: =VLOOKUP(TBLBAHANMASUK[[#This Row],[NAMA BAHAN]],TBLREKAPBAHAN[[NAMA BAHAN]:[MODAL SATUAN]],3,FALSE) -> 250 | G8: =VLOOKUP(TBLBAHANMASUK[[#This Row],[NAMA BAHAN]],TBLREKAPBAHAN[[NAMA BAHAN]:[MODAL SATUAN]],4,FALSE) -> 48 | H8: 500 | I8: =TBLBAHANMASUK[[#This Row],[MODAL SATUAN]]*TBLBAHANMASUK[[#This Row],[MASUK]] -> 24000 | J8: 10950 | K8: =TBLBAHANMASUK[[#This Row],[ISI]] -> 250 | L8: =TBLBAHANMASUK[[#This Row],[HARGA ASLI]]/TBLBAHANMASUK[[#This Row],[QTY]] -> 43.8 | M8: =TBLBAHANMASUK[[#This Row],[MASUK]] -> 500 | N8: =TBLBAHANMASUK[[#This Row],[MODAL ASLI]]*TBLBAHANMASUK[[#This Row],[QTY MASUK]] -> 21900 | O8: =TBLBAHANMASUK[[#This Row],[NILAI MASUK]]-TBLBAHANMASUK[[#This Row],[NILAI MASUK ASLI]] -> 2100
A9: 2026 | B9: JUNI | C9: 46190 | D9: MAYONAIS GRAM | E9: =VLOOKUP(TBLBAHANMASUK[[#This Row],[NAMA BAHAN]],TBLREKAPBAHAN[[NAMA BAHAN]:[MODAL SATUAN]],2,FALSE) -> 50000 | F9: =VLOOKUP(TBLBAHANMASUK[[#This Row],[NAMA BAHAN]],TBLREKAPBAHAN[[NAMA BAHAN]:[MODAL SATUAN]],3,FALSE) -> 1000 | G9: =VLOOKUP(TBLBAHANMASUK[[#This Row],[NAMA BAHAN]],TBLREKAPBAHAN[[NAMA BAHAN]:[MODAL SATUAN]],4,FALSE) -> 50 | H9: 1000 | I9: =TBLBAHANMASUK[[#This Row],[MODAL SATUAN]]*TBLBAHANMASUK[[#This Row],[MASUK]] -> 50000 | J9: 32000 | K9: =TBLBAHANMASUK[[#This Row],[ISI]] -> 1000 | L9: =TBLBAHANMASUK[[#This Row],[HARGA ASLI]]/TBLBAHANMASUK[[#This Row],[QTY]] -> 32 | M9: =TBLBAHANMASUK[[#This Row],[MASUK]] -> 1000 | N9: =TBLBAHANMASUK[[#This Row],[MODAL ASLI]]*TBLBAHANMASUK[[#This Row],[QTY MASUK]] -> 32000 | O9: =TBLBAHANMASUK[[#This Row],[NILAI MASUK]]-TBLBAHANMASUK[[#This Row],[NILAI MASUK ASLI]] -> 18000
A10: 2026 | B10: JUNI | C10: 46190 | D10: KULIT KEBAB 17/18 CM | E10: =VLOOKUP(TBLBAHANMASUK[[#This Row],[NAMA BAHAN]],TBLREKAPBAHAN[[NAMA BAHAN]:[MODAL SATUAN]],2,FALSE) -> 27000 | F10: =VLOOKUP(TBLBAHANMASUK[[#This Row],[NAMA BAHAN]],TBLREKAPBAHAN[[NAMA BAHAN]:[MODAL SATUAN]],3,FALSE) -> 20 | G10: =VLOOKUP(TBLBAHANMASUK[[#This Row],[NAMA BAHAN]],TBLREKAPBAHAN[[NAMA BAHAN]:[MODAL SATUAN]],4,FALSE) -> 1350 | H10: 20 | I10: =TBLBAHANMASUK[[#This Row],[MODAL SATUAN]]*TBLBAHANMASUK[[#This Row],[MASUK]] -> 27000 | J10: 26000 | K10: =TBLBAHANMASUK[[#This Row],[ISI]] -> 20 | L10: =TBLBAHANMASUK[[#This Row],[HARGA ASLI]]/TBLBAHANMASUK[[#This Row],[QTY]] -> 1300 | M10: =TBLBAHANMASUK[[#This Row],[MASUK]] -> 20 | N10: =TBLBAHANMASUK[[#This Row],[MODAL ASLI]]*TBLBAHANMASUK[[#This Row],[QTY MASUK]] -> 26000 | O10: =TBLBAHANMASUK[[#This Row],[NILAI MASUK]]-TBLBAHANMASUK[[#This Row],[NILAI MASUK ASLI]] -> 1000
A11: 2026 | B11: JUNI | C11: 46190 | D11: KULIT KEBAB 19/20 CM | E11: =VLOOKUP(TBLBAHANMASUK[[#This Row],[NAMA BAHAN]],TBLREKAPBAHAN[[NAMA BAHAN]:[MODAL SATUAN]],2,FALSE) -> 29000 | F11: =VLOOKUP(TBLBAHANMASUK[[#This Row],[NAMA BAHAN]],TBLREKAPBAHAN[[NAMA BAHAN]:[MODAL SATUAN]],3,FALSE) -> 20 | G11: =VLOOKUP(TBLBAHANMASUK[[#This Row],[NAMA BAHAN]],TBLREKAPBAHAN[[NAMA BAHAN]:[MODAL SATUAN]],4,FALSE) -> 1450 | H11: 20 | I11: =TBLBAHANMASUK[[#This Row],[MODAL SATUAN]]*TBLBAHANMASUK[[#This Row],[MASUK]] -> 29000 | J11: 28500 | K11: =TBLBAHANMASUK[[#This Row],[ISI]] -> 20 | L11: =TBLBAHANMASUK[[#This Row],[HARGA ASLI]]/TBLBAHANMASUK[[#This Row],[QTY]] -> 1425 | M11: =TBLBAHANMASUK[[#This Row],[MASUK]] -> 20 | N11: =TBLBAHANMASUK[[#This Row],[MODAL ASLI]]*TBLBAHANMASUK[[#This Row],[QTY MASUK]] -> 28500 | O11: =TBLBAHANMASUK[[#This Row],[NILAI MASUK]]-TBLBAHANMASUK[[#This Row],[NILAI MASUK ASLI]] -> 500
A12: 2026 | B12: JUNI | C12: 46190 | D12: ROTI MARYAM | E12: =VLOOKUP(TBLBAHANMASUK[[#This Row],[NAMA BAHAN]],TBLREKAPBAHAN[[NAMA BAHAN]:[MODAL SATUAN]],2,FALSE) -> 20000 | F12: =VLOOKUP(TBLBAHANMASUK[[#This Row],[NAMA BAHAN]],TBLREKAPBAHAN[[NAMA BAHAN]:[MODAL SATUAN]],3,FALSE) -> 10 | G12: =VLOOKUP(TBLBAHANMASUK[[#This Row],[NAMA BAHAN]],TBLREKAPBAHAN[[NAMA BAHAN]:[MODAL SATUAN]],4,FALSE) -> 2000 | H12: 10 | I12: =TBLBAHANMASUK[[#This Row],[MODAL SATUAN]]*TBLBAHANMASUK[[#This Row],[MASUK]] -> 20000 | J12: 18500 | K12: =TBLBAHANMASUK[[#This Row],[ISI]] -> 10 | L12: =TBLBAHANMASUK[[#This Row],[HARGA ASLI]]/TBLBAHANMASUK[[#This Row],[QTY]] -> 1850 | M12: =TBLBAHANMASUK[[#This Row],[MASUK]] -> 10 | N12: =TBLBAHANMASUK[[#This Row],[MODAL ASLI]]*TBLBAHANMASUK[[#This Row],[QTY MASUK]] -> 18500 | O12: =TBLBAHANMASUK[[#This Row],[NILAI MASUK]]-TBLBAHANMASUK[[#This Row],[NILAI MASUK ASLI]] -> 1500
A13: 2026 | B13: JUNI | C13: 46190 | D13: ROTI BURGER MEDIUM | E13: =VLOOKUP(TBLBAHANMASUK[[#This Row],[NAMA BAHAN]],TBLREKAPBAHAN[[NAMA BAHAN]:[MODAL SATUAN]],2,FALSE) -> 15000 | F13: =VLOOKUP(TBLBAHANMASUK[[#This Row],[NAMA BAHAN]],TBLREKAPBAHAN[[NAMA BAHAN]:[MODAL SATUAN]],3,FALSE) -> 6 | G13: =VLOOKUP(TBLBAHANMASUK[[#This Row],[NAMA BAHAN]],TBLREKAPBAHAN[[NAMA BAHAN]:[MODAL SATUAN]],4,FALSE) -> 2500 | H13: 6 | I13: =TBLBAHANMASUK[[#This Row],[MODAL SATUAN]]*TBLBAHANMASUK[[#This Row],[MASUK]] -> 15000 | J13: 14500 | K13: =TBLBAHANMASUK[[#This Row],[ISI]] -> 6 | L13: =TBLBAHANMASUK[[#This Row],[HARGA ASLI]]/TBLBAHANMASUK[[#This Row],[QTY]] -> 2416.6667 | M13: =TBLBAHANMASUK[[#This Row],[MASUK]] -> 6 | N13: =TBLBAHANMASUK[[#This Row],[MODAL ASLI]]*TBLBAHANMASUK[[#This Row],[QTY MASUK]] -> 14500 | O13: =TBLBAHANMASUK[[#This Row],[NILAI MASUK]]-TBLBAHANMASUK[[#This Row],[NILAI MASUK ASLI]] -> 500
A14: 2026 | B14: JUNI | C14: 46190 | D14: DAGING SAPI | E14: =VLOOKUP(TBLBAHANMASUK[[#This Row],[NAMA BAHAN]],TBLREKAPBAHAN[[NAMA BAHAN]:[MODAL SATUAN]],2,FALSE) -> 85000 | F14: =VLOOKUP(TBLBAHANMASUK[[#This Row],[NAMA BAHAN]],TBLREKAPBAHAN[[NAMA BAHAN]:[MODAL SATUAN]],3,FALSE) -> 1000 | G14: =VLOOKUP(TBLBAHANMASUK[[#This Row],[NAMA BAHAN]],TBLREKAPBAHAN[[NAMA BAHAN]:[MODAL SATUAN]],4,FALSE) -> 85 | H14: 1000 | I14: =TBLBAHANMASUK[[#This Row],[MODAL SATUAN]]*TBLBAHANMASUK[[#This Row],[MASUK]] -> 85000 | J14: 79900 | K14: =TBLBAHANMASUK[[#This Row],[ISI]] -> 1000 | L14: =TBLBAHANMASUK[[#This Row],[HARGA ASLI]]/TBLBAHANMASUK[[#This Row],[QTY]] -> 79.9 | M14: =TBLBAHANMASUK[[#This Row],[MASUK]] -> 1000 | N14: =TBLBAHANMASUK[[#This Row],[MODAL ASLI]]*TBLBAHANMASUK[[#This Row],[QTY MASUK]] -> 79900 | O14: =TBLBAHANMASUK[[#This Row],[NILAI MASUK]]-TBLBAHANMASUK[[#This Row],[NILAI MASUK ASLI]] -> 5100
A15: 2026 | B15: JUNI | C15: 46190 | D15: SLADA | E15: =VLOOKUP(TBLBAHANMASUK[[#This Row],[NAMA BAHAN]],TBLREKAPBAHAN[[NAMA BAHAN]:[MODAL SATUAN]],2,FALSE) -> 60000 | F15: =VLOOKUP(TBLBAHANMASUK[[#This Row],[NAMA BAHAN]],TBLREKAPBAHAN[[NAMA BAHAN]:[MODAL SATUAN]],3,FALSE) -> 50 | G15: =VLOOKUP(TBLBAHANMASUK[[#This Row],[NAMA BAHAN]],TBLREKAPBAHAN[[NAMA BAHAN]:[MODAL SATUAN]],4,FALSE) -> 1200 | H15: 50 | I15: =TBLBAHANMASUK[[#This Row],[MODAL SATUAN]]*TBLBAHANMASUK[[#This Row],[MASUK]] -> 60000 | J15: 50000 | K15: =TBLBAHANMASUK[[#This Row],[ISI]] -> 50 | L15: =TBLBAHANMASUK[[#This Row],[HARGA ASLI]]/TBLBAHANMASUK[[#This Row],[QTY]] -> 1000 | M15: =TBLBAHANMASUK[[#This Row],[MASUK]] -> 50 | N15: =TBLBAHANMASUK[[#This Row],[MODAL ASLI]]*TBLBAHANMASUK[[#This Row],[QTY MASUK]] -> 50000 | O15: =TBLBAHANMASUK[[#This Row],[NILAI MASUK]]-TBLBAHANMASUK[[#This Row],[NILAI MASUK ASLI]] -> 10000
A16: 2026 | B16: JUNI | C16: 46190 | D16: KEJU MOZZARELLA | E16: =VLOOKUP(TBLBAHANMASUK[[#This Row],[NAMA BAHAN]],TBLREKAPBAHAN[[NAMA BAHAN]:[MODAL SATUAN]],2,FALSE) -> 90000 | F16: =VLOOKUP(TBLBAHANMASUK[[#This Row],[NAMA BAHAN]],TBLREKAPBAHAN[[NAMA BAHAN]:[MODAL SATUAN]],3,FALSE) -> 500 | G16: =VLOOKUP(TBLBAHANMASUK[[#This Row],[NAMA BAHAN]],TBLREKAPBAHAN[[NAMA BAHAN]:[MODAL SATUAN]],4,FALSE) -> 180 | H16: 500 | I16: =TBLBAHANMASUK[[#This Row],[MODAL SATUAN]]*TBLBAHANMASUK[[#This Row],[MASUK]] -> 90000 | J16: 88000 | K16: =TBLBAHANMASUK[[#This Row],[ISI]] -> 500 | L16: =TBLBAHANMASUK[[#This Row],[HARGA ASLI]]/TBLBAHANMASUK[[#This Row],[QTY]] -> 176 | M16: =TBLBAHANMASUK[[#This Row],[MASUK]] -> 500 | N16: =TBLBAHANMASUK[[#This Row],[MODAL ASLI]]*TBLBAHANMASUK[[#This Row],[QTY MASUK]] -> 88000 | O16: =TBLBAHANMASUK[[#This Row],[NILAI MASUK]]-TBLBAHANMASUK[[#This Row],[NILAI MASUK ASLI]] -> 2000
... A74: 2026 | B74: JULI | C74: 46228 | D74: JAGUNG | E74: =VLOOKUP(TBLBAHANMASUK[[#This Row],[NAMA BAHAN]],TBLREKAPBAHAN[[NAMA BAHAN]:[MODAL SATUAN]],2,FALSE) -> 3000 | F74: =VLOOKUP(TBLBAHANMASUK[[#This Row],[NAMA BAHAN]],TBLREKAPBAHAN[[NAMA BAHAN]:[MODAL SATUAN]],3,FALSE) -> 2 | G74: =VLOOKUP(TBLBAHANMASUK[[#This Row],[NAMA BAHAN]],TBLREKAPBAHAN[[NAMA BAHAN]:[MODAL SATUAN]],4,FALSE) -> 1500 | H74: 1 | I74: =TBLBAHANMASUK[[#This Row],[MODAL SATUAN]]*TBLBAHANMASUK[[#This Row],[MASUK]] -> 1500 | J74: 4000 | K74: =TBLBAHANMASUK[[#This Row],[ISI]] -> 2 | L74: =TBLBAHANMASUK[[#This Row],[HARGA ASLI]]/TBLBAHANMASUK[[#This Row],[QTY]] -> 2000 | M74: =TBLBAHANMASUK[[#This Row],[MASUK]] -> 1 | N74: =TBLBAHANMASUK[[#This Row],[MODAL ASLI]]*TBLBAHANMASUK[[#This Row],[QTY MASUK]] -> 2000 | O74: =TBLBAHANMASUK[[#This Row],[NILAI MASUK]]-TBLBAHANMASUK[[#This Row],[NILAI MASUK ASLI]] -> -500

Sheet DATA BAHAN KELUAR
G1: CASH VALUE DAN LABA
G2: CAHYA GALLERY FOOD & BEVERAGE
E5: WAJIB DIISI MANUAL BY DATA VALIDATION UNTUK MENAUTKAN JUMLAH PRODUK KELUAR | F5: KODE BAHAN WAJIB DIISI MANUAL UNTUK MENAMPILKAN NAMA BAHAN DAN KEBUTUHAN BAHAN | G5: INGAT! SETIAP GANTI MENU/PRODUK MAKA NAMA PRODUK YG ADA DI DALAM RUMUS HARUS DIEDIT/DIGANTI | K5: INGAT! SETIAP GANTI MENU/PRODUK MAKA NAMA PRODUK YG ADA DI DALAM RUMUS HARUS DIEDIT/DIGANTI | L5: INI AKAN TERISI OTOMATIS KETIKA JUMLAH PRODUK KELUAR PADA SHEET PRODUK KELUAR TELAH DIISI (PERHATIKAN BULAN KELUAR NYA)
A6: TAHUN | B6: BULAN | C6: PEKAN | D6: TANGGAL | E6: NAMA PRODUK | F6: KODE BAHAN | G6: NAMA BAHAN | H6: MODAL | I6: ISI | J6: MODAL SATUAN | K6: KEB. BAHAN | L6: JUMLAH KEB. BAHAN KELUAR | M6: TOTAL BAHAN KELUAR | N6: NILAI BAHAN KELUAR
A7: 2026 | B7: JUNI | E7: KEBAB AYAM + SOSIZ (KECIL) | F7: 1 | G7: =VLOOKUP(TBLBAHANKELUAR[[#This Row],[KODE BAHAN]],[4]!TBLKEBABSOSYAMKECIL[#Data],2,FALSE) -> SAOS TOMAT GRAM | H7: =VLOOKUP(TBLBAHANKELUAR[[#This Row],[NAMA BAHAN]],TBLREKAPBAHAN[[NAMA BAHAN]:[MODAL SATUAN]],2,FALSE) -> 20000 | I7: =VLOOKUP(TBLBAHANKELUAR[[#This Row],[NAMA BAHAN]],TBLREKAPBAHAN[[NAMA BAHAN]:[MODAL SATUAN]],3,FALSE) -> 1000 | J7: =VLOOKUP(TBLBAHANKELUAR[[#This Row],[NAMA BAHAN]],TBLREKAPBAHAN[[NAMA BAHAN]:[MODAL SATUAN]],4,FALSE) -> 20 | K7: =VLOOKUP(TBLBAHANKELUAR[[#This Row],[KODE BAHAN]],[4]!TBLKEBABSOSYAMKECIL[#Data],8,FALSE) -> 10 | L7: =SUMIF(TBLPRODUKKELUARJUNI[NAMA PRODUK],TBLBAHANKELUAR[[#This Row],[NAMA PRODUK]],TBLPRODUKKELUARJUNI[JUMLAH TERJUAL]) -> 2 | M7: =TBLBAHANKELUAR[[#This Row],[KEB. BAHAN]]*TBLBAHANKELUAR[[#This Row],[JUMLAH KEB. BAHAN KELUAR]] -> 20 | N7: =TBLBAHANKELUAR[[#This Row],[MODAL SATUAN]]*TBLBAHANKELUAR[[#This Row],[TOTAL BAHAN KELUAR]] -> 400
A8: 2026 | B8: JUNI | E8: KEBAB AYAM + SOSIZ (KECIL) | F8: 2 | G8: =VLOOKUP(TBLBAHANKELUAR[[#This Row],[KODE BAHAN]],[4]!TBLKEBABSOSYAMKECIL[#Data],2,FALSE) -> SAOS SAMBAL GRAM | H8: =VLOOKUP(TBLBAHANKELUAR[[#This Row],[NAMA BAHAN]],TBLREKAPBAHAN[[NAMA BAHAN]:[MODAL SATUAN]],2,FALSE) -> 18000 | I8: =VLOOKUP(TBLBAHANKELUAR[[#This Row],[NAMA BAHAN]],TBLREKAPBAHAN[[NAMA BAHAN]:[MODAL SATUAN]],3,FALSE) -> 1000 | J8: =VLOOKUP(TBLBAHANKELUAR[[#This Row],[NAMA BAHAN]],TBLREKAPBAHAN[[NAMA BAHAN]:[MODAL SATUAN]],4,FALSE) -> 18 | K8: =VLOOKUP(TBLBAHANKELUAR[[#This Row],[KODE BAHAN]],[4]!TBLKEBABSOSYAMKECIL[#Data],8,FALSE) -> 0 | L8: =SUMIF(TBLPRODUKKELUARJUNI[NAMA PRODUK],TBLBAHANKELUAR[[#This Row],[NAMA PRODUK]],TBLPRODUKKELUARJUNI[JUMLAH TERJUAL]) -> 2 | M8: =TBLBAHANKELUAR[[#This Row],[KEB. BAHAN]]*TBLBAHANKELUAR[[#This Row],[JUMLAH KEB. BAHAN KELUAR]] -> 0 | N8: =TBLBAHANKELUAR[[#This Row],[MODAL SATUAN]]*TBLBAHANKELUAR[[#This Row],[TOTAL BAHAN KELUAR]] -> 0
A9: 2026 | B9: JUNI | E9: KEBAB AYAM + SOSIZ (KECIL) | F9: 3 | G9: =VLOOKUP(TBLBAHANKELUAR[[#This Row],[KODE BAHAN]],[4]!TBLKEBABSOSYAMKECIL[#Data],2,FALSE) -> SAOS BBQ GRAM | H9: =VLOOKUP(TBLBAHANKELUAR[[#This Row],[NAMA BAHAN]],TBLREKAPBAHAN[[NAMA BAHAN]:[MODAL SATUAN]],2,FALSE) -> 12000 | I9: =VLOOKUP(TBLBAHANKELUAR[[#This Row],[NAMA BAHAN]],TBLREKAPBAHAN[[NAMA BAHAN]:[MODAL SATUAN]],3,FALSE) -> 250 | J9: =VLOOKUP(TBLBAHANKELUAR[[#This Row],[NAMA BAHAN]],TBLREKAPBAHAN[[NAMA BAHAN]:[MODAL SATUAN]],4,FALSE) -> 48 | K9: =VLOOKUP(TBLBAHANKELUAR[[#This Row],[KODE BAHAN]],[4]!TBLKEBABSOSYAMKECIL[#Data],8,FALSE) -> 5 | L9: =SUMIF(TBLPRODUKKELUARJUNI[NAMA PRODUK],TBLBAHANKELUAR[[#This Row],[NAMA PRODUK]],TBLPRODUKKELUARJUNI[JUMLAH TERJUAL]) -> 2 | M9: =TBLBAHANKELUAR[[#This Row],[KEB. BAHAN]]*TBLBAHANKELUAR[[#This Row],[JUMLAH KEB. BAHAN KELUAR]] -> 10 | N9: =TBLBAHANKELUAR[[#This Row],[MODAL SATUAN]]*TBLBAHANKELUAR[[#This Row],[TOTAL BAHAN KELUAR]] -> 480
A10: 2026 | B10: JUNI | E10: KEBAB AYAM + SOSIZ (KECIL) | F10: 4 | G10: =VLOOKUP(TBLBAHANKELUAR[[#This Row],[KODE BAHAN]],[4]!TBLKEBABSOSYAMKECIL[#Data],2,FALSE) -> MAYONAIS GRAM | H10: =VLOOKUP(TBLBAHANKELUAR[[#This Row],[NAMA BAHAN]],TBLREKAPBAHAN[[NAMA BAHAN]:[MODAL SATUAN]],2,FALSE) -> 50000 | I10: =VLOOKUP(TBLBAHANKELUAR[[#This Row],[NAMA BAHAN]],TBLREKAPBAHAN[[NAMA BAHAN]:[MODAL SATUAN]],3,FALSE) -> 1000 | J10: =VLOOKUP(TBLBAHANKELUAR[[#This Row],[NAMA BAHAN]],TBLREKAPBAHAN[[NAMA BAHAN]:[MODAL SATUAN]],4,FALSE) -> 50 | K10: =VLOOKUP(TBLBAHANKELUAR[[#This Row],[KODE BAHAN]],[4]!TBLKEBABSOSYAMKECIL[#Data],8,FALSE) -> 7 | L10: =SUMIF(TBLPRODUKKELUARJUNI[NAMA PRODUK],TBLBAHANKELUAR[[#This Row],[NAMA PRODUK]],TBLPRODUKKELUARJUNI[JUMLAH TERJUAL]) -> 2 | M10: =TBLBAHANKELUAR[[#This Row],[KEB. BAHAN]]*TBLBAHANKELUAR[[#This Row],[JUMLAH KEB. BAHAN KELUAR]] -> 14 | N10: =TBLBAHANKELUAR[[#This Row],[MODAL SATUAN]]*TBLBAHANKELUAR[[#This Row],[TOTAL BAHAN KELUAR]] -> 700
A11: 2026 | B11: JUNI | E11: KEBAB AYAM + SOSIZ (KECIL) | F11: 5 | G11: =VLOOKUP(TBLBAHANKELUAR[[#This Row],[KODE BAHAN]],[4]!TBLKEBABSOSYAMKECIL[#Data],2,FALSE) -> SAOS SPAGHETI GRAM | H11: =VLOOKUP(TBLBAHANKELUAR[[#This Row],[NAMA BAHAN]],TBLREKAPBAHAN[[NAMA BAHAN]:[MODAL SATUAN]],2,FALSE) -> 12000 | I11: =VLOOKUP(TBLBAHANKELUAR[[#This Row],[NAMA BAHAN]],TBLREKAPBAHAN[[NAMA BAHAN]:[MODAL SATUAN]],3,FALSE) -> 250 | J11: =VLOOKUP(TBLBAHANKELUAR[[#This Row],[NAMA BAHAN]],TBLREKAPBAHAN[[NAMA BAHAN]:[MODAL SATUAN]],4,FALSE) -> 48 | K11: =VLOOKUP(TBLBAHANKELUAR[[#This Row],[KODE BAHAN]],[4]!TBLKEBABSOSYAMKECIL[#Data],8,FALSE) -> 5 | L11: =SUMIF(TBLPRODUKKELUARJUNI[NAMA PRODUK],TBLBAHANKELUAR[[#This Row],[NAMA PRODUK]],TBLPRODUKKELUARJUNI[JUMLAH TERJUAL]) -> 2 | M11: =TBLBAHANKELUAR[[#This Row],[KEB. BAHAN]]*TBLBAHANKELUAR[[#This Row],[JUMLAH KEB. BAHAN KELUAR]] -> 10 | N11: =TBLBAHANKELUAR[[#This Row],[MODAL SATUAN]]*TBLBAHANKELUAR[[#This Row],[TOTAL BAHAN KELUAR]] -> 480
A12: 2026 | B12: JUNI | E12: KEBAB AYAM + SOSIZ (KECIL) | F12: 6 | G12: =VLOOKUP(TBLBAHANKELUAR[[#This Row],[KODE BAHAN]],[4]!TBLKEBABSOSYAMKECIL[#Data],2,FALSE) -> SOSIZ BATANG | H12: =VLOOKUP(TBLBAHANKELUAR[[#This Row],[NAMA BAHAN]],TBLREKAPBAHAN[[NAMA BAHAN]:[MODAL SATUAN]],2,FALSE) -> 35000 | I12: =VLOOKUP(TBLBAHANKELUAR[[#This Row],[NAMA BAHAN]],TBLREKAPBAHAN[[NAMA BAHAN]:[MODAL SATUAN]],3,FALSE) -> 38 | J12: =VLOOKUP(TBLBAHANKELUAR[[#This Row],[NAMA BAHAN]],TBLREKAPBAHAN[[NAMA BAHAN]:[MODAL SATUAN]],4,FALSE) -> 921.05263 | K12: =VLOOKUP(TBLBAHANKELUAR[[#This Row],[KODE BAHAN]],[4]!TBLKEBABSOSYAMKECIL[#Data],8,FALSE) -> 0.5 | L12: =SUMIF(TBLPRODUKKELUARJUNI[NAMA PRODUK],TBLBAHANKELUAR[[#This Row],[NAMA PRODUK]],TBLPRODUKKELUARJUNI[JUMLAH TERJUAL]) -> 2 | M12: =TBLBAHANKELUAR[[#This Row],[KEB. BAHAN]]*TBLBAHANKELUAR[[#This Row],[JUMLAH KEB. BAHAN KELUAR]] -> 1 | N12: =TBLBAHANKELUAR[[#This Row],[MODAL SATUAN]]*TBLBAHANKELUAR[[#This Row],[TOTAL BAHAN KELUAR]] -> 921.05263
A13: 2026 | B13: JUNI | E13: KEBAB AYAM + SOSIZ (KECIL) | F13: 7 | G13: =VLOOKUP(TBLBAHANKELUAR[[#This Row],[KODE BAHAN]],[4]!TBLKEBABSOSYAMKECIL[#Data],2,FALSE) -> AYAM SUWIR | H13: =VLOOKUP(TBLBAHANKELUAR[[#This Row],[NAMA BAHAN]],TBLREKAPBAHAN[[NAMA BAHAN]:[MODAL SATUAN]],2,FALSE) -> 45000 | I13: =VLOOKUP(TBLBAHANKELUAR[[#This Row],[NAMA BAHAN]],TBLREKAPBAHAN[[NAMA BAHAN]:[MODAL SATUAN]],3,FALSE) -> 400 | J13: =VLOOKUP(TBLBAHANKELUAR[[#This Row],[NAMA BAHAN]],TBLREKAPBAHAN[[NAMA BAHAN]:[MODAL SATUAN]],4,FALSE) -> 112.5 | K13: =VLOOKUP(TBLBAHANKELUAR[[#This Row],[KODE BAHAN]],[4]!TBLKEBABSOSYAMKECIL[#Data],8,FALSE) -> 12 | L13: =SUMIF(TBLPRODUKKELUARJUNI[NAMA PRODUK],TBLBAHANKELUAR[[#This Row],[NAMA PRODUK]],TBLPRODUKKELUARJUNI[JUMLAH TERJUAL]) -> 2 | M13: =TBLBAHANKELUAR[[#This Row],[KEB. BAHAN]]*TBLBAHANKELUAR[[#This Row],[JUMLAH KEB. BAHAN KELUAR]] -> 24 | N13: =TBLBAHANKELUAR[[#This Row],[MODAL SATUAN]]*TBLBAHANKELUAR[[#This Row],[TOTAL BAHAN KELUAR]] -> 2700
A14: 2026 | B14: JUNI | E14: KEBAB AYAM + SOSIZ (KECIL) | F14: 8 | G14: =VLOOKUP(TBLBAHANKELUAR[[#This Row],[KODE BAHAN]],[4]!TBLKEBABSOSYAMKECIL[#Data],2,FALSE) -> KULIT KEBAB 17/18 CM | H14: =VLOOKUP(TBLBAHANKELUAR[[#This Row],[NAMA BAHAN]],TBLREKAPBAHAN[[NAMA BAHAN]:[MODAL SATUAN]],2,FALSE) -> 27000 | I14: =VLOOKUP(TBLBAHANKELUAR[[#This Row],[NAMA BAHAN]],TBLREKAPBAHAN[[NAMA BAHAN]:[MODAL SATUAN]],3,FALSE) -> 20 | J14: =VLOOKUP(TBLBAHANKELUAR[[#This Row],[NAMA BAHAN]],TBLREKAPBAHAN[[NAMA BAHAN]:[MODAL SATUAN]],4,FALSE) -> 1350 | K14: =VLOOKUP(TBLBAHANKELUAR[[#This Row],[KODE BAHAN]],[4]!TBLKEBABSOSYAMKECIL[#Data],8,FALSE) -> 1 | L14: =SUMIF(TBLPRODUKKELUARJUNI[NAMA PRODUK],TBLBAHANKELUAR[[#This Row],[NAMA PRODUK]],TBLPRODUKKELUARJUNI[JUMLAH TERJUAL]) -> 2 | M14: =TBLBAHANKELUAR[[#This Row],[KEB. BAHAN]]*TBLBAHANKELUAR[[#This Row],[JUMLAH KEB. BAHAN KELUAR]] -> 2 | N14: =TBLBAHANKELUAR[[#This Row],[MODAL SATUAN]]*TBLBAHANKELUAR[[#This Row],[TOTAL BAHAN KELUAR]] -> 2700
A15: 2026 | B15: JUNI | E15: KEBAB AYAM + SOSIZ (KECIL) | F15: 9 | G15: =VLOOKUP(TBLBAHANKELUAR[[#This Row],[KODE BAHAN]],[4]!TBLKEBABSOSYAMKECIL[#Data],2,FALSE) -> SLADA | H15: =VLOOKUP(TBLBAHANKELUAR[[#This Row],[NAMA BAHAN]],TBLREKAPBAHAN[[NAMA BAHAN]:[MODAL SATUAN]],2,FALSE) -> 60000 | I15: =VLOOKUP(TBLBAHANKELUAR[[#This Row],[NAMA BAHAN]],TBLREKAPBAHAN[[NAMA BAHAN]:[MODAL SATUAN]],3,FALSE) -> 50 | J15: =VLOOKUP(TBLBAHANKELUAR[[#This Row],[NAMA BAHAN]],TBLREKAPBAHAN[[NAMA BAHAN]:[MODAL SATUAN]],4,FALSE) -> 1200 | K15: =VLOOKUP(TBLBAHANKELUAR[[#This Row],[KODE BAHAN]],[4]!TBLKEBABSOSYAMKECIL[#Data],8,FALSE) -> 1 | L15: =SUMIF(TBLPRODUKKELUARJUNI[NAMA PRODUK],TBLBAHANKELUAR[[#This Row],[NAMA PRODUK]],TBLPRODUKKELUARJUNI[JUMLAH TERJUAL]) -> 2 | M15: =TBLBAHANKELUAR[[#This Row],[KEB. BAHAN]]*TBLBAHANKELUAR[[#This Row],[JUMLAH KEB. BAHAN KELUAR]] -> 2 | N15: =TBLBAHANKELUAR[[#This Row],[MODAL SATUAN]]*TBLBAHANKELUAR[[#This Row],[TOTAL BAHAN KELUAR]] -> 2400
A16: 2026 | B16: JUNI | E16: KEBAB AYAM + SOSIZ (KECIL) | F16: 10 | G16: =VLOOKUP(TBLBAHANKELUAR[[#This Row],[KODE BAHAN]],[4]!TBLKEBABSOSYAMKECIL[#Data],2,FALSE) -> MENTEGA | H16: =VLOOKUP(TBLBAHANKELUAR[[#This Row],[NAMA BAHAN]],TBLREKAPBAHAN[[NAMA BAHAN]:[MODAL SATUAN]],2,FALSE) -> 35000 | I16: =VLOOKUP(TBLBAHANKELUAR[[#This Row],[NAMA BAHAN]],TBLREKAPBAHAN[[NAMA BAHAN]:[MODAL SATUAN]],3,FALSE) -> 1000 | J16: =VLOOKUP(TBLBAHANKELUAR[[#This Row],[NAMA BAHAN]],TBLREKAPBAHAN[[NAMA BAHAN]:[MODAL SATUAN]],4,FALSE) -> 35 | K16: =VLOOKUP(TBLBAHANKELUAR[[#This Row],[KODE BAHAN]],[4]!TBLKEBABSOSYAMKECIL[#Data],8,FALSE) -> 10 | L16: =SUMIF(TBLPRODUKKELUARJUNI[NAMA PRODUK],TBLBAHANKELUAR[[#This Row],[NAMA PRODUK]],TBLPRODUKKELUARJUNI[JUMLAH TERJUAL]) -> 2 | M16: =TBLBAHANKELUAR[[#This Row],[KEB. BAHAN]]*TBLBAHANKELUAR[[#This Row],[JUMLAH KEB. BAHAN KELUAR]] -> 20 | N16: =TBLBAHANKELUAR[[#This Row],[MODAL SATUAN]]*TBLBAHANKELUAR[[#This Row],[TOTAL BAHAN KELUAR]] -> 700
A17: 2026 | B17: JUNI | E17: KEBAB AYAM + SOSIZ (KECIL) | F17: 11 | G17: =VLOOKUP(TBLBAHANKELUAR[[#This Row],[KODE BAHAN]],[4]!TBLKEBABSOSYAMKECIL[#Data],2,FALSE) -> GAS ELPIJI | H17: =VLOOKUP(TBLBAHANKELUAR[[#This Row],[NAMA BAHAN]],TBLREKAPBAHAN[[NAMA BAHAN]:[MODAL SATUAN]],2,FALSE) -> 23000 | I17: =VLOOKUP(TBLBAHANKELUAR[[#This Row],[NAMA BAHAN]],TBLREKAPBAHAN[[NAMA BAHAN]:[MODAL SATUAN]],3,FALSE) -> 3000 | J17: =VLOOKUP(TBLBAHANKELUAR[[#This Row],[NAMA BAHAN]],TBLREKAPBAHAN[[NAMA BAHAN]:[MODAL SATUAN]],4,FALSE) -> 7.6666667 | K17: =VLOOKUP(TBLBAHANKELUAR[[#This Row],[KODE BAHAN]],[4]!TBLKEBABSOSYAMKECIL[#Data],8,FALSE) -> 10 | L17: =SUMIF(TBLPRODUKKELUARJUNI[NAMA PRODUK],TBLBAHANKELUAR[[#This Row],[NAMA PRODUK]],TBLPRODUKKELUARJUNI[JUMLAH TERJUAL]) -> 2 | M17: =TBLBAHANKELUAR[[#This Row],[KEB. BAHAN]]*TBLBAHANKELUAR[[#This Row],[JUMLAH KEB. BAHAN KELUAR]] -> 20 | N17: =TBLBAHANKELUAR[[#This Row],[MODAL SATUAN]]*TBLBAHANKELUAR[[#This Row],[TOTAL BAHAN KELUAR]] -> 153.33333
A18: 2026 | B18: JUNI | E18: KEBAB AYAM + SOSIZ (KECIL) | F18: 12 | G18: =VLOOKUP(TBLBAHANKELUAR[[#This Row],[KODE BAHAN]],[4]!TBLKEBABSOSYAMKECIL[#Data],2,FALSE) -> KERTAS KEBAB | H18: =VLOOKUP(TBLBAHANKELUAR[[#This Row],[NAMA BAHAN]],TBLREKAPBAHAN[[NAMA BAHAN]:[MODAL SATUAN]],2,FALSE) -> 25000 | I18: =VLOOKUP(TBLBAHANKELUAR[[#This Row],[NAMA BAHAN]],TBLREKAPBAHAN[[NAMA BAHAN]:[MODAL SATUAN]],3,FALSE) -> 100 | J18: =VLOOKUP(TBLBAHANKELUAR[[#This Row],[NAMA BAHAN]],TBLREKAPBAHAN[[NAMA BAHAN]:[MODAL SATUAN]],4,FALSE) -> 250 | K18: =VLOOKUP(TBLBAHANKELUAR[[#This Row],[KODE BAHAN]],[4]!TBLKEBABSOSYAMKECIL[#Data],8,FALSE) -> 1 | L18: =SUMIF(TBLPRODUKKELUARJUNI[NAMA PRODUK],TBLBAHANKELUAR[[#This Row],[NAMA PRODUK]],TBLPRODUKKELUARJUNI[JUMLAH TERJUAL]) -> 2 | M18: =TBLBAHANKELUAR[[#This Row],[KEB. BAHAN]]*TBLBAHANKELUAR[[#This Row],[JUMLAH KEB. BAHAN KELUAR]] -> 2 | N18: =TBLBAHANKELUAR[[#This Row],[MODAL SATUAN]]*TBLBAHANKELUAR[[#This Row],[TOTAL BAHAN KELUAR]] -> 500
A19: 2026 | B19: JUNI | E19: KEBAB AYAM + SOSIZ (KECIL) | F19: 13 | G19: =VLOOKUP(TBLBAHANKELUAR[[#This Row],[KODE BAHAN]],[4]!TBLKEBABSOSYAMKECIL[#Data],2,FALSE) -> KRESEK 10 CM | H19: =VLOOKUP(TBLBAHANKELUAR[[#This Row],[NAMA BAHAN]],TBLREKAPBAHAN[[NAMA BAHAN]:[MODAL SATUAN]],2,FALSE) -> 5500 | I19: =VLOOKUP(TBLBAHANKELUAR[[#This Row],[NAMA BAHAN]],TBLREKAPBAHAN[[NAMA BAHAN]:[MODAL SATUAN]],3,FALSE) -> 100 | J19: =VLOOKUP(TBLBAHANKELUAR[[#This Row],[NAMA BAHAN]],TBLREKAPBAHAN[[NAMA BAHAN]:[MODAL SATUAN]],4,FALSE) -> 55 | K19: =VLOOKUP(TBLBAHANKELUAR[[#This Row],[KODE BAHAN]],[4]!TBLKEBABSOSYAMKECIL[#Data],8,FALSE) -> 1 | L19: =SUMIF(TBLPRODUKKELUARJUNI[NAMA PRODUK],TBLBAHANKELUAR[[#This Row],[NAMA PRODUK]],TBLPRODUKKELUARJUNI[JUMLAH TERJUAL]) -> 2 | M19: =TBLBAHANKELUAR[[#This Row],[KEB. BAHAN]]*TBLBAHANKELUAR[[#This Row],[JUMLAH KEB. BAHAN KELUAR]] -> 2 | N19: =TBLBAHANKELUAR[[#This Row],[MODAL SATUAN]]*TBLBAHANKELUAR[[#This Row],[TOTAL BAHAN KELUAR]] -> 110
A20: 2026 | B20: JUNI | E20: KEBAB AYAM + SOSIZ (KECIL) PEDAS | F20: 1 | G20: =VLOOKUP(TBLBAHANKELUAR[[#This Row],[KODE BAHAN]],[4]!TBLKEBABSOSYAMKECIL[#Data],2,FALSE) -> SAOS TOMAT GRAM | H20: =VLOOKUP(TBLBAHANKELUAR[[#This Row],[NAMA BAHAN]],TBLREKAPBAHAN[[NAMA BAHAN]:[MODAL SATUAN]],2,FALSE) -> 20000 | I20: =VLOOKUP(TBLBAHANKELUAR[[#This Row],[NAMA BAHAN]],TBLREKAPBAHAN[[NAMA BAHAN]:[MODAL SATUAN]],3,FALSE) -> 1000 | J20: =VLOOKUP(TBLBAHANKELUAR[[#This Row],[NAMA BAHAN]],TBLREKAPBAHAN[[NAMA BAHAN]:[MODAL SATUAN]],4,FALSE) -> 20 | K20: =VLOOKUP(TBLBAHANKELUAR[[#This Row],[KODE BAHAN]],[4]!TBLKEBABSOSYAMKECIL[#Data],10,FALSE) -> 0 | L20: =SUMIF(TBLPRODUKKELUARJUNI[NAMA PRODUK],TBLBAHANKELUAR[[#This Row],[NAMA PRODUK]],TBLPRODUKKELUARJUNI[JUMLAH TERJUAL]) -> 3 | M20: =TBLBAHANKELUAR[[#This Row],[KEB. BAHAN]]*TBLBAHANKELUAR[[#This Row],[JUMLAH KEB. BAHAN KELUAR]] -> 0 | N20: =TBLBAHANKELUAR[[#This Row],[MODAL SATUAN]]*TBLBAHANKELUAR[[#This Row],[TOTAL BAHAN KELUAR]] -> 0
A21: 2026 | B21: JUNI | E21: KEBAB AYAM + SOSIZ (KECIL) PEDAS | F21: 2 | G21: =VLOOKUP(TBLBAHANKELUAR[[#This Row],[KODE BAHAN]],[4]!TBLKEBABSOSYAMKECIL[#Data],2,FALSE) -> SAOS SAMBAL GRAM | H21: =VLOOKUP(TBLBAHANKELUAR[[#This Row],[NAMA BAHAN]],TBLREKAPBAHAN[[NAMA BAHAN]:[MODAL SATUAN]],2,FALSE) -> 18000 | I21: =VLOOKUP(TBLBAHANKELUAR[[#This Row],[NAMA BAHAN]],TBLREKAPBAHAN[[NAMA BAHAN]:[MODAL SATUAN]],3,FALSE) -> 1000 | J21: =VLOOKUP(TBLBAHANKELUAR[[#This Row],[NAMA BAHAN]],TBLREKAPBAHAN[[NAMA BAHAN]:[MODAL SATUAN]],4,FALSE) -> 18 | K21: =VLOOKUP(TBLBAHANKELUAR[[#This Row],[KODE BAHAN]],[4]!TBLKEBABSOSYAMKECIL[#Data],10,FALSE) -> 15 | L21: =SUMIF(TBLPRODUKKELUARJUNI[NAMA PRODUK],TBLBAHANKELUAR[[#This Row],[NAMA PRODUK]],TBLPRODUKKELUARJUNI[JUMLAH TERJUAL]) -> 3 | M21: =TBLBAHANKELUAR[[#This Row],[KEB. BAHAN]]*TBLBAHANKELUAR[[#This Row],[JUMLAH KEB. BAHAN KELUAR]] -> 45 | N21: =TBLBAHANKELUAR[[#This Row],[MODAL SATUAN]]*TBLBAHANKELUAR[[#This Row],[TOTAL BAHAN KELUAR]] -> 810
A22: 2026 | B22: JUNI | E22: KEBAB AYAM + SOSIZ (KECIL) PEDAS | F22: 3 | G22: =VLOOKUP(TBLBAHANKELUAR[[#This Row],[KODE BAHAN]],[4]!TBLKEBABSOSYAMKECIL[#Data],2,FALSE) -> SAOS BBQ GRAM | H22: =VLOOKUP(TBLBAHANKELUAR[[#This Row],[NAMA BAHAN]],TBLREKAPBAHAN[[NAMA BAHAN]:[MODAL SATUAN]],2,FALSE) -> 12000 | I22: =VLOOKUP(TBLBAHANKELUAR[[#This Row],[NAMA BAHAN]],TBLREKAPBAHAN[[NAMA BAHAN]:[MODAL SATUAN]],3,FALSE) -> 250 | J22: =VLOOKUP(TBLBAHANKELUAR[[#This Row],[NAMA BAHAN]],TBLREKAPBAHAN[[NAMA BAHAN]:[MODAL SATUAN]],4,FALSE) -> 48 | K22: =VLOOKUP(TBLBAHANKELUAR[[#This Row],[KODE BAHAN]],[4]!TBLKEBABSOSYAMKECIL[#Data],10,FALSE) -> 5 | L22: =SUMIF(TBLPRODUKKELUARJUNI[NAMA PRODUK],TBLBAHANKELUAR[[#This Row],[NAMA PRODUK]],TBLPRODUKKELUARJUNI[JUMLAH TERJUAL]) -> 3 | M22: =TBLBAHANKELUAR[[#This Row],[KEB. BAHAN]]*TBLBAHANKELUAR[[#This Row],[JUMLAH KEB. BAHAN KELUAR]] -> 15 | N22: =TBLBAHANKELUAR[[#This Row],[MODAL SATUAN]]*TBLBAHANKELUAR[[#This Row],[TOTAL BAHAN KELUAR]] -> 720
A23: 2026 | B23: JUNI | E23: KEBAB AYAM + SOSIZ (KECIL) PEDAS | F23: 4 | G23: =VLOOKUP(TBLBAHANKELUAR[[#This Row],[KODE BAHAN]],[4]!TBLKEBABSOSYAMKECIL[#Data],2,FALSE) -> MAYONAIS GRAM | H23: =VLOOKUP(TBLBAHANKELUAR[[#This Row],[NAMA BAHAN]],TBLREKAPBAHAN[[NAMA BAHAN]:[MODAL SATUAN]],2,FALSE) -> 50000 | I23: =VLOOKUP(TBLBAHANKELUAR[[#This Row],[NAMA BAHAN]],TBLREKAPBAHAN[[NAMA BAHAN]:[MODAL SATUAN]],3,FALSE) -> 1000 | J23: =VLOOKUP(TBLBAHANKELUAR[[#This Row],[NAMA BAHAN]],TBLREKAPBAHAN[[NAMA BAHAN]:[MODAL SATUAN]],4,FALSE) -> 50 | K23: =VLOOKUP(TBLBAHANKELUAR[[#This Row],[KODE BAHAN]],[4]!TBLKEBABSOSYAMKECIL[#Data],10,FALSE) -> 7 | L23: =SUMIF(TBLPRODUKKELUARJUNI[NAMA PRODUK],TBLBAHANKELUAR[[#This Row],[NAMA PRODUK]],TBLPRODUKKELUARJUNI[JUMLAH TERJUAL]) -> 3 | M23: =TBLBAHANKELUAR[[#This Row],[KEB. BAHAN]]*TBLBAHANKELUAR[[#This Row],[JUMLAH KEB. BAHAN KELUAR]] -> 21 | N23: =TBLBAHANKELUAR[[#This Row],[MODAL SATUAN]]*TBLBAHANKELUAR[[#This Row],[TOTAL BAHAN KELUAR]] -> 1050
A24: 2026 | B24: JUNI | E24: KEBAB AYAM + SOSIZ (KECIL) PEDAS | F24: 5 | G24: =VLOOKUP(TBLBAHANKELUAR[[#This Row],[KODE BAHAN]],[4]!TBLKEBABSOSYAMKECIL[#Data],2,FALSE) -> SAOS SPAGHETI GRAM | H24: =VLOOKUP(TBLBAHANKELUAR[[#This Row],[NAMA BAHAN]],TBLREKAPBAHAN[[NAMA BAHAN]:[MODAL SATUAN]],2,FALSE) -> 12000 | I24: =VLOOKUP(TBLBAHANKELUAR[[#This Row],[NAMA BAHAN]],TBLREKAPBAHAN[[NAMA BAHAN]:[MODAL SATUAN]],3,FALSE) -> 250 | J24: =VLOOKUP(TBLBAHANKELUAR[[#This Row],[NAMA BAHAN]],TBLREKAPBAHAN[[NAMA BAHAN]:[MODAL SATUAN]],4,FALSE) -> 48 | K24: =VLOOKUP(TBLBAHANKELUAR[[#This Row],[KODE BAHAN]],[4]!TBLKEBABSOSYAMKECIL[#Data],10,FALSE) -> 5 | L24: =SUMIF(TBLPRODUKKELUARJUNI[NAMA PRODUK],TBLBAHANKELUAR[[#This Row],[NAMA PRODUK]],TBLPRODUKKELUARJUNI[JUMLAH TERJUAL]) -> 3 | M24: =TBLBAHANKELUAR[[#This Row],[KEB. BAHAN]]*TBLBAHANKELUAR[[#This Row],[JUMLAH KEB. BAHAN KELUAR]] -> 15 | N24: =TBLBAHANKELUAR[[#This Row],[MODAL SATUAN]]*TBLBAHANKELUAR[[#This Row],[TOTAL BAHAN KELUAR]] -> 720
A25: 2026 | B25: JUNI | E25: KEBAB AYAM + SOSIZ (KECIL) PEDAS | F25: 6 | G25: =VLOOKUP(TBLBAHANKELUAR[[#This Row],[KODE BAHAN]],[4]!TBLKEBABSOSYAMKECIL[#Data],2,FALSE) -> SOSIZ BATANG | H25: =VLOOKUP(TBLBAHANKELUAR[[#This Row],[NAMA BAHAN]],TBLREKAPBAHAN[[NAMA BAHAN]:[MODAL SATUAN]],2,FALSE) -> 35000 | I25: =VLOOKUP(TBLBAHANKELUAR[[#This Row],[NAMA BAHAN]],TBLREKAPBAHAN[[NAMA BAHAN]:[MODAL SATUAN]],3,FALSE) -> 38 | J25: =VLOOKUP(TBLBAHANKELUAR[[#This Row],[NAMA BAHAN]],TBLREKAPBAHAN[[NAMA BAHAN]:[MODAL SATUAN]],4,FALSE) -> 921.05263 | K25: =VLOOKUP(TBLBAHANKELUAR[[#This Row],[KODE BAHAN]],[4]!TBLKEBABSOSYAMKECIL[#Data],10,FALSE) -> 0.5 | L25: =SUMIF(TBLPRODUKKELUARJUNI[NAMA PRODUK],TBLBAHANKELUAR[[#This Row],[NAMA PRODUK]],TBLPRODUKKELUARJUNI[JUMLAH TERJUAL]) -> 3 | M25: =TBLBAHANKELUAR[[#This Row],[KEB. BAHAN]]*TBLBAHANKELUAR[[#This Row],[JUMLAH KEB. BAHAN KELUAR]] -> 1.5 | N25: =TBLBAHANKELUAR[[#This Row],[MODAL SATUAN]]*TBLBAHANKELUAR[[#This Row],[TOTAL BAHAN KELUAR]] -> 1381.5789
A26: 2026 | B26: JUNI | E26: KEBAB AYAM + SOSIZ (KECIL) PEDAS | F26: 7 | G26: =VLOOKUP(TBLBAHANKELUAR[[#This Row],[KODE BAHAN]],[4]!TBLKEBABSOSYAMKECIL[#Data],2,FALSE) -> AYAM SUWIR | H26: =VLOOKUP(TBLBAHANKELUAR[[#This Row],[NAMA BAHAN]],TBLREKAPBAHAN[[NAMA BAHAN]:[MODAL SATUAN]],2,FALSE) -> 45000 | I26: =VLOOKUP(TBLBAHANKELUAR[[#This Row],[NAMA BAHAN]],TBLREKAPBAHAN[[NAMA BAHAN]:[MODAL SATUAN]],3,FALSE) -> 400 | J26: =VLOOKUP(TBLBAHANKELUAR[[#This Row],[NAMA BAHAN]],TBLREKAPBAHAN[[NAMA BAHAN]:[MODAL SATUAN]],4,FALSE) -> 112.5 | K26: =VLOOKUP(TBLBAHANKELUAR[[#This Row],[KODE BAHAN]],[4]!TBLKEBABSOSYAMKECIL[#Data],10,FALSE) -> 12 | L26: =SUMIF(TBLPRODUKKELUARJUNI[NAMA PRODUK],TBLBAHANKELUAR[[#This Row],[NAMA PRODUK]],TBLPRODUKKELUARJUNI[JUMLAH TERJUAL]) -> 3 | M26: =TBLBAHANKELUAR[[#This Row],[KEB. BAHAN]]*TBLBAHANKELUAR[[#This Row],[JUMLAH KEB. BAHAN KELUAR]] -> 36 | N26: =TBLBAHANKELUAR[[#This Row],[MODAL SATUAN]]*TBLBAHANKELUAR[[#This Row],[TOTAL BAHAN KELUAR]] -> 4050
A27: 2026 | B27: JUNI | E27: KEBAB AYAM + SOSIZ (KECIL) PEDAS | F27: 8 | G27: =VLOOKUP(TBLBAHANKELUAR[[#This Row],[KODE BAHAN]],[4]!TBLKEBABSOSYAMKECIL[#Data],2,FALSE) -> KULIT KEBAB 17/18 CM | H27: =VLOOKUP(TBLBAHANKELUAR[[#This Row],[NAMA BAHAN]],TBLREKAPBAHAN[[NAMA BAHAN]:[MODAL SATUAN]],2,FALSE) -> 27000 | I27: =VLOOKUP(TBLBAHANKELUAR[[#This Row],[NAMA BAHAN]],TBLREKAPBAHAN[[NAMA BAHAN]:[MODAL SATUAN]],3,FALSE) -> 20 | J27: =VLOOKUP(TBLBAHANKELUAR[[#This Row],[NAMA BAHAN]],TBLREKAPBAHAN[[NAMA BAHAN]:[MODAL SATUAN]],4,FALSE) -> 1350 | K27: =VLOOKUP(TBLBAHANKELUAR[[#This Row],[KODE BAHAN]],[4]!TBLKEBABSOSYAMKECIL[#Data],10,FALSE) -> 1 | L27: =SUMIF(TBLPRODUKKELUARJUNI[NAMA PRODUK],TBLBAHANKELUAR[[#This Row],[NAMA PRODUK]],TBLPRODUKKELUARJUNI[JUMLAH TERJUAL]) -> 3 | M27: =TBLBAHANKELUAR[[#This Row],[KEB. BAHAN]]*TBLBAHANKELUAR[[#This Row],[JUMLAH KEB. BAHAN KELUAR]] -> 3 | N27: =TBLBAHANKELUAR[[#This Row],[MODAL SATUAN]]*TBLBAHANKELUAR[[#This Row],[TOTAL BAHAN KELUAR]] -> 4050
A28: 2026 | B28: JUNI | E28: KEBAB AYAM + SOSIZ (KECIL) PEDAS | F28: 9 | G28: =VLOOKUP(TBLBAHANKELUAR[[#This Row],[KODE BAHAN]],[4]!TBLKEBABSOSYAMKECIL[#Data],2,FALSE) -> SLADA | H28: =VLOOKUP(TBLBAHANKELUAR[[#This Row],[NAMA BAHAN]],TBLREKAPBAHAN[[NAMA BAHAN]:[MODAL SATUAN]],2,FALSE) -> 60000 | I28: =VLOOKUP(TBLBAHANKELUAR[[#This Row],[NAMA BAHAN]],TBLREKAPBAHAN[[NAMA BAHAN]:[MODAL SATUAN]],3,FALSE) -> 50 | J28: =VLOOKUP(TBLBAHANKELUAR[[#This Row],[NAMA BAHAN]],TBLREKAPBAHAN[[NAMA BAHAN]:[MODAL SATUAN]],4,FALSE) -> 1200 | K28: =VLOOKUP(TBLBAHANKELUAR[[#This Row],[KODE BAHAN]],[4]!TBLKEBABSOSYAMKECIL[#Data],10,FALSE) -> 1 | L28: =SUMIF(TBLPRODUKKELUARJUNI[NAMA PRODUK],TBLBAHANKELUAR[[#This Row],[NAMA PRODUK]],TBLPRODUKKELUARJUNI[JUMLAH TERJUAL]) -> 3 | M28: =TBLBAHANKELUAR[[#This Row],[KEB. BAHAN]]*TBLBAHANKELUAR[[#This Row],[JUMLAH KEB. BAHAN KELUAR]] -> 3 | N28: =TBLBAHANKELUAR[[#This Row],[MODAL SATUAN]]*TBLBAHANKELUAR[[#This Row],[TOTAL BAHAN KELUAR]] -> 3600
A29: 2026 | B29: JUNI | E29: KEBAB AYAM + SOSIZ (KECIL) PEDAS | F29: 10 | G29: =VLOOKUP(TBLBAHANKELUAR[[#This Row],[KODE BAHAN]],[4]!TBLKEBABSOSYAMKECIL[#Data],2,FALSE) -> MENTEGA | H29: =VLOOKUP(TBLBAHANKELUAR[[#This Row],[NAMA BAHAN]],TBLREKAPBAHAN[[NAMA BAHAN]:[MODAL SATUAN]],2,FALSE) -> 35000 | I29: =VLOOKUP(TBLBAHANKELUAR[[#This Row],[NAMA BAHAN]],TBLREKAPBAHAN[[NAMA BAHAN]:[MODAL SATUAN]],3,FALSE) -> 1000 | J29: =VLOOKUP(TBLBAHANKELUAR[[#This Row],[NAMA BAHAN]],TBLREKAPBAHAN[[NAMA BAHAN]:[MODAL SATUAN]],4,FALSE) -> 35 | K29: =VLOOKUP(TBLBAHANKELUAR[[#This Row],[KODE BAHAN]],[4]!TBLKEBABSOSYAMKECIL[#Data],10,FALSE) -> 10 | L29: =SUMIF(TBLPRODUKKELUARJUNI[NAMA PRODUK],TBLBAHANKELUAR[[#This Row],[NAMA PRODUK]],TBLPRODUKKELUARJUNI[JUMLAH TERJUAL]) -> 3 | M29: =TBLBAHANKELUAR[[#This Row],[KEB. BAHAN]]*TBLBAHANKELUAR[[#This Row],[JUMLAH KEB. BAHAN KELUAR]] -> 30 | N29: =TBLBAHANKELUAR[[#This Row],[MODAL SATUAN]]*TBLBAHANKELUAR[[#This Row],[TOTAL BAHAN KELUAR]] -> 1050
A30: 2026 | B30: JUNI | E30: KEBAB AYAM + SOSIZ (KECIL) PEDAS | F30: 11 | G30: =VLOOKUP(TBLBAHANKELUAR[[#This Row],[KODE BAHAN]],[4]!TBLKEBABSOSYAMKECIL[#Data],2,FALSE) -> GAS ELPIJI | H30: =VLOOKUP(TBLBAHANKELUAR[[#This Row],[NAMA BAHAN]],TBLREKAPBAHAN[[NAMA BAHAN]:[MODAL SATUAN]],2,FALSE) -> 23000 | I30: =VLOOKUP(TBLBAHANKELUAR[[#This Row],[NAMA BAHAN]],TBLREKAPBAHAN[[NAMA BAHAN]:[MODAL SATUAN]],3,FALSE) -> 3000 | J30: =VLOOKUP(TBLBAHANKELUAR[[#This Row],[NAMA BAHAN]],TBLREKAPBAHAN[[NAMA BAHAN]:[MODAL SATUAN]],4,FALSE) -> 7.6666667 | K30: =VLOOKUP(TBLBAHANKELUAR[[#This Row],[KODE BAHAN]],[4]!TBLKEBABSOSYAMKECIL[#Data],10,FALSE) -> 10 | L30: =SUMIF(TBLPRODUKKELUARJUNI[NAMA PRODUK],TBLBAHANKELUAR[[#This Row],[NAMA PRODUK]],TBLPRODUKKELUARJUNI[JUMLAH TERJUAL]) -> 3 | M30: =TBLBAHANKELUAR[[#This Row],[KEB. BAHAN]]*TBLBAHANKELUAR[[#This Row],[JUMLAH KEB. BAHAN KELUAR]] -> 30 | N30: =TBLBAHANKELUAR[[#This Row],[MODAL SATUAN]]*TBLBAHANKELUAR[[#This Row],[TOTAL BAHAN KELUAR]] -> 230
A31: 2026 | B31: JUNI | E31: KEBAB AYAM + SOSIZ (KECIL) PEDAS | F31: 12 | G31: =VLOOKUP(TBLBAHANKELUAR[[#This Row],[KODE BAHAN]],[4]!TBLKEBABSOSYAMKECIL[#Data],2,FALSE) -> KERTAS KEBAB | H31: =VLOOKUP(TBLBAHANKELUAR[[#This Row],[NAMA BAHAN]],TBLREKAPBAHAN[[NAMA BAHAN]:[MODAL SATUAN]],2,FALSE) -> 25000 | I31: =VLOOKUP(TBLBAHANKELUAR[[#This Row],[NAMA BAHAN]],TBLREKAPBAHAN[[NAMA BAHAN]:[MODAL SATUAN]],3,FALSE) -> 100 | J31: =VLOOKUP(TBLBAHANKELUAR[[#This Row],[NAMA BAHAN]],TBLREKAPBAHAN[[NAMA BAHAN]:[MODAL SATUAN]],4,FALSE) -> 250 | K31: =VLOOKUP(TBLBAHANKELUAR[[#This Row],[KODE BAHAN]],[4]!TBLKEBABSOSYAMKECIL[#Data],10,FALSE) -> 1 | L31: =SUMIF(TBLPRODUKKELUARJUNI[NAMA PRODUK],TBLBAHANKELUAR[[#This Row],[NAMA PRODUK]],TBLPRODUKKELUARJUNI[JUMLAH TERJUAL]) -> 3 | M31: =TBLBAHANKELUAR[[#This Row],[KEB. BAHAN]]*TBLBAHANKELUAR[[#This Row],[JUMLAH KEB. BAHAN KELUAR]] -> 3 | N31: =TBLBAHANKELUAR[[#This Row],[MODAL SATUAN]]*TBLBAHANKELUAR[[#This Row],[TOTAL BAHAN KELUAR]] -> 750
A32: 2026 | B32: JUNI | E32: KEBAB AYAM + SOSIZ (KECIL) PEDAS | F32: 13 | G32: =VLOOKUP(TBLBAHANKELUAR[[#This Row],[KODE BAHAN]],[4]!TBLKEBABSOSYAMKECIL[#Data],2,FALSE) -> KRESEK 10 CM | H32: =VLOOKUP(TBLBAHANKELUAR[[#This Row],[NAMA BAHAN]],TBLREKAPBAHAN[[NAMA BAHAN]:[MODAL SATUAN]],2,FALSE) -> 5500 | I32: =VLOOKUP(TBLBAHANKELUAR[[#This Row],[NAMA BAHAN]],TBLREKAPBAHAN[[NAMA BAHAN]:[MODAL SATUAN]],3,FALSE) -> 100 | J32: =VLOOKUP(TBLBAHANKELUAR[[#This Row],[NAMA BAHAN]],TBLREKAPBAHAN[[NAMA BAHAN]:[MODAL SATUAN]],4,FALSE) -> 55 | K32: =VLOOKUP(TBLBAHANKELUAR[[#This Row],[KODE BAHAN]],[4]!TBLKEBABSOSYAMKECIL[#Data],10,FALSE) -> 1 | L32: =SUMIF(TBLPRODUKKELUARJUNI[NAMA PRODUK],TBLBAHANKELUAR[[#This Row],[NAMA PRODUK]],TBLPRODUKKELUARJUNI[JUMLAH TERJUAL]) -> 3 | M32: =TBLBAHANKELUAR[[#This Row],[KEB. BAHAN]]*TBLBAHANKELUAR[[#This Row],[JUMLAH KEB. BAHAN KELUAR]] -> 3 | N32: =TBLBAHANKELUAR[[#This Row],[MODAL SATUAN]]*TBLBAHANKELUAR[[#This Row],[TOTAL BAHAN KELUAR]] -> 165
A33: 2026 | B33: JUNI | E33: KEBAB AYAM + SOSIZ (MEDIUM) PEDAS | F33: 1 | G33: =VLOOKUP(TBLBAHANKELUAR[[#This Row],[KODE BAHAN]],[4]!TBLKEBABSOSYAMMEDIUM[#Data],2,FALSE) -> SAOS TOMAT GRAM | H33: =VLOOKUP(TBLBAHANKELUAR[[#This Row],[NAMA BAHAN]],TBLREKAPBAHAN[[NAMA BAHAN]:[MODAL SATUAN]],2,FALSE) -> 20000 | I33: =VLOOKUP(TBLBAHANKELUAR[[#This Row],[NAMA BAHAN]],TBLREKAPBAHAN[[NAMA BAHAN]:[MODAL SATUAN]],3,FALSE) -> 1000 | J33: =VLOOKUP(TBLBAHANKELUAR[[#This Row],[NAMA BAHAN]],TBLREKAPBAHAN[[NAMA BAHAN]:[MODAL SATUAN]],4,FALSE) -> 20 | K33: =VLOOKUP(TBLBAHANKELUAR[[#This Row],[KODE BAHAN]],[4]!TBLKEBABSOSYAMMEDIUM[#Data],10,FALSE) -> 0 | L33: =SUMIF(TBLPRODUKKELUARJUNI[NAMA PRODUK],TBLBAHANKELUAR[[#This Row],[NAMA PRODUK]],TBLPRODUKKELUARJUNI[JUMLAH TERJUAL]) -> 2 | M33: =TBLBAHANKELUAR[[#This Row],[KEB. BAHAN]]*TBLBAHANKELUAR[[#This Row],[JUMLAH KEB. BAHAN KELUAR]] -> 0 | N33: =TBLBAHANKELUAR[[#This Row],[MODAL SATUAN]]*TBLBAHANKELUAR[[#This Row],[TOTAL BAHAN KELUAR]] -> 0
A34: 2026 | B34: JUNI | E34: KEBAB AYAM + SOSIZ (MEDIUM) PEDAS | F34: 2 | G34: =VLOOKUP(TBLBAHANKELUAR[[#This Row],[KODE BAHAN]],[4]!TBLKEBABSOSYAMMEDIUM[#Data],2,FALSE) -> SAOS SAMBAL GRAM | H34: =VLOOKUP(TBLBAHANKELUAR[[#This Row],[NAMA BAHAN]],TBLREKAPBAHAN[[NAMA BAHAN]:[MODAL SATUAN]],2,FALSE) -> 18000 | I34: =VLOOKUP(TBLBAHANKELUAR[[#This Row],[NAMA BAHAN]],TBLREKAPBAHAN[[NAMA BAHAN]:[MODAL SATUAN]],3,FALSE) -> 1000 | J34: =VLOOKUP(TBLBAHANKELUAR[[#This Row],[NAMA BAHAN]],TBLREKAPBAHAN[[NAMA BAHAN]:[MODAL SATUAN]],4,FALSE) -> 18 | K34: =VLOOKUP(TBLBAHANKELUAR[[#This Row],[KODE BAHAN]],[4]!TBLKEBABSOSYAMMEDIUM[#Data],10,FALSE) -> 25 | L34: =SUMIF(TBLPRODUKKELUARJUNI[NAMA PRODUK],TBLBAHANKELUAR[[#This Row],[NAMA PRODUK]],TBLPRODUKKELUARJUNI[JUMLAH TERJUAL]) -> 2 | M34: =TBLBAHANKELUAR[[#This Row],[KEB. BAHAN]]*TBLBAHANKELUAR[[#This Row],[JUMLAH KEB. BAHAN KELUAR]] -> 50 | N34: =TBLBAHANKELUAR[[#This Row],[MODAL SATUAN]]*TBLBAHANKELUAR[[#This Row],[TOTAL BAHAN KELUAR]] -> 900
A35: 2026 | B35: JUNI | E35: KEBAB AYAM + SOSIZ (MEDIUM) PEDAS | F35: 3 | G35: =VLOOKUP(TBLBAHANKELUAR[[#This Row],[KODE BAHAN]],[4]!TBLKEBABSOSYAMMEDIUM[#Data],2,FALSE) -> SAOS BBQ GRAM | H35: =VLOOKUP(TBLBAHANKELUAR[[#This Row],[NAMA BAHAN]],TBLREKAPBAHAN[[NAMA BAHAN]:[MODAL SATUAN]],2,FALSE) -> 12000 | I35: =VLOOKUP(TBLBAHANKELUAR[[#This Row],[NAMA BAHAN]],TBLREKAPBAHAN[[NAMA BAHAN]:[MODAL SATUAN]],3,FALSE) -> 250 | J35: =VLOOKUP(TBLBAHANKELUAR[[#This Row],[NAMA BAHAN]],TBLREKAPBAHAN[[NAMA BAHAN]:[MODAL SATUAN]],4,FALSE) -> 48 | K35: =VLOOKUP(TBLBAHANKELUAR[[#This Row],[KODE BAHAN]],[4]!TBLKEBABSOSYAMMEDIUM[#Data],10,FALSE) -> 7 | L35: =SUMIF(TBLPRODUKKELUARJUNI[NAMA PRODUK],TBLBAHANKELUAR[[#This Row],[NAMA PRODUK]],TBLPRODUKKELUARJUNI[JUMLAH TERJUAL]) -> 2 | M35: =TBLBAHANKELUAR[[#This Row],[KEB. BAHAN]]*TBLBAHANKELUAR[[#This Row],[JUMLAH KEB. BAHAN KELUAR]] -> 14 | N35: =TBLBAHANKELUAR[[#This Row],[MODAL SATUAN]]*TBLBAHANKELUAR[[#This Row],[TOTAL BAHAN KELUAR]] -> 672
A36: 2026 | B36: JUNI | E36: KEBAB AYAM + SOSIZ (MEDIUM) PEDAS | F36: 4 | G36: =VLOOKUP(TBLBAHANKELUAR[[#This Row],[KODE BAHAN]],[4]!TBLKEBABSOSYAMMEDIUM[#Data],2,FALSE) -> MAYONAIS GRAM | H36: =VLOOKUP(TBLBAHANKELUAR[[#This Row],[NAMA BAHAN]],TBLREKAPBAHAN[[NAMA BAHAN]:[MODAL SATUAN]],2,FALSE) -> 50000 | I36: =VLOOKUP(TBLBAHANKELUAR[[#This Row],[NAMA BAHAN]],TBLREKAPBAHAN[[NAMA BAHAN]:[MODAL SATUAN]],3,FALSE) -> 1000 | J36: =VLOOKUP(TBLBAHANKELUAR[[#This Row],[NAMA BAHAN]],TBLREKAPBAHAN[[NAMA BAHAN]:[MODAL SATUAN]],4,FALSE) -> 50 | K36: =VLOOKUP(TBLBAHANKELUAR[[#This Row],[KODE BAHAN]],[4]!TBLKEBABSOSYAMMEDIUM[#Data],10,FALSE) -> 10 | L36: =SUMIF(TBLPRODUKKELUARJUNI[NAMA PRODUK],TBLBAHANKELUAR[[#This Row],[NAMA PRODUK]],TBLPRODUKKELUARJUNI[JUMLAH TERJUAL]) -> 2 | M36: =TBLBAHANKELUAR[[#This Row],[KEB. BAHAN]]*TBLBAHANKELUAR[[#This Row],[JUMLAH KEB. BAHAN KELUAR]] -> 20 | N36: =TBLBAHANKELUAR[[#This Row],[MODAL SATUAN]]*TBLBAHANKELUAR[[#This Row],[TOTAL BAHAN KELUAR]] -> 1000
A37: 2026 | B37: JUNI | E37: KEBAB AYAM + SOSIZ (MEDIUM) PEDAS | F37: 5 | G37: =VLOOKUP(TBLBAHANKELUAR[[#This Row],[KODE BAHAN]],[4]!TBLKEBABSOSYAMMEDIUM[#Data],2,FALSE) -> SAOS SPAGHETI GRAM | H37: =VLOOKUP(TBLBAHANKELUAR[[#This Row],[NAMA BAHAN]],TBLREKAPBAHAN[[NAMA BAHAN]:[MODAL SATUAN]],2,FALSE) -> 12000 | I37: =VLOOKUP(TBLBAHANKELUAR[[#This Row],[NAMA BAHAN]],TBLREKAPBAHAN[[NAMA BAHAN]:[MODAL SATUAN]],3,FALSE) -> 250 | J37: =VLOOKUP(TBLBAHANKELUAR[[#This Row],[NAMA BAHAN]],TBLREKAPBAHAN[[NAMA BAHAN]:[MODAL SATUAN]],4,FALSE) -> 48 | K37: =VLOOKUP(TBLBAHANKELUAR[[#This Row],[KODE BAHAN]],[4]!TBLKEBABSOSYAMMEDIUM[#Data],10,FALSE) -> 7 | L37: =SUMIF(TBLPRODUKKELUARJUNI[NAMA PRODUK],TBLBAHANKELUAR[[#This Row],[NAMA PRODUK]],TBLPRODUKKELUARJUNI[JUMLAH TERJUAL]) -> 2 | M37: =TBLBAHANKELUAR[[#This Row],[KEB. BAHAN]]*TBLBAHANKELUAR[[#This Row],[JUMLAH KEB. BAHAN KELUAR]] -> 14 | N37: =TBLBAHANKELUAR[[#This Row],[MODAL SATUAN]]*TBLBAHANKELUAR[[#This Row],[TOTAL BAHAN KELUAR]] -> 672
A38: 2026 | B38: JUNI | E38: KEBAB AYAM + SOSIZ (MEDIUM) PEDAS | F38: 6 | G38: =VLOOKUP(TBLBAHANKELUAR[[#This Row],[KODE BAHAN]],[4]!TBLKEBABSOSYAMMEDIUM[#Data],2,FALSE) -> SOSIZ BATANG | H38: =VLOOKUP(TBLBAHANKELUAR[[#This Row],[NAMA BAHAN]],TBLREKAPBAHAN[[NAMA BAHAN]:[MODAL SATUAN]],2,FALSE) -> 35000 | I38: =VLOOKUP(TBLBAHANKELUAR[[#This Row],[NAMA BAHAN]],TBLREKAPBAHAN[[NAMA BAHAN]:[MODAL SATUAN]],3,FALSE) -> 38 | J38: =VLOOKUP(TBLBAHANKELUAR[[#This Row],[NAMA BAHAN]],TBLREKAPBAHAN[[NAMA BAHAN]:[MODAL SATUAN]],4,FALSE) -> 921.05263 | K38: =VLOOKUP(TBLBAHANKELUAR[[#This Row],[KODE BAHAN]],[4]!TBLKEBABSOSYAMMEDIUM[#Data],10,FALSE) -> 1 | L38: =SUMIF(TBLPRODUKKELUARJUNI[NAMA PRODUK],TBLBAHANKELUAR[[#This Row],[NAMA PRODUK]],TBLPRODUKKELUARJUNI[JUMLAH TERJUAL]) -> 2 | M38: =TBLBAHANKELUAR[[#This Row],[KEB. BAHAN]]*TBLBAHANKELUAR[[#This Row],[JUMLAH KEB. BAHAN KELUAR]] -> 2 | N38: =TBLBAHANKELUAR[[#This Row],[MODAL SATUAN]]*TBLBAHANKELUAR[[#This Row],[TOTAL BAHAN KELUAR]] -> 1842.1053
A39: 2026 | B39: JUNI | E39: KEBAB AYAM + SOSIZ (MEDIUM) PEDAS | F39: 7 | G39: =VLOOKUP(TBLBAHANKELUAR[[#This Row],[KODE BAHAN]],[4]!TBLKEBABSOSYAMMEDIUM[#Data],2,FALSE) -> AYAM SUWIR | H39: =VLOOKUP(TBLBAHANKELUAR[[#This Row],[NAMA BAHAN]],TBLREKAPBAHAN[[NAMA BAHAN]:[MODAL SATUAN]],2,FALSE) -> 45000 | I39: =VLOOKUP(TBLBAHANKELUAR[[#This Row],[NAMA BAHAN]],TBLREKAPBAHAN[[NAMA BAHAN]:[MODAL SATUAN]],3,FALSE) -> 400 | J39: =VLOOKUP(TBLBAHANKELUAR[[#This Row],[NAMA BAHAN]],TBLREKAPBAHAN[[NAMA BAHAN]:[MODAL SATUAN]],4,FALSE) -> 112.5 | K39: =VLOOKUP(TBLBAHANKELUAR[[#This Row],[KODE BAHAN]],[4]!TBLKEBABSOSYAMMEDIUM[#Data],10,FALSE) -> 20 | L39: =SUMIF(TBLPRODUKKELUARJUNI[NAMA PRODUK],TBLBAHANKELUAR[[#This Row],[NAMA PRODUK]],TBLPRODUKKELUARJUNI[JUMLAH TERJUAL]) -> 2 | M39: =TBLBAHANKELUAR[[#This Row],[KEB. BAHAN]]*TBLBAHANKELUAR[[#This Row],[JUMLAH KEB. BAHAN KELUAR]] -> 40 | N39: =TBLBAHANKELUAR[[#This Row],[MODAL SATUAN]]*TBLBAHANKELUAR[[#This Row],[TOTAL BAHAN KELUAR]] -> 4500
A40: 2026 | B40: JUNI | E40: KEBAB AYAM + SOSIZ (MEDIUM) PEDAS | F40: 8 | G40: =VLOOKUP(TBLBAHANKELUAR[[#This Row],[KODE BAHAN]],[4]!TBLKEBABSOSYAMMEDIUM[#Data],2,FALSE) -> KULIT KEBAB 19/20 CM | H40: =VLOOKUP(TBLBAHANKELUAR[[#This Row],[NAMA BAHAN]],TBLREKAPBAHAN[[NAMA BAHAN]:[MODAL SATUAN]],2,FALSE) -> 29000 | I40: =VLOOKUP(TBLBAHANKELUAR[[#This Row],[NAMA BAHAN]],TBLREKAPBAHAN[[NAMA BAHAN]:[MODAL SATUAN]],3,FALSE) -> 20 | J40: =VLOOKUP(TBLBAHANKELUAR[[#This Row],[NAMA BAHAN]],TBLREKAPBAHAN[[NAMA BAHAN]:[MODAL SATUAN]],4,FALSE) -> 1450 | K40: =VLOOKUP(TBLBAHANKELUAR[[#This Row],[KODE BAHAN]],[4]!TBLKEBABSOSYAMMEDIUM[#Data],10,FALSE) -> 1 | L40: =SUMIF(TBLPRODUKKELUARJUNI[NAMA PRODUK],TBLBAHANKELUAR[[#This Row],[NAMA PRODUK]],TBLPRODUKKELUARJUNI[JUMLAH TERJUAL]) -> 2 | M40: =TBLBAHANKELUAR[[#This Row],[KEB. BAHAN]]*TBLBAHANKELUAR[[#This Row],[JUMLAH KEB. BAHAN KELUAR]] -> 2 | N40: =TBLBAHANKELUAR[[#This Row],[MODAL SATUAN]]*TBLBAHANKELUAR[[#This Row],[TOTAL BAHAN KELUAR]] -> 2900
A41: 2026 | B41: JUNI | E41: KEBAB AYAM + SOSIZ (MEDIUM) PEDAS | F41: 9 | G41: =VLOOKUP(TBLBAHANKELUAR[[#This Row],[KODE BAHAN]],[4]!TBLKEBABSOSYAMMEDIUM[#Data],2,FALSE) -> SLADA | H41: =VLOOKUP(TBLBAHANKELUAR[[#This Row],[NAMA BAHAN]],TBLREKAPBAHAN[[NAMA BAHAN]:[MODAL SATUAN]],2,FALSE) -> 60000 | I41: =VLOOKUP(TBLBAHANKELUAR[[#This Row],[NAMA BAHAN]],TBLREKAPBAHAN[[NAMA BAHAN]:[MODAL SATUAN]],3,FALSE) -> 50 | J41: =VLOOKUP(TBLBAHANKELUAR[[#This Row],[NAMA BAHAN]],TBLREKAPBAHAN[[NAMA BAHAN]:[MODAL SATUAN]],4,FALSE) -> 1200 | K41: =VLOOKUP(TBLBAHANKELUAR[[#This Row],[KODE BAHAN]],[4]!TBLKEBABSOSYAMMEDIUM[#Data],10,FALSE) -> 1 | L41: =SUMIF(TBLPRODUKKELUARJUNI[NAMA PRODUK],TBLBAHANKELUAR[[#This Row],[NAMA PRODUK]],TBLPRODUKKELUARJUNI[JUMLAH TERJUAL]) -> 2 | M41: =TBLBAHANKELUAR[[#This Row],[KEB. BAHAN]]*TBLBAHANKELUAR[[#This Row],[JUMLAH KEB. BAHAN KELUAR]] -> 2 | N41: =TBLBAHANKELUAR[[#This Row],[MODAL SATUAN]]*TBLBAHANKELUAR[[#This Row],[TOTAL BAHAN KELUAR]] -> 2400
A42: 2026 | B42: JUNI | E42: KEBAB AYAM + SOSIZ (MEDIUM) PEDAS | F42: 10 | G42: =VLOOKUP(TBLBAHANKELUAR[[#This Row],[KODE BAHAN]],[4]!TBLKEBABSOSYAMMEDIUM[#Data],2,FALSE) -> MENTEGA | H42: =VLOOKUP(TBLBAHANKELUAR[[#This Row],[NAMA BAHAN]],TBLREKAPBAHAN[[NAMA BAHAN]:[MODAL SATUAN]],2,FALSE) -> 35000 | I42: =VLOOKUP(TBLBAHANKELUAR[[#This Row],[NAMA BAHAN]],TBLREKAPBAHAN[[NAMA BAHAN]:[MODAL SATUAN]],3,FALSE) -> 1000 | J42: =VLOOKUP(TBLBAHANKELUAR[[#This Row],[NAMA BAHAN]],TBLREKAPBAHAN[[NAMA BAHAN]:[MODAL SATUAN]],4,FALSE) -> 35 | K42: =VLOOKUP(TBLBAHANKELUAR[[#This Row],[KODE BAHAN]],[4]!TBLKEBABSOSYAMMEDIUM[#Data],10,FALSE) -> 10 | L42: =SUMIF(TBLPRODUKKELUARJUNI[NAMA PRODUK],TBLBAHANKELUAR[[#This Row],[NAMA PRODUK]],TBLPRODUKKELUARJUNI[JUMLAH TERJUAL]) -> 2 | M42: =TBLBAHANKELUAR[[#This Row],[KEB. BAHAN]]*TBLBAHANKELUAR[[#This Row],[JUMLAH KEB. BAHAN KELUAR]] -> 20 | N42: =TBLBAHANKELUAR[[#This Row],[MODAL SATUAN]]*TBLBAHANKELUAR[[#This Row],[TOTAL BAHAN KELUAR]] -> 700
A43: 2026 | B43: JUNI | E43: KEBAB AYAM + SOSIZ (MEDIUM) PEDAS | F43: 11 | G43: =VLOOKUP(TBLBAHANKELUAR[[#This Row],[KODE BAHAN]],[4]!TBLKEBABSOSYAMMEDIUM[#Data],2,FALSE) -> GAS ELPIJI | H43: =VLOOKUP(TBLBAHANKELUAR[[#This Row],[NAMA BAHAN]],TBLREKAPBAHAN[[NAMA BAHAN]:[MODAL SATUAN]],2,FALSE) -> 23000 | I43: =VLOOKUP(TBLBAHANKELUAR[[#This Row],[NAMA BAHAN]],TBLREKAPBAHAN[[NAMA BAHAN]:[MODAL SATUAN]],3,FALSE) -> 3000 | J43: =VLOOKUP(TBLBAHANKELUAR[[#This Row],[NAMA BAHAN]],TBLREKAPBAHAN[[NAMA BAHAN]:[MODAL SATUAN]],4,FALSE) -> 7.6666667 | K43: =VLOOKUP(TBLBAHANKELUAR[[#This Row],[KODE BAHAN]],[4]!TBLKEBABSOSYAMMEDIUM[#Data],10,FALSE) -> 10 | L43: =SUMIF(TBLPRODUKKELUARJUNI[NAMA PRODUK],TBLBAHANKELUAR[[#This Row],[NAMA PRODUK]],TBLPRODUKKELUARJUNI[JUMLAH TERJUAL]) -> 2 | M43: =TBLBAHANKELUAR[[#This Row],[KEB. BAHAN]]*TBLBAHANKELUAR[[#This Row],[JUMLAH KEB. BAHAN KELUAR]] -> 20 | N43: =TBLBAHANKELUAR[[#This Row],[MODAL SATUAN]]*TBLBAHANKELUAR[[#This Row],[TOTAL BAHAN KELUAR]] -> 153.33333
A44: 2026 | B44: JUNI | E44: KEBAB AYAM + SOSIZ (MEDIUM) PEDAS | F44: 12 | G44: =VLOOKUP(TBLBAHANKELUAR[[#This Row],[KODE BAHAN]],[4]!TBLKEBABSOSYAMMEDIUM[#Data],2,FALSE) -> KERTAS KEBAB | H44: =VLOOKUP(TBLBAHANKELUAR[[#This Row],[NAMA BAHAN]],TBLREKAPBAHAN[[NAMA BAHAN]:[MODAL SATUAN]],2,FALSE) -> 25000 | I44: =VLOOKUP(TBLBAHANKELUAR[[#This Row],[NAMA BAHAN]],TBLREKAPBAHAN[[NAMA BAHAN]:[MODAL SATUAN]],3,FALSE) -> 100 | J44: =VLOOKUP(TBLBAHANKELUAR[[#This Row],[NAMA BAHAN]],TBLREKAPBAHAN[[NAMA BAHAN]:[MODAL SATUAN]],4,FALSE) -> 250 | K44: =VLOOKUP(TBLBAHANKELUAR[[#This Row],[KODE BAHAN]],[4]!TBLKEBABSOSYAMMEDIUM[#Data],10,FALSE) -> 1 | L44: =SUMIF(TBLPRODUKKELUARJUNI[NAMA PRODUK],TBLBAHANKELUAR[[#This Row],[NAMA PRODUK]],TBLPRODUKKELUARJUNI[JUMLAH TERJUAL]) -> 2 | M44: =TBLBAHANKELUAR[[#This Row],[KEB. BAHAN]]*TBLBAHANKELUAR[[#This Row],[JUMLAH KEB. BAHAN KELUAR]] -> 2 | N44: =TBLBAHANKELUAR[[#This Row],[MODAL SATUAN]]*TBLBAHANKELUAR[[#This Row],[TOTAL BAHAN KELUAR]] -> 500
A45: 2026 | B45: JUNI | E45: KEBAB AYAM + SOSIZ (MEDIUM) PEDAS | F45: 13 | G45: =VLOOKUP(TBLBAHANKELUAR[[#This Row],[KODE BAHAN]],[4]!TBLKEBABSOSYAMMEDIUM[#Data],2,FALSE) -> KRESEK 10 CM | H45: =VLOOKUP(TBLBAHANKELUAR[[#This Row],[NAMA BAHAN]],TBLREKAPBAHAN[[NAMA BAHAN]:[MODAL SATUAN]],2,FALSE) -> 5500 | I45: =VLOOKUP(TBLBAHANKELUAR[[#This Row],[NAMA BAHAN]],TBLREKAPBAHAN[[NAMA BAHAN]:[MODAL SATUAN]],3,FALSE) -> 100 | J45: =VLOOKUP(TBLBAHANKELUAR[[#This Row],[NAMA BAHAN]],TBLREKAPBAHAN[[NAMA BAHAN]:[MODAL SATUAN]],4,FALSE) -> 55 | K45: =VLOOKUP(TBLBAHANKELUAR[[#This Row],[KODE BAHAN]],[4]!TBLKEBABSOSYAMMEDIUM[#Data],10,FALSE) -> 1 | L45: =SUMIF(TBLPRODUKKELUARJUNI[NAMA PRODUK],TBLBAHANKELUAR[[#This Row],[NAMA PRODUK]],TBLPRODUKKELUARJUNI[JUMLAH TERJUAL]) -> 2 | M45: =TBLBAHANKELUAR[[#This Row],[KEB. BAHAN]]*TBLBAHANKELUAR[[#This Row],[JUMLAH KEB. BAHAN KELUAR]] -> 2 | N45: =TBLBAHANKELUAR[[#This Row],[MODAL SATUAN]]*TBLBAHANKELUAR[[#This Row],[TOTAL BAHAN KELUAR]] -> 110
A46: 2026 | B46: JUNI | E46: KEBAB AYAM MEDIUM PEDAS | F46: 1 | G46: =VLOOKUP(TBLBAHANKELUAR[[#This Row],[KODE BAHAN]],[4]!TBLKEBABAYAMMEDIUM[#Data],2,FALSE) -> SAOS TOMAT GRAM | H46: =VLOOKUP(TBLBAHANKELUAR[[#This Row],[NAMA BAHAN]],TBLREKAPBAHAN[[NAMA BAHAN]:[MODAL SATUAN]],2,FALSE) -> 20000 | I46: =VLOOKUP(TBLBAHANKELUAR[[#This Row],[NAMA BAHAN]],TBLREKAPBAHAN[[NAMA BAHAN]:[MODAL SATUAN]],3,FALSE) -> 1000 | J46: =VLOOKUP(TBLBAHANKELUAR[[#This Row],[NAMA BAHAN]],TBLREKAPBAHAN[[NAMA BAHAN]:[MODAL SATUAN]],4,FALSE) -> 20 | K46: =VLOOKUP(TBLBAHANKELUAR[[#This Row],[KODE BAHAN]],[4]!TBLKEBABAYAMMEDIUM[#Data],10,FALSE) -> 0 | L46: =SUMIF(TBLPRODUKKELUARJUNI[NAMA PRODUK],TBLBAHANKELUAR[[#This Row],[NAMA PRODUK]],TBLPRODUKKELUARJUNI[JUMLAH TERJUAL]) -> 4 | M46: =TBLBAHANKELUAR[[#This Row],[KEB. BAHAN]]*TBLBAHANKELUAR[[#This Row],[JUMLAH KEB. BAHAN KELUAR]] -> 0 | N46: =TBLBAHANKELUAR[[#This Row],[MODAL SATUAN]]*TBLBAHANKELUAR[[#This Row],[TOTAL BAHAN KELUAR]] -> 0
A47: 2026 | B47: JUNI | E47: KEBAB AYAM MEDIUM PEDAS | F47: 2 | G47: =VLOOKUP(TBLBAHANKELUAR[[#This Row],[KODE BAHAN]],[4]!TBLKEBABAYAMMEDIUM[#Data],2,FALSE) -> SAOS SAMBAL GRAM | H47: =VLOOKUP(TBLBAHANKELUAR[[#This Row],[NAMA BAHAN]],TBLREKAPBAHAN[[NAMA BAHAN]:[MODAL SATUAN]],2,FALSE) -> 18000 | I47: =VLOOKUP(TBLBAHANKELUAR[[#This Row],[NAMA BAHAN]],TBLREKAPBAHAN[[NAMA BAHAN]:[MODAL SATUAN]],3,FALSE) -> 1000 | J47: =VLOOKUP(TBLBAHANKELUAR[[#This Row],[NAMA BAHAN]],TBLREKAPBAHAN[[NAMA BAHAN]:[MODAL SATUAN]],4,FALSE) -> 18 | K47: =VLOOKUP(TBLBAHANKELUAR[[#This Row],[KODE BAHAN]],[4]!TBLKEBABAYAMMEDIUM[#Data],10,FALSE) -> 25 | L47: =SUMIF(TBLPRODUKKELUARJUNI[NAMA PRODUK],TBLBAHANKELUAR[[#This Row],[NAMA PRODUK]],TBLPRODUKKELUARJUNI[JUMLAH TERJUAL]) -> 4 | M47: =TBLBAHANKELUAR[[#This Row],[KEB. BAHAN]]*TBLBAHANKELUAR[[#This Row],[JUMLAH KEB. BAHAN KELUAR]] -> 100 | N47: =TBLBAHANKELUAR[[#This Row],[MODAL SATUAN]]*TBLBAHANKELUAR[[#This Row],[TOTAL BAHAN KELUAR]] -> 1800
A48: 2026 | B48: JUNI | E48: KEBAB AYAM MEDIUM PEDAS | F48: 3 | G48: =VLOOKUP(TBLBAHANKELUAR[[#This Row],[KODE BAHAN]],[4]!TBLKEBABAYAMMEDIUM[#Data],2,FALSE) -> SAOS BBQ GRAM | H48: =VLOOKUP(TBLBAHANKELUAR[[#This Row],[NAMA BAHAN]],TBLREKAPBAHAN[[NAMA BAHAN]:[MODAL SATUAN]],2,FALSE) -> 12000 | I48: =VLOOKUP(TBLBAHANKELUAR[[#This Row],[NAMA BAHAN]],TBLREKAPBAHAN[[NAMA BAHAN]:[MODAL SATUAN]],3,FALSE) -> 250 | J48: =VLOOKUP(TBLBAHANKELUAR[[#This Row],[NAMA BAHAN]],TBLREKAPBAHAN[[NAMA BAHAN]:[MODAL SATUAN]],4,FALSE) -> 48 | K48: =VLOOKUP(TBLBAHANKELUAR[[#This Row],[KODE BAHAN]],[4]!TBLKEBABAYAMMEDIUM[#Data],10,FALSE) -> 7 | L48: =SUMIF(TBLPRODUKKELUARJUNI[NAMA PRODUK],TBLBAHANKELUAR[[#This Row],[NAMA PRODUK]],TBLPRODUKKELUARJUNI[JUMLAH TERJUAL]) -> 4 | M48: =TBLBAHANKELUAR[[#This Row],[KEB. BAHAN]]*TBLBAHANKELUAR[[#This Row],[JUMLAH KEB. BAHAN KELUAR]] -> 28 | N48: =TBLBAHANKELUAR[[#This Row],[MODAL SATUAN]]*TBLBAHANKELUAR[[#This Row],[TOTAL BAHAN KELUAR]] -> 1344
A49: 2026 | B49: JUNI | E49: KEBAB AYAM MEDIUM PEDAS | F49: 4 | G49: =VLOOKUP(TBLBAHANKELUAR[[#This Row],[KODE BAHAN]],[4]!TBLKEBABAYAMMEDIUM[#Data],2,FALSE) -> MAYONAIS GRAM | H49: =VLOOKUP(TBLBAHANKELUAR[[#This Row],[NAMA BAHAN]],TBLREKAPBAHAN[[NAMA BAHAN]:[MODAL SATUAN]],2,FALSE) -> 50000 | I49: =VLOOKUP(TBLBAHANKELUAR[[#This Row],[NAMA BAHAN]],TBLREKAPBAHAN[[NAMA BAHAN]:[MODAL SATUAN]],3,FALSE) -> 1000 | J49: =VLOOKUP(TBLBAHANKELUAR[[#This Row],[NAMA BAHAN]],TBLREKAPBAHAN[[NAMA BAHAN]:[MODAL SATUAN]],4,FALSE) -> 50 | K49: =VLOOKUP(TBLBAHANKELUAR[[#This Row],[KODE BAHAN]],[4]!TBLKEBABAYAMMEDIUM[#Data],10,FALSE) -> 10 | L49: =SUMIF(TBLPRODUKKELUARJUNI[NAMA PRODUK],TBLBAHANKELUAR[[#This Row],[NAMA PRODUK]],TBLPRODUKKELUARJUNI[JUMLAH TERJUAL]) -> 4 | M49: =TBLBAHANKELUAR[[#This Row],[KEB. BAHAN]]*TBLBAHANKELUAR[[#This Row],[JUMLAH KEB. BAHAN KELUAR]] -> 40 | N49: =TBLBAHANKELUAR[[#This Row],[MODAL SATUAN]]*TBLBAHANKELUAR[[#This Row],[TOTAL BAHAN KELUAR]] -> 2000
A50: 2026 | B50: JUNI | E50: KEBAB AYAM MEDIUM PEDAS | F50: 5 | G50: =VLOOKUP(TBLBAHANKELUAR[[#This Row],[KODE BAHAN]],[4]!TBLKEBABAYAMMEDIUM[#Data],2,FALSE) -> SAOS SPAGHETI GRAM | H50: =VLOOKUP(TBLBAHANKELUAR[[#This Row],[NAMA BAHAN]],TBLREKAPBAHAN[[NAMA BAHAN]:[MODAL SATUAN]],2,FALSE) -> 12000 | I50: =VLOOKUP(TBLBAHANKELUAR[[#This Row],[NAMA BAHAN]],TBLREKAPBAHAN[[NAMA BAHAN]:[MODAL SATUAN]],3,FALSE) -> 250 | J50: =VLOOKUP(TBLBAHANKELUAR[[#This Row],[NAMA BAHAN]],TBLREKAPBAHAN[[NAMA BAHAN]:[MODAL SATUAN]],4,FALSE) -> 48 | K50: =VLOOKUP(TBLBAHANKELUAR[[#This Row],[KODE BAHAN]],[4]!TBLKEBABAYAMMEDIUM[#Data],10,FALSE) -> 7 | L50: =SUMIF(TBLPRODUKKELUARJUNI[NAMA PRODUK],TBLBAHANKELUAR[[#This Row],[NAMA PRODUK]],TBLPRODUKKELUARJUNI[JUMLAH TERJUAL]) -> 4 | M50: =TBLBAHANKELUAR[[#This Row],[KEB. BAHAN]]*TBLBAHANKELUAR[[#This Row],[JUMLAH KEB. BAHAN KELUAR]] -> 28 | N50: =TBLBAHANKELUAR[[#This Row],[MODAL SATUAN]]*TBLBAHANKELUAR[[#This Row],[TOTAL BAHAN KELUAR]] -> 1344
A51: 2026 | B51: JUNI | E51: KEBAB AYAM MEDIUM PEDAS | F51: 6 | G51: =VLOOKUP(TBLBAHANKELUAR[[#This Row],[KODE BAHAN]],[4]!TBLKEBABAYAMMEDIUM[#Data],2,FALSE) -> AYAM SUWIR | H51: =VLOOKUP(TBLBAHANKELUAR[[#This Row],[NAMA BAHAN]],TBLREKAPBAHAN[[NAMA BAHAN]:[MODAL SATUAN]],2,FALSE) -> 45000 | I51: =VLOOKUP(TBLBAHANKELUAR[[#This Row],[NAMA BAHAN]],TBLREKAPBAHAN[[NAMA BAHAN]:[MODAL SATUAN]],3,FALSE) -> 400 | J51: =VLOOKUP(TBLBAHANKELUAR[[#This Row],[NAMA BAHAN]],TBLREKAPBAHAN[[NAMA BAHAN]:[MODAL SATUAN]],4,FALSE) -> 112.5 | K51: =VLOOKUP(TBLBAHANKELUAR[[#This Row],[KODE BAHAN]],[4]!TBLKEBABAYAMMEDIUM[#Data],10,FALSE) -> 30 | L51: =SUMIF(TBLPRODUKKELUARJUNI[NAMA PRODUK],TBLBAHANKELUAR[[#This Row],[NAMA PRODUK]],TBLPRODUKKELUARJUNI[JUMLAH TERJUAL]) -> 4 | M51: =TBLBAHANKELUAR[[#This Row],[KEB. BAHAN]]*TBLBAHANKELUAR[[#This Row],[JUMLAH KEB. BAHAN KELUAR]] -> 120 | N51: =TBLBAHANKELUAR[[#This Row],[MODAL SATUAN]]*TBLBAHANKELUAR[[#This Row],[TOTAL BAHAN KELUAR]] -> 13500
A52: 2026 | B52: JUNI | E52: KEBAB AYAM MEDIUM PEDAS | F52: 7 | G52: =VLOOKUP(TBLBAHANKELUAR[[#This Row],[KODE BAHAN]],[4]!TBLKEBABAYAMMEDIUM[#Data],2,FALSE) -> KULIT KEBAB 19/20 CM | H52: =VLOOKUP(TBLBAHANKELUAR[[#This Row],[NAMA BAHAN]],TBLREKAPBAHAN[[NAMA BAHAN]:[MODAL SATUAN]],2,FALSE) -> 29000 | I52: =VLOOKUP(TBLBAHANKELUAR[[#This Row],[NAMA BAHAN]],TBLREKAPBAHAN[[NAMA BAHAN]:[MODAL SATUAN]],3,FALSE) -> 20 | J52: =VLOOKUP(TBLBAHANKELUAR[[#This Row],[NAMA BAHAN]],TBLREKAPBAHAN[[NAMA BAHAN]:[MODAL SATUAN]],4,FALSE) -> 1450 | K52: =VLOOKUP(TBLBAHANKELUAR[[#This Row],[KODE BAHAN]],[4]!TBLKEBABAYAMMEDIUM[#Data],10,FALSE) -> 1 | L52: =SUMIF(TBLPRODUKKELUARJUNI[NAMA PRODUK],TBLBAHANKELUAR[[#This Row],[NAMA PRODUK]],TBLPRODUKKELUARJUNI[JUMLAH TERJUAL]) -> 4 | M52: =TBLBAHANKELUAR[[#This Row],[KEB. BAHAN]]*TBLBAHANKELUAR[[#This Row],[JUMLAH KEB. BAHAN KELUAR]] -> 4 | N52: =TBLBAHANKELUAR[[#This Row],[MODAL SATUAN]]*TBLBAHANKELUAR[[#This Row],[TOTAL BAHAN KELUAR]] -> 5800
A53: 2026 | B53: JUNI | E53: KEBAB AYAM MEDIUM PEDAS | F53: 8 | G53: =VLOOKUP(TBLBAHANKELUAR[[#This Row],[KODE BAHAN]],[4]!TBLKEBABAYAMMEDIUM[#Data],2,FALSE) -> SLADA | H53: =VLOOKUP(TBLBAHANKELUAR[[#This Row],[NAMA BAHAN]],TBLREKAPBAHAN[[NAMA BAHAN]:[MODAL SATUAN]],2,FALSE) -> 60000 | I53: =VLOOKUP(TBLBAHANKELUAR[[#This Row],[NAMA BAHAN]],TBLREKAPBAHAN[[NAMA BAHAN]:[MODAL SATUAN]],3,FALSE) -> 50 | J53: =VLOOKUP(TBLBAHANKELUAR[[#This Row],[NAMA BAHAN]],TBLREKAPBAHAN[[NAMA BAHAN]:[MODAL SATUAN]],4,FALSE) -> 1200 | K53: =VLOOKUP(TBLBAHANKELUAR[[#This Row],[KODE BAHAN]],[4]!TBLKEBABAYAMMEDIUM[#Data],10,FALSE) -> 1 | L53: =SUMIF(TBLPRODUKKELUARJUNI[NAMA PRODUK],TBLBAHANKELUAR[[#This Row],[NAMA PRODUK]],TBLPRODUKKELUARJUNI[JUMLAH TERJUAL]) -> 4 | M53: =TBLBAHANKELUAR[[#This Row],[KEB. BAHAN]]*TBLBAHANKELUAR[[#This Row],[JUMLAH KEB. BAHAN KELUAR]] -> 4 | N53: =TBLBAHANKELUAR[[#This Row],[MODAL SATUAN]]*TBLBAHANKELUAR[[#This Row],[TOTAL BAHAN KELUAR]] -> 4800
A54: 2026 | B54: JUNI | E54: KEBAB AYAM MEDIUM PEDAS | F54: 9 | G54: =VLOOKUP(TBLBAHANKELUAR[[#This Row],[KODE BAHAN]],[4]!TBLKEBABAYAMMEDIUM[#Data],2,FALSE) -> MENTEGA | H54: =VLOOKUP(TBLBAHANKELUAR[[#This Row],[NAMA BAHAN]],TBLREKAPBAHAN[[NAMA BAHAN]:[MODAL SATUAN]],2,FALSE) -> 35000 | I54: =VLOOKUP(TBLBAHANKELUAR[[#This Row],[NAMA BAHAN]],TBLREKAPBAHAN[[NAMA BAHAN]:[MODAL SATUAN]],3,FALSE) -> 1000 | J54: =VLOOKUP(TBLBAHANKELUAR[[#This Row],[NAMA BAHAN]],TBLREKAPBAHAN[[NAMA BAHAN]:[MODAL SATUAN]],4,FALSE) -> 35 | K54: =VLOOKUP(TBLBAHANKELUAR[[#This Row],[KODE BAHAN]],[4]!TBLKEBABAYAMMEDIUM[#Data],10,FALSE) -> 10 | L54: =SUMIF(TBLPRODUKKELUARJUNI[NAMA PRODUK],TBLBAHANKELUAR[[#This Row],[NAMA PRODUK]],TBLPRODUKKELUARJUNI[JUMLAH TERJUAL]) -> 4 | M54: =TBLBAHANKELUAR[[#This Row],[KEB. BAHAN]]*TBLBAHANKELUAR[[#This Row],[JUMLAH KEB. BAHAN KELUAR]] -> 40 | N54: =TBLBAHANKELUAR[[#This Row],[MODAL SATUAN]]*TBLBAHANKELUAR[[#This Row],[TOTAL BAHAN KELUAR]] -> 1400
A55: 2026 | B55: JUNI | E55: KEBAB AYAM MEDIUM PEDAS | F55: 10 | G55: =VLOOKUP(TBLBAHANKELUAR[[#This Row],[KODE BAHAN]],[4]!TBLKEBABAYAMMEDIUM[#Data],2,FALSE) -> GAS ELPIJI | H55: =VLOOKUP(TBLBAHANKELUAR[[#This Row],[NAMA BAHAN]],TBLREKAPBAHAN[[NAMA BAHAN]:[MODAL SATUAN]],2,FALSE) -> 23000 | I55: =VLOOKUP(TBLBAHANKELUAR[[#This Row],[NAMA BAHAN]],TBLREKAPBAHAN[[NAMA BAHAN]:[MODAL SATUAN]],3,FALSE) -> 3000 | J55: =VLOOKUP(TBLBAHANKELUAR[[#This Row],[NAMA BAHAN]],TBLREKAPBAHAN[[NAMA BAHAN]:[MODAL SATUAN]],4,FALSE) -> 7.6666667 | K55: =VLOOKUP(TBLBAHANKELUAR[[#This Row],[KODE BAHAN]],[4]!TBLKEBABAYAMMEDIUM[#Data],10,FALSE) -> 10 | L55: =SUMIF(TBLPRODUKKELUARJUNI[NAMA PRODUK],TBLBAHANKELUAR[[#This Row],[NAMA PRODUK]],TBLPRODUKKELUARJUNI[JUMLAH TERJUAL]) -> 4 | M55: =TBLBAHANKELUAR[[#This Row],[KEB. BAHAN]]*TBLBAHANKELUAR[[#This Row],[JUMLAH KEB. BAHAN KELUAR]] -> 40 | N55: =TBLBAHANKELUAR[[#This Row],[MODAL SATUAN]]*TBLBAHANKELUAR[[#This Row],[TOTAL BAHAN KELUAR]] -> 306.66667
A56: 2026 | B56: JUNI | E56: KEBAB AYAM MEDIUM PEDAS | F56: 11 | G56: =VLOOKUP(TBLBAHANKELUAR[[#This Row],[KODE BAHAN]],[4]!TBLKEBABAYAMMEDIUM[#Data],2,FALSE) -> KERTAS KEBAB | H56: =VLOOKUP(TBLBAHANKELUAR[[#This Row],[NAMA BAHAN]],TBLREKAPBAHAN[[NAMA BAHAN]:[MODAL SATUAN]],2,FALSE) -> 25000 | I56: =VLOOKUP(TBLBAHANKELUAR[[#This Row],[NAMA BAHAN]],TBLREKAPBAHAN[[NAMA BAHAN]:[MODAL SATUAN]],3,FALSE) -> 100 | J56: =VLOOKUP(TBLBAHANKELUAR[[#This Row],[NAMA BAHAN]],TBLREKAPBAHAN[[NAMA BAHAN]:[MODAL SATUAN]],4,FALSE) -> 250 | K56: =VLOOKUP(TBLBAHANKELUAR[[#This Row],[KODE BAHAN]],[4]!TBLKEBABAYAMMEDIUM[#Data],10,FALSE) -> 1 | L56: =SUMIF(TBLPRODUKKELUARJUNI[NAMA PRODUK],TBLBAHANKELUAR[[#This Row],[NAMA PRODUK]],TBLPRODUKKELUARJUNI[JUMLAH TERJUAL]) -> 4 | M56: =TBLBAHANKELUAR[[#This Row],[KEB. BAHAN]]*TBLBAHANKELUAR[[#This Row],[JUMLAH KEB. BAHAN KELUAR]] -> 4 | N56: =TBLBAHANKELUAR[[#This Row],[MODAL SATUAN]]*TBLBAHANKELUAR[[#This Row],[TOTAL BAHAN KELUAR]] -> 1000
A57: 2026 | B57: JUNI | E57: KEBAB AYAM MEDIUM PEDAS | F57: 12 | G57: =VLOOKUP(TBLBAHANKELUAR[[#This Row],[KODE BAHAN]],[4]!TBLKEBABAYAMMEDIUM[#Data],2,FALSE) -> KRESEK 10 CM | H57: =VLOOKUP(TBLBAHANKELUAR[[#This Row],[NAMA BAHAN]],TBLREKAPBAHAN[[NAMA BAHAN]:[MODAL SATUAN]],2,FALSE) -> 5500 | I57: =VLOOKUP(TBLBAHANKELUAR[[#This Row],[NAMA BAHAN]],TBLREKAPBAHAN[[NAMA BAHAN]:[MODAL SATUAN]],3,FALSE) -> 100 | J57: =VLOOKUP(TBLBAHANKELUAR[[#This Row],[NAMA BAHAN]],TBLREKAPBAHAN[[NAMA BAHAN]:[MODAL SATUAN]],4,FALSE) -> 55 | K57: =VLOOKUP(TBLBAHANKELUAR[[#This Row],[KODE BAHAN]],[4]!TBLKEBABAYAMMEDIUM[#Data],10,FALSE) -> 1 | L57: =SUMIF(TBLPRODUKKELUARJUNI[NAMA PRODUK],TBLBAHANKELUAR[[#This Row],[NAMA PRODUK]],TBLPRODUKKELUARJUNI[JUMLAH TERJUAL]) -> 4 | M57: =TBLBAHANKELUAR[[#This Row],[KEB. BAHAN]]*TBLBAHANKELUAR[[#This Row],[JUMLAH KEB. BAHAN KELUAR]] -> 4 | N57: =TBLBAHANKELUAR[[#This Row],[MODAL SATUAN]]*TBLBAHANKELUAR[[#This Row],[TOTAL BAHAN KELUAR]] -> 220
A58: 2026 | B58: JUNI | E58: KEBAB AYAM MEDIUM | F58: 1 | G58: =VLOOKUP(TBLBAHANKELUAR[[#This Row],[KODE BAHAN]],[4]!TBLKEBABAYAMMEDIUM[#Data],2,FALSE) -> SAOS TOMAT GRAM | H58: =VLOOKUP(TBLBAHANKELUAR[[#This Row],[NAMA BAHAN]],TBLREKAPBAHAN[[NAMA BAHAN]:[MODAL SATUAN]],2,FALSE) -> 20000 | I58: =VLOOKUP(TBLBAHANKELUAR[[#This Row],[NAMA BAHAN]],TBLREKAPBAHAN[[NAMA BAHAN]:[MODAL SATUAN]],3,FALSE) -> 1000 | J58: =VLOOKUP(TBLBAHANKELUAR[[#This Row],[NAMA BAHAN]],TBLREKAPBAHAN[[NAMA BAHAN]:[MODAL SATUAN]],4,FALSE) -> 20 | K58: =VLOOKUP(TBLBAHANKELUAR[[#This Row],[KODE BAHAN]],[4]!TBLKEBABAYAMMEDIUM[#Data],8,FALSE) -> 15 | L58: =SUMIF(TBLPRODUKKELUARJUNI[NAMA PRODUK],TBLBAHANKELUAR[[#This Row],[NAMA PRODUK]],TBLPRODUKKELUARJUNI[JUMLAH TERJUAL]) -> 1 | M58: =TBLBAHANKELUAR[[#This Row],[KEB. BAHAN]]*TBLBAHANKELUAR[[#This Row],[JUMLAH KEB. BAHAN KELUAR]] -> 15 | N58: =TBLBAHANKELUAR[[#This Row],[MODAL SATUAN]]*TBLBAHANKELUAR[[#This Row],[TOTAL BAHAN KELUAR]] -> 300
A59: 2026 | B59: JUNI | E59: KEBAB AYAM MEDIUM | F59: 2 | G59: =VLOOKUP(TBLBAHANKELUAR[[#This Row],[KODE BAHAN]],[4]!TBLKEBABAYAMMEDIUM[#Data],2,FALSE) -> SAOS SAMBAL GRAM | H59: =VLOOKUP(TBLBAHANKELUAR[[#This Row],[NAMA BAHAN]],TBLREKAPBAHAN[[NAMA BAHAN]:[MODAL SATUAN]],2,FALSE) -> 18000 | I59: =VLOOKUP(TBLBAHANKELUAR[[#This Row],[NAMA BAHAN]],TBLREKAPBAHAN[[NAMA BAHAN]:[MODAL SATUAN]],3,FALSE) -> 1000 | J59: =VLOOKUP(TBLBAHANKELUAR[[#This Row],[NAMA BAHAN]],TBLREKAPBAHAN[[NAMA BAHAN]:[MODAL SATUAN]],4,FALSE) -> 18 | K59: =VLOOKUP(TBLBAHANKELUAR[[#This Row],[KODE BAHAN]],[4]!TBLKEBABAYAMMEDIUM[#Data],8,FALSE) -> 0 | L59: =SUMIF(TBLPRODUKKELUARJUNI[NAMA PRODUK],TBLBAHANKELUAR[[#This Row],[NAMA PRODUK]],TBLPRODUKKELUARJUNI[JUMLAH TERJUAL]) -> 1 | M59: =TBLBAHANKELUAR[[#This Row],[KEB. BAHAN]]*TBLBAHANKELUAR[[#This Row],[JUMLAH KEB. BAHAN KELUAR]] -> 0 | N59: =TBLBAHANKELUAR[[#This Row],[MODAL SATUAN]]*TBLBAHANKELUAR[[#This Row],[TOTAL BAHAN KELUAR]] -> 0
A60: 2026 | B60: JUNI | E60: KEBAB AYAM MEDIUM | F60: 3 | G60: =VLOOKUP(TBLBAHANKELUAR[[#This Row],[KODE BAHAN]],[4]!TBLKEBABAYAMMEDIUM[#Data],2,FALSE) -> SAOS BBQ GRAM | H60: =VLOOKUP(TBLBAHANKELUAR[[#This Row],[NAMA BAHAN]],TBLREKAPBAHAN[[NAMA BAHAN]:[MODAL SATUAN]],2,FALSE) -> 12000 | I60: =VLOOKUP(TBLBAHANKELUAR[[#This Row],[NAMA BAHAN]],TBLREKAPBAHAN[[NAMA BAHAN]:[MODAL SATUAN]],3,FALSE) -> 250 | J60: =VLOOKUP(TBLBAHANKELUAR[[#This Row],[NAMA BAHAN]],TBLREKAPBAHAN[[NAMA BAHAN]:[MODAL SATUAN]],4,FALSE) -> 48 | K60: =VLOOKUP(TBLBAHANKELUAR[[#This Row],[KODE BAHAN]],[4]!TBLKEBABAYAMMEDIUM[#Data],8,FALSE) -> 7 | L60: =SUMIF(TBLPRODUKKELUARJUNI[NAMA PRODUK],TBLBAHANKELUAR[[#This Row],[NAMA PRODUK]],TBLPRODUKKELUARJUNI[JUMLAH TERJUAL]) -> 1 | M60: =TBLBAHANKELUAR[[#This Row],[KEB. BAHAN]]*TBLBAHANKELUAR[[#This Row],[JUMLAH KEB. BAHAN KELUAR]] -> 7 | N60: =TBLBAHANKELUAR[[#This Row],[MODAL SATUAN]]*TBLBAHANKELUAR[[#This Row],[TOTAL BAHAN KELUAR]] -> 336
A61: 2026 | B61: JUNI | E61: KEBAB AYAM MEDIUM | F61: 4 | G61: =VLOOKUP(TBLBAHANKELUAR[[#This Row],[KODE BAHAN]],[4]!TBLKEBABAYAMMEDIUM[#Data],2,FALSE) -> MAYONAIS GRAM | H61: =VLOOKUP(TBLBAHANKELUAR[[#This Row],[NAMA BAHAN]],TBLREKAPBAHAN[[NAMA BAHAN]:[MODAL SATUAN]],2,FALSE) -> 50000 | I61: =VLOOKUP(TBLBAHANKELUAR[[#This Row],[NAMA BAHAN]],TBLREKAPBAHAN[[NAMA BAHAN]:[MODAL SATUAN]],3,FALSE) -> 1000 | J61: =VLOOKUP(TBLBAHANKELUAR[[#This Row],[NAMA BAHAN]],TBLREKAPBAHAN[[NAMA BAHAN]:[MODAL SATUAN]],4,FALSE) -> 50 | K61: =VLOOKUP(TBLBAHANKELUAR[[#This Row],[KODE BAHAN]],[4]!TBLKEBABAYAMMEDIUM[#Data],8,FALSE) -> 15 | L61: =SUMIF(TBLPRODUKKELUARJUNI[NAMA PRODUK],TBLBAHANKELUAR[[#This Row],[NAMA PRODUK]],TBLPRODUKKELUARJUNI[JUMLAH TERJUAL]) -> 1 | M61: =TBLBAHANKELUAR[[#This Row],[KEB. BAHAN]]*TBLBAHANKELUAR[[#This Row],[JUMLAH KEB. BAHAN KELUAR]] -> 15 | N61: =TBLBAHANKELUAR[[#This Row],[MODAL SATUAN]]*TBLBAHANKELUAR[[#This Row],[TOTAL BAHAN KELUAR]] -> 750
A62: 2026 | B62: JUNI | E62: KEBAB AYAM MEDIUM | F62: 5 | G62: =VLOOKUP(TBLBAHANKELUAR[[#This Row],[KODE BAHAN]],[4]!TBLKEBABAYAMMEDIUM[#Data],2,FALSE) -> SAOS SPAGHETI GRAM | H62: =VLOOKUP(TBLBAHANKELUAR[[#This Row],[NAMA BAHAN]],TBLREKAPBAHAN[[NAMA BAHAN]:[MODAL SATUAN]],2,FALSE) -> 12000 | I62: =VLOOKUP(TBLBAHANKELUAR[[#This Row],[NAMA BAHAN]],TBLREKAPBAHAN[[NAMA BAHAN]:[MODAL SATUAN]],3,FALSE) -> 250 | J62: =VLOOKUP(TBLBAHANKELUAR[[#This Row],[NAMA BAHAN]],TBLREKAPBAHAN[[NAMA BAHAN]:[MODAL SATUAN]],4,FALSE) -> 48 | K62: =VLOOKUP(TBLBAHANKELUAR[[#This Row],[KODE BAHAN]],[4]!TBLKEBABAYAMMEDIUM[#Data],8,FALSE) -> 7 | L62: =SUMIF(TBLPRODUKKELUARJUNI[NAMA PRODUK],TBLBAHANKELUAR[[#This Row],[NAMA PRODUK]],TBLPRODUKKELUARJUNI[JUMLAH TERJUAL]) -> 1 | M62: =TBLBAHANKELUAR[[#This Row],[KEB. BAHAN]]*TBLBAHANKELUAR[[#This Row],[JUMLAH KEB. BAHAN KELUAR]] -> 7 | N62: =TBLBAHANKELUAR[[#This Row],[MODAL SATUAN]]*TBLBAHANKELUAR[[#This Row],[TOTAL BAHAN KELUAR]] -> 336
A63: 2026 | B63: JUNI | E63: KEBAB AYAM MEDIUM | F63: 6 | G63: =VLOOKUP(TBLBAHANKELUAR[[#This Row],[KODE BAHAN]],[4]!TBLKEBABAYAMMEDIUM[#Data],2,FALSE) -> AYAM SUWIR | H63: =VLOOKUP(TBLBAHANKELUAR[[#This Row],[NAMA BAHAN]],TBLREKAPBAHAN[[NAMA BAHAN]:[MODAL SATUAN]],2,FALSE) -> 45000 | I63: =VLOOKUP(TBLBAHANKELUAR[[#This Row],[NAMA BAHAN]],TBLREKAPBAHAN[[NAMA BAHAN]:[MODAL SATUAN]],3,FALSE) -> 400 | J63: =VLOOKUP(TBLBAHANKELUAR[[#This Row],[NAMA BAHAN]],TBLREKAPBAHAN[[NAMA BAHAN]:[MODAL SATUAN]],4,FALSE) -> 112.5 | K63: =VLOOKUP(TBLBAHANKELUAR[[#This Row],[KODE BAHAN]],[4]!TBLKEBABAYAMMEDIUM[#Data],8,FALSE) -> 30 | L63: =SUMIF(TBLPRODUKKELUARJUNI[NAMA PRODUK],TBLBAHANKELUAR[[#This Row],[NAMA PRODUK]],TBLPRODUKKELUARJUNI[JUMLAH TERJUAL]) -> 1 | M63: =TBLBAHANKELUAR[[#This Row],[KEB. BAHAN]]*TBLBAHANKELUAR[[#This Row],[JUMLAH KEB. BAHAN KELUAR]] -> 30 | N63: =TBLBAHANKELUAR[[#This Row],[MODAL SATUAN]]*TBLBAHANKELUAR[[#This Row],[TOTAL BAHAN KELUAR]] -> 3375
A64: 2026 | B64: JUNI | E64: KEBAB AYAM MEDIUM | F64: 7 | G64: =VLOOKUP(TBLBAHANKELUAR[[#This Row],[KODE BAHAN]],[4]!TBLKEBABAYAMMEDIUM[#Data],2,FALSE) -> KULIT KEBAB 19/20 CM | H64: =VLOOKUP(TBLBAHANKELUAR[[#This Row],[NAMA BAHAN]],TBLREKAPBAHAN[[NAMA BAHAN]:[MODAL SATUAN]],2,FALSE) -> 29000 | I64: =VLOOKUP(TBLBAHANKELUAR[[#This Row],[NAMA BAHAN]],TBLREKAPBAHAN[[NAMA BAHAN]:[MODAL SATUAN]],3,FALSE) -> 20 | J64: =VLOOKUP(TBLBAHANKELUAR[[#This Row],[NAMA BAHAN]],TBLREKAPBAHAN[[NAMA BAHAN]:[MODAL SATUAN]],4,FALSE) -> 1450 | K64: =VLOOKUP(TBLBAHANKELUAR[[#This Row],[KODE BAHAN]],[4]!TBLKEBABAYAMMEDIUM[#Data],8,FALSE) -> 1 | L64: =SUMIF(TBLPRODUKKELUARJUNI[NAMA PRODUK],TBLBAHANKELUAR[[#This Row],[NAMA PRODUK]],TBLPRODUKKELUARJUNI[JUMLAH TERJUAL]) -> 1 | M64: =TBLBAHANKELUAR[[#This Row],[KEB. BAHAN]]*TBLBAHANKELUAR[[#This Row],[JUMLAH KEB. BAHAN KELUAR]] -> 1 | N64: =TBLBAHANKELUAR[[#This Row],[MODAL SATUAN]]*TBLBAHANKELUAR[[#This Row],[TOTAL BAHAN KELUAR]] -> 1450
A65: 2026 | B65: JUNI | E65: KEBAB AYAM MEDIUM | F65: 8 | G65: =VLOOKUP(TBLBAHANKELUAR[[#This Row],[KODE BAHAN]],[4]!TBLKEBABAYAMMEDIUM[#Data],2,FALSE) -> SLADA | H65: =VLOOKUP(TBLBAHANKELUAR[[#This Row],[NAMA BAHAN]],TBLREKAPBAHAN[[NAMA BAHAN]:[MODAL SATUAN]],2,FALSE) -> 60000 | I65: =VLOOKUP(TBLBAHANKELUAR[[#This Row],[NAMA BAHAN]],TBLREKAPBAHAN[[NAMA BAHAN]:[MODAL SATUAN]],3,FALSE) -> 50 | J65: =VLOOKUP(TBLBAHANKELUAR[[#This Row],[NAMA BAHAN]],TBLREKAPBAHAN[[NAMA BAHAN]:[MODAL SATUAN]],4,FALSE) -> 1200 | K65: =VLOOKUP(TBLBAHANKELUAR[[#This Row],[KODE BAHAN]],[4]!TBLKEBABAYAMMEDIUM[#Data],8,FALSE) -> 1 | L65: =SUMIF(TBLPRODUKKELUARJUNI[NAMA PRODUK],TBLBAHANKELUAR[[#This Row],[NAMA PRODUK]],TBLPRODUKKELUARJUNI[JUMLAH TERJUAL]) -> 1 | M65: =TBLBAHANKELUAR[[#This Row],[KEB. BAHAN]]*TBLBAHANKELUAR[[#This Row],[JUMLAH KEB. BAHAN KELUAR]] -> 1 | N65: =TBLBAHANKELUAR[[#This Row],[MODAL SATUAN]]*TBLBAHANKELUAR[[#This Row],[TOTAL BAHAN KELUAR]] -> 1200
A66: 2026 | B66: JUNI | E66: KEBAB AYAM MEDIUM | F66: 9 | G66: =VLOOKUP(TBLBAHANKELUAR[[#This Row],[KODE BAHAN]],[4]!TBLKEBABAYAMMEDIUM[#Data],2,FALSE) -> MENTEGA | H66: =VLOOKUP(TBLBAHANKELUAR[[#This Row],[NAMA BAHAN]],TBLREKAPBAHAN[[NAMA BAHAN]:[MODAL SATUAN]],2,FALSE) -> 35000 | I66: =VLOOKUP(TBLBAHANKELUAR[[#This Row],[NAMA BAHAN]],TBLREKAPBAHAN[[NAMA BAHAN]:[MODAL SATUAN]],3,FALSE) -> 1000 | J66: =VLOOKUP(TBLBAHANKELUAR[[#This Row],[NAMA BAHAN]],TBLREKAPBAHAN[[NAMA BAHAN]:[MODAL SATUAN]],4,FALSE) -> 35 | K66: =VLOOKUP(TBLBAHANKELUAR[[#This Row],[KODE BAHAN]],[4]!TBLKEBABAYAMMEDIUM[#Data],8,FALSE) -> 10 | L66: =SUMIF(TBLPRODUKKELUARJUNI[NAMA PRODUK],TBLBAHANKELUAR[[#This Row],[NAMA PRODUK]],TBLPRODUKKELUARJUNI[JUMLAH TERJUAL]) -> 1 | M66: =TBLBAHANKELUAR[[#This Row],[KEB. BAHAN]]*TBLBAHANKELUAR[[#This Row],[JUMLAH KEB. BAHAN KELUAR]] -> 10 | N66: =TBLBAHANKELUAR[[#This Row],[MODAL SATUAN]]*TBLBAHANKELUAR[[#This Row],[TOTAL BAHAN KELUAR]] -> 350
A67: 2026 | B67: JUNI | E67: KEBAB AYAM MEDIUM | F67: 10 | G67: =VLOOKUP(TBLBAHANKELUAR[[#This Row],[KODE BAHAN]],[4]!TBLKEBABAYAMMEDIUM[#Data],2,FALSE) -> GAS ELPIJI | H67: =VLOOKUP(TBLBAHANKELUAR[[#This Row],[NAMA BAHAN]],TBLREKAPBAHAN[[NAMA BAHAN]:[MODAL SATUAN]],2,FALSE) -> 23000 | I67: =VLOOKUP(TBLBAHANKELUAR[[#This Row],[NAMA BAHAN]],TBLREKAPBAHAN[[NAMA BAHAN]:[MODAL SATUAN]],3,FALSE) -> 3000 | J67: =VLOOKUP(TBLBAHANKELUAR[[#This Row],[NAMA BAHAN]],TBLREKAPBAHAN[[NAMA BAHAN]:[MODAL SATUAN]],4,FALSE) -> 7.6666667 | K67: =VLOOKUP(TBLBAHANKELUAR[[#This Row],[KODE BAHAN]],[4]!TBLKEBABAYAMMEDIUM[#Data],8,FALSE) -> 10 | L67: =SUMIF(TBLPRODUKKELUARJUNI[NAMA PRODUK],TBLBAHANKELUAR[[#This Row],[NAMA PRODUK]],TBLPRODUKKELUARJUNI[JUMLAH TERJUAL]) -> 1 | M67: =TBLBAHANKELUAR[[#This Row],[KEB. BAHAN]]*TBLBAHANKELUAR[[#This Row],[JUMLAH KEB. BAHAN KELUAR]] -> 10 | N67: =TBLBAHANKELUAR[[#This Row],[MODAL SATUAN]]*TBLBAHANKELUAR[[#This Row],[TOTAL BAHAN KELUAR]] -> 76.666667
A68: 2026 | B68: JUNI | E68: KEBAB AYAM MEDIUM | F68: 11 | G68: =VLOOKUP(TBLBAHANKELUAR[[#This Row],[KODE BAHAN]],[4]!TBLKEBABAYAMMEDIUM[#Data],2,FALSE) -> KERTAS KEBAB | H68: =VLOOKUP(TBLBAHANKELUAR[[#This Row],[NAMA BAHAN]],TBLREKAPBAHAN[[NAMA BAHAN]:[MODAL SATUAN]],2,FALSE) -> 25000 | I68: =VLOOKUP(TBLBAHANKELUAR[[#This Row],[NAMA BAHAN]],TBLREKAPBAHAN[[NAMA BAHAN]:[MODAL SATUAN]],3,FALSE) -> 100 | J68: =VLOOKUP(TBLBAHANKELUAR[[#This Row],[NAMA BAHAN]],TBLREKAPBAHAN[[NAMA BAHAN]:[MODAL SATUAN]],4,FALSE) -> 250 | K68: =VLOOKUP(TBLBAHANKELUAR[[#This Row],[KODE BAHAN]],[4]!TBLKEBABAYAMMEDIUM[#Data],8,FALSE) -> 1 | L68: =SUMIF(TBLPRODUKKELUARJUNI[NAMA PRODUK],TBLBAHANKELUAR[[#This Row],[NAMA PRODUK]],TBLPRODUKKELUARJUNI[JUMLAH TERJUAL]) -> 1 | M68: =TBLBAHANKELUAR[[#This Row],[KEB. BAHAN]]*TBLBAHANKELUAR[[#This Row],[JUMLAH KEB. BAHAN KELUAR]] -> 1 | N68: =TBLBAHANKELUAR[[#This Row],[MODAL SATUAN]]*TBLBAHANKELUAR[[#This Row],[TOTAL BAHAN KELUAR]] -> 250
A69: 2026 | B69: JUNI | E69: KEBAB AYAM MEDIUM | F69: 12 | G69: =VLOOKUP(TBLBAHANKELUAR[[#This Row],[KODE BAHAN]],[4]!TBLKEBABAYAMMEDIUM[#Data],2,FALSE) -> KRESEK 10 CM | H69: =VLOOKUP(TBLBAHANKELUAR[[#This Row],[NAMA BAHAN]],TBLREKAPBAHAN[[NAMA BAHAN]:[MODAL SATUAN]],2,FALSE) -> 5500 | I69: =VLOOKUP(TBLBAHANKELUAR[[#This Row],[NAMA BAHAN]],TBLREKAPBAHAN[[NAMA BAHAN]:[MODAL SATUAN]],3,FALSE) -> 100 | J69: =VLOOKUP(TBLBAHANKELUAR[[#This Row],[NAMA BAHAN]],TBLREKAPBAHAN[[NAMA BAHAN]:[MODAL SATUAN]],4,FALSE) -> 55 | K69: =VLOOKUP(TBLBAHANKELUAR[[#This Row],[KODE BAHAN]],[4]!TBLKEBABAYAMMEDIUM[#Data],8,FALSE) -> 1 | L69: =SUMIF(TBLPRODUKKELUARJUNI[NAMA PRODUK],TBLBAHANKELUAR[[#This Row],[NAMA PRODUK]],TBLPRODUKKELUARJUNI[JUMLAH TERJUAL]) -> 1 | M69: =TBLBAHANKELUAR[[#This Row],[KEB. BAHAN]]*TBLBAHANKELUAR[[#This Row],[JUMLAH KEB. BAHAN KELUAR]] -> 1 | N69: =TBLBAHANKELUAR[[#This Row],[MODAL SATUAN]]*TBLBAHANKELUAR[[#This Row],[TOTAL BAHAN KELUAR]] -> 55
A70: 2026 | B70: JULI | E70: KEBAB AYAM + SOSIZ (MEDIUM) | F70: 1 | G70: =VLOOKUP(TBLBAHANKELUAR[[#This Row],[KODE BAHAN]],[4]!TBLKEBABSOSYAMMEDIUM[#Data],2,FALSE) -> SAOS TOMAT GRAM | H70: =VLOOKUP(TBLBAHANKELUAR[[#This Row],[NAMA BAHAN]],TBLREKAPBAHAN[[NAMA BAHAN]:[MODAL SATUAN]],2,FALSE) -> 20000 | I70: =VLOOKUP(TBLBAHANKELUAR[[#This Row],[NAMA BAHAN]],TBLREKAPBAHAN[[NAMA BAHAN]:[MODAL SATUAN]],3,FALSE) -> 1000 | J70: =VLOOKUP(TBLBAHANKELUAR[[#This Row],[NAMA BAHAN]],TBLREKAPBAHAN[[NAMA BAHAN]:[MODAL SATUAN]],4,FALSE) -> 20 | K70: =VLOOKUP(TBLBAHANKELUAR[[#This Row],[KODE BAHAN]],[4]!TBLKEBABSOSYAMMEDIUM[#Data],8,FALSE) -> 15 | L70: =SUMIF(TBLPRODUKKELUARJULI[NAMA PRODUK],TBLBAHANKELUAR[[#This Row],[NAMA PRODUK]],TBLPRODUKKELUARJULI[JUMLAH TERJUAL]) -> 9 | M70: =TBLBAHANKELUAR[[#This Row],[KEB. BAHAN]]*TBLBAHANKELUAR[[#This Row],[JUMLAH KEB. BAHAN KELUAR]] -> 135 | N70: =TBLBAHANKELUAR[[#This Row],[MODAL SATUAN]]*TBLBAHANKELUAR[[#This Row],[TOTAL BAHAN KELUAR]] -> 2700
A71: 2026 | B71: JULI | E71: KEBAB AYAM + SOSIZ (MEDIUM) | F71: 2 | G71: =VLOOKUP(TBLBAHANKELUAR[[#This Row],[KODE BAHAN]],[4]!TBLKEBABSOSYAMMEDIUM[#Data],2,FALSE) -> SAOS SAMBAL GRAM | H71: =VLOOKUP(TBLBAHANKELUAR[[#This Row],[NAMA BAHAN]],TBLREKAPBAHAN[[NAMA BAHAN]:[MODAL SATUAN]],2,FALSE) -> 18000 | I71: =VLOOKUP(TBLBAHANKELUAR[[#This Row],[NAMA BAHAN]],TBLREKAPBAHAN[[NAMA BAHAN]:[MODAL SATUAN]],3,FALSE) -> 1000 | J71: =VLOOKUP(TBLBAHANKELUAR[[#This Row],[NAMA BAHAN]],TBLREKAPBAHAN[[NAMA BAHAN]:[MODAL SATUAN]],4,FALSE) -> 18 | K71: =VLOOKUP(TBLBAHANKELUAR[[#This Row],[KODE BAHAN]],[4]!TBLKEBABSOSYAMMEDIUM[#Data],8,FALSE) -> 0 | L71: =SUMIF(TBLPRODUKKELUARJULI[NAMA PRODUK],TBLBAHANKELUAR[[#This Row],[NAMA PRODUK]],TBLPRODUKKELUARJULI[JUMLAH TERJUAL]) -> 9 | M71: =TBLBAHANKELUAR[[#This Row],[KEB. BAHAN]]*TBLBAHANKELUAR[[#This Row],[JUMLAH KEB. BAHAN KELUAR]] -> 0 | N71: =TBLBAHANKELUAR[[#This Row],[MODAL SATUAN]]*TBLBAHANKELUAR[[#This Row],[TOTAL BAHAN KELUAR]] -> 0
A72: 2026 | B72: JULI | E72: KEBAB AYAM + SOSIZ (MEDIUM) | F72: 3 | G72: =VLOOKUP(TBLBAHANKELUAR[[#This Row],[KODE BAHAN]],[4]!TBLKEBABSOSYAMMEDIUM[#Data],2,FALSE) -> SAOS BBQ GRAM | H72: =VLOOKUP(TBLBAHANKELUAR[[#This Row],[NAMA BAHAN]],TBLREKAPBAHAN[[NAMA BAHAN]:[MODAL SATUAN]],2,FALSE) -> 12000 | I72: =VLOOKUP(TBLBAHANKELUAR[[#This Row],[NAMA BAHAN]],TBLREKAPBAHAN[[NAMA BAHAN]:[MODAL SATUAN]],3,FALSE) -> 250 | J72: =VLOOKUP(TBLBAHANKELUAR[[#This Row],[NAMA BAHAN]],TBLREKAPBAHAN[[NAMA BAHAN]:[MODAL SATUAN]],4,FALSE) -> 48 | K72: =VLOOKUP(TBLBAHANKELUAR[[#This Row],[KODE BAHAN]],[4]!TBLKEBABSOSYAMMEDIUM[#Data],8,FALSE) -> 7 | L72: =SUMIF(TBLPRODUKKELUARJULI[NAMA PRODUK],TBLBAHANKELUAR[[#This Row],[NAMA PRODUK]],TBLPRODUKKELUARJULI[JUMLAH TERJUAL]) -> 9 | M72: =TBLBAHANKELUAR[[#This Row],[KEB. BAHAN]]*TBLBAHANKELUAR[[#This Row],[JUMLAH KEB. BAHAN KELUAR]] -> 63 | N72: =TBLBAHANKELUAR[[#This Row],[MODAL SATUAN]]*TBLBAHANKELUAR[[#This Row],[TOTAL BAHAN KELUAR]] -> 3024
A73: 2026 | B73: JULI | E73: KEBAB AYAM + SOSIZ (MEDIUM) | F73: 4 | G73: =VLOOKUP(TBLBAHANKELUAR[[#This Row],[KODE BAHAN]],[4]!TBLKEBABSOSYAMMEDIUM[#Data],2,FALSE) -> MAYONAIS GRAM | H73: =VLOOKUP(TBLBAHANKELUAR[[#This Row],[NAMA BAHAN]],TBLREKAPBAHAN[[NAMA BAHAN]:[MODAL SATUAN]],2,FALSE) -> 50000 | I73: =VLOOKUP(TBLBAHANKELUAR[[#This Row],[NAMA BAHAN]],TBLREKAPBAHAN[[NAMA BAHAN]:[MODAL SATUAN]],3,FALSE) -> 1000 | J73: =VLOOKUP(TBLBAHANKELUAR[[#This Row],[NAMA BAHAN]],TBLREKAPBAHAN[[NAMA BAHAN]:[MODAL SATUAN]],4,FALSE) -> 50 | K73: =VLOOKUP(TBLBAHANKELUAR[[#This Row],[KODE BAHAN]],[4]!TBLKEBABSOSYAMMEDIUM[#Data],8,FALSE) -> 15 | L73: =SUMIF(TBLPRODUKKELUARJULI[NAMA PRODUK],TBLBAHANKELUAR[[#This Row],[NAMA PRODUK]],TBLPRODUKKELUARJULI[JUMLAH TERJUAL]) -> 9 | M73: =TBLBAHANKELUAR[[#This Row],[KEB. BAHAN]]*TBLBAHANKELUAR[[#This Row],[JUMLAH KEB. BAHAN KELUAR]] -> 135 | N73: =TBLBAHANKELUAR[[#This Row],[MODAL SATUAN]]*TBLBAHANKELUAR[[#This Row],[TOTAL BAHAN KELUAR]] -> 6750
A74: 2026 | B74: JULI | E74: KEBAB AYAM + SOSIZ (MEDIUM) | F74: 5 | G74: =VLOOKUP(TBLBAHANKELUAR[[#This Row],[KODE BAHAN]],[4]!TBLKEBABSOSYAMMEDIUM[#Data],2,FALSE) -> SAOS SPAGHETI GRAM | H74: =VLOOKUP(TBLBAHANKELUAR[[#This Row],[NAMA BAHAN]],TBLREKAPBAHAN[[NAMA BAHAN]:[MODAL SATUAN]],2,FALSE) -> 12000 | I74: =VLOOKUP(TBLBAHANKELUAR[[#This Row],[NAMA BAHAN]],TBLREKAPBAHAN[[NAMA BAHAN]:[MODAL SATUAN]],3,FALSE) -> 250 | J74: =VLOOKUP(TBLBAHANKELUAR[[#This Row],[NAMA BAHAN]],TBLREKAPBAHAN[[NAMA BAHAN]:[MODAL SATUAN]],4,FALSE) -> 48 | K74: =VLOOKUP(TBLBAHANKELUAR[[#This Row],[KODE BAHAN]],[4]!TBLKEBABSOSYAMMEDIUM[#Data],8,FALSE) -> 7 | L74: =SUMIF(TBLPRODUKKELUARJULI[NAMA PRODUK],TBLBAHANKELUAR[[#This Row],[NAMA PRODUK]],TBLPRODUKKELUARJULI[JUMLAH TERJUAL]) -> 9 | M74: =TBLBAHANKELUAR[[#This Row],[KEB. BAHAN]]*TBLBAHANKELUAR[[#This Row],[JUMLAH KEB. BAHAN KELUAR]] -> 63 | N74: =TBLBAHANKELUAR[[#This Row],[MODAL SATUAN]]*TBLBAHANKELUAR[[#This Row],[TOTAL BAHAN KELUAR]] -> 3024
A75: 2026 | B75: JULI | E75: KEBAB AYAM + SOSIZ (MEDIUM) | F75: 6 | G75: =VLOOKUP(TBLBAHANKELUAR[[#This Row],[KODE BAHAN]],[4]!TBLKEBABSOSYAMMEDIUM[#Data],2,FALSE) -> SOSIZ BATANG | H75: =VLOOKUP(TBLBAHANKELUAR[[#This Row],[NAMA BAHAN]],TBLREKAPBAHAN[[NAMA BAHAN]:[MODAL SATUAN]],2,FALSE) -> 35000 | I75: =VLOOKUP(TBLBAHANKELUAR[[#This Row],[NAMA BAHAN]],TBLREKAPBAHAN[[NAMA BAHAN]:[MODAL SATUAN]],3,FALSE) -> 38 | J75: =VLOOKUP(TBLBAHANKELUAR[[#This Row],[NAMA BAHAN]],TBLREKAPBAHAN[[NAMA BAHAN]:[MODAL SATUAN]],4,FALSE) -> 921.05263 | K75: =VLOOKUP(TBLBAHANKELUAR[[#This Row],[KODE BAHAN]],[4]!TBLKEBABSOSYAMMEDIUM[#Data],8,FALSE) -> 1 | L75: =SUMIF(TBLPRODUKKELUARJULI[NAMA PRODUK],TBLBAHANKELUAR[[#This Row],[NAMA PRODUK]],TBLPRODUKKELUARJULI[JUMLAH TERJUAL]) -> 9 | M75: =TBLBAHANKELUAR[[#This Row],[KEB. BAHAN]]*TBLBAHANKELUAR[[#This Row],[JUMLAH KEB. BAHAN KELUAR]] -> 9 | N75: =TBLBAHANKELUAR[[#This Row],[MODAL SATUAN]]*TBLBAHANKELUAR[[#This Row],[TOTAL BAHAN KELUAR]] -> 8289.4737
A76: 2026 | B76: JULI | E76: KEBAB AYAM + SOSIZ (MEDIUM) | F76: 7 | G76: =VLOOKUP(TBLBAHANKELUAR[[#This Row],[KODE BAHAN]],[4]!TBLKEBABSOSYAMMEDIUM[#Data],2,FALSE) -> AYAM SUWIR | H76: =VLOOKUP(TBLBAHANKELUAR[[#This Row],[NAMA BAHAN]],TBLREKAPBAHAN[[NAMA BAHAN]:[MODAL SATUAN]],2,FALSE) -> 45000 | I76: =VLOOKUP(TBLBAHANKELUAR[[#This Row],[NAMA BAHAN]],TBLREKAPBAHAN[[NAMA BAHAN]:[MODAL SATUAN]],3,FALSE) -> 400 | J76: =VLOOKUP(TBLBAHANKELUAR[[#This Row],[NAMA BAHAN]],TBLREKAPBAHAN[[NAMA BAHAN]:[MODAL SATUAN]],4,FALSE) -> 112.5 | K76: =VLOOKUP(TBLBAHANKELUAR[[#This Row],[KODE BAHAN]],[4]!TBLKEBABSOSYAMMEDIUM[#Data],8,FALSE) -> 20 | L76: =SUMIF(TBLPRODUKKELUARJULI[NAMA PRODUK],TBLBAHANKELUAR[[#This Row],[NAMA PRODUK]],TBLPRODUKKELUARJULI[JUMLAH TERJUAL]) -> 9 | M76: =TBLBAHANKELUAR[[#This Row],[KEB. BAHAN]]*TBLBAHANKELUAR[[#This Row],[JUMLAH KEB. BAHAN KELUAR]] -> 180 | N76: =TBLBAHANKELUAR[[#This Row],[MODAL SATUAN]]*TBLBAHANKELUAR[[#This Row],[TOTAL BAHAN KELUAR]] -> 20250
A77: 2026 | B77: JULI | E77: KEBAB AYAM + SOSIZ (MEDIUM) | F77: 8 | G77: =VLOOKUP(TBLBAHANKELUAR[[#This Row],[KODE BAHAN]],[4]!TBLKEBABSOSYAMMEDIUM[#Data],2,FALSE) -> KULIT KEBAB 19/20 CM | H77: =VLOOKUP(TBLBAHANKELUAR[[#This Row],[NAMA BAHAN]],TBLREKAPBAHAN[[NAMA BAHAN]:[MODAL SATUAN]],2,FALSE) -> 29000 | I77: =VLOOKUP(TBLBAHANKELUAR[[#This Row],[NAMA BAHAN]],TBLREKAPBAHAN[[NAMA BAHAN]:[MODAL SATUAN]],3,FALSE) -> 20 | J77: =VLOOKUP(TBLBAHANKELUAR[[#This Row],[NAMA BAHAN]],TBLREKAPBAHAN[[NAMA BAHAN]:[MODAL SATUAN]],4,FALSE) -> 1450 | K77: =VLOOKUP(TBLBAHANKELUAR[[#This Row],[KODE BAHAN]],[4]!TBLKEBABSOSYAMMEDIUM[#Data],8,FALSE) -> 1 | L77: =SUMIF(TBLPRODUKKELUARJULI[NAMA PRODUK],TBLBAHANKELUAR[[#This Row],[NAMA PRODUK]],TBLPRODUKKELUARJULI[JUMLAH TERJUAL]) -> 9 | M77: =TBLBAHANKELUAR[[#This Row],[KEB. BAHAN]]*TBLBAHANKELUAR[[#This Row],[JUMLAH KEB. BAHAN KELUAR]] -> 9 | N77: =TBLBAHANKELUAR[[#This Row],[MODAL SATUAN]]*TBLBAHANKELUAR[[#This Row],[TOTAL BAHAN KELUAR]] -> 13050
A78: 2026 | B78: JULI | E78: KEBAB AYAM + SOSIZ (MEDIUM) | F78: 9 | G78: =VLOOKUP(TBLBAHANKELUAR[[#This Row],[KODE BAHAN]],[4]!TBLKEBABSOSYAMMEDIUM[#Data],2,FALSE) -> SLADA | H78: =VLOOKUP(TBLBAHANKELUAR[[#This Row],[NAMA BAHAN]],TBLREKAPBAHAN[[NAMA BAHAN]:[MODAL SATUAN]],2,FALSE) -> 60000 | I78: =VLOOKUP(TBLBAHANKELUAR[[#This Row],[NAMA BAHAN]],TBLREKAPBAHAN[[NAMA BAHAN]:[MODAL SATUAN]],3,FALSE) -> 50 | J78: =VLOOKUP(TBLBAHANKELUAR[[#This Row],[NAMA BAHAN]],TBLREKAPBAHAN[[NAMA BAHAN]:[MODAL SATUAN]],4,FALSE) -> 1200 | K78: =VLOOKUP(TBLBAHANKELUAR[[#This Row],[KODE BAHAN]],[4]!TBLKEBABSOSYAMMEDIUM[#Data],8,FALSE) -> 1 | L78: =SUMIF(TBLPRODUKKELUARJULI[NAMA PRODUK],TBLBAHANKELUAR[[#This Row],[NAMA PRODUK]],TBLPRODUKKELUARJULI[JUMLAH TERJUAL]) -> 9 | M78: =TBLBAHANKELUAR[[#This Row],[KEB. BAHAN]]*TBLBAHANKELUAR[[#This Row],[JUMLAH KEB. BAHAN KELUAR]] -> 9 | N78: =TBLBAHANKELUAR[[#This Row],[MODAL SATUAN]]*TBLBAHANKELUAR[[#This Row],[TOTAL BAHAN KELUAR]] -> 10800
A79: 2026 | B79: JULI | E79: KEBAB AYAM + SOSIZ (MEDIUM) | F79: 10 | G79: =VLOOKUP(TBLBAHANKELUAR[[#This Row],[KODE BAHAN]],[4]!TBLKEBABSOSYAMMEDIUM[#Data],2,FALSE) -> MENTEGA | H79: =VLOOKUP(TBLBAHANKELUAR[[#This Row],[NAMA BAHAN]],TBLREKAPBAHAN[[NAMA BAHAN]:[MODAL SATUAN]],2,FALSE) -> 35000 | I79: =VLOOKUP(TBLBAHANKELUAR[[#This Row],[NAMA BAHAN]],TBLREKAPBAHAN[[NAMA BAHAN]:[MODAL SATUAN]],3,FALSE) -> 1000 | J79: =VLOOKUP(TBLBAHANKELUAR[[#This Row],[NAMA BAHAN]],TBLREKAPBAHAN[[NAMA BAHAN]:[MODAL SATUAN]],4,FALSE) -> 35 | K79: =VLOOKUP(TBLBAHANKELUAR[[#This Row],[KODE BAHAN]],[4]!TBLKEBABSOSYAMMEDIUM[#Data],8,FALSE) -> 10 | L79: =SUMIF(TBLPRODUKKELUARJULI[NAMA PRODUK],TBLBAHANKELUAR[[#This Row],[NAMA PRODUK]],TBLPRODUKKELUARJULI[JUMLAH TERJUAL]) -> 9 | M79: =TBLBAHANKELUAR[[#This Row],[KEB. BAHAN]]*TBLBAHANKELUAR[[#This Row],[JUMLAH KEB. BAHAN KELUAR]] -> 90 | N79: =TBLBAHANKELUAR[[#This Row],[MODAL SATUAN]]*TBLBAHANKELUAR[[#This Row],[TOTAL BAHAN KELUAR]] -> 3150
A80: 2026 | B80: JULI | E80: KEBAB AYAM + SOSIZ (MEDIUM) | F80: 11 | G80: =VLOOKUP(TBLBAHANKELUAR[[#This Row],[KODE BAHAN]],[4]!TBLKEBABSOSYAMMEDIUM[#Data],2,FALSE) -> GAS ELPIJI | H80: =VLOOKUP(TBLBAHANKELUAR[[#This Row],[NAMA BAHAN]],TBLREKAPBAHAN[[NAMA BAHAN]:[MODAL SATUAN]],2,FALSE) -> 23000 | I80: =VLOOKUP(TBLBAHANKELUAR[[#This Row],[NAMA BAHAN]],TBLREKAPBAHAN[[NAMA BAHAN]:[MODAL SATUAN]],3,FALSE) -> 3000 | J80: =VLOOKUP(TBLBAHANKELUAR[[#This Row],[NAMA BAHAN]],TBLREKAPBAHAN[[NAMA BAHAN]:[MODAL SATUAN]],4,FALSE) -> 7.6666667 | K80: =VLOOKUP(TBLBAHANKELUAR[[#This Row],[KODE BAHAN]],[4]!TBLKEBABSOSYAMMEDIUM[#Data],8,FALSE) -> 10 | L80: =SUMIF(TBLPRODUKKELUARJULI[NAMA PRODUK],TBLBAHANKELUAR[[#This Row],[NAMA PRODUK]],TBLPRODUKKELUARJULI[JUMLAH TERJUAL]) -> 9 | M80: =TBLBAHANKELUAR[[#This Row],[KEB. BAHAN]]*TBLBAHANKELUAR[[#This Row],[JUMLAH KEB. BAHAN KELUAR]] -> 90 | N80: =TBLBAHANKELUAR[[#This Row],[MODAL SATUAN]]*TBLBAHANKELUAR[[#This Row],[TOTAL BAHAN KELUAR]] -> 690
A81: 2026 | B81: JULI | E81: KEBAB AYAM + SOSIZ (MEDIUM) | F81: 12 | G81: =VLOOKUP(TBLBAHANKELUAR[[#This Row],[KODE BAHAN]],[4]!TBLKEBABSOSYAMMEDIUM[#Data],2,FALSE) -> KERTAS KEBAB | H81: =VLOOKUP(TBLBAHANKELUAR[[#This Row],[NAMA BAHAN]],TBLREKAPBAHAN[[NAMA BAHAN]:[MODAL SATUAN]],2,FALSE) -> 25000 | I81: =VLOOKUP(TBLBAHANKELUAR[[#This Row],[NAMA BAHAN]],TBLREKAPBAHAN[[NAMA BAHAN]:[MODAL SATUAN]],3,FALSE) -> 100 | J81: =VLOOKUP(TBLBAHANKELUAR[[#This Row],[NAMA BAHAN]],TBLREKAPBAHAN[[NAMA BAHAN]:[MODAL SATUAN]],4,FALSE) -> 250 | K81: =VLOOKUP(TBLBAHANKELUAR[[#This Row],[KODE BAHAN]],[4]!TBLKEBABSOSYAMMEDIUM[#Data],8,FALSE) -> 1 | L81: =SUMIF(TBLPRODUKKELUARJULI[NAMA PRODUK],TBLBAHANKELUAR[[#This Row],[NAMA PRODUK]],TBLPRODUKKELUARJULI[JUMLAH TERJUAL]) -> 9 | M81: =TBLBAHANKELUAR[[#This Row],[KEB. BAHAN]]*TBLBAHANKELUAR[[#This Row],[JUMLAH KEB. BAHAN KELUAR]] -> 9 | N81: =TBLBAHANKELUAR[[#This Row],[MODAL SATUAN]]*TBLBAHANKELUAR[[#This Row],[TOTAL BAHAN KELUAR]] -> 2250
A82: 2026 | B82: JULI | E82: KEBAB AYAM + SOSIZ (MEDIUM) | F82: 13 | G82: =VLOOKUP(TBLBAHANKELUAR[[#This Row],[KODE BAHAN]],[4]!TBLKEBABSOSYAMMEDIUM[#Data],2,FALSE) -> KRESEK 10 CM | H82: =VLOOKUP(TBLBAHANKELUAR[[#This Row],[NAMA BAHAN]],TBLREKAPBAHAN[[NAMA BAHAN]:[MODAL SATUAN]],2,FALSE) -> 5500 | I82: =VLOOKUP(TBLBAHANKELUAR[[#This Row],[NAMA BAHAN]],TBLREKAPBAHAN[[NAMA BAHAN]:[MODAL SATUAN]],3,FALSE) -> 100 | J82: =VLOOKUP(TBLBAHANKELUAR[[#This Row],[NAMA BAHAN]],TBLREKAPBAHAN[[NAMA BAHAN]:[MODAL SATUAN]],4,FALSE) -> 55 | K82: =VLOOKUP(TBLBAHANKELUAR[[#This Row],[KODE BAHAN]],[4]!TBLKEBABSOSYAMMEDIUM[#Data],8,FALSE) -> 1 | L82: =SUMIF(TBLPRODUKKELUARJULI[NAMA PRODUK],TBLBAHANKELUAR[[#This Row],[NAMA PRODUK]],TBLPRODUKKELUARJULI[JUMLAH TERJUAL]) -> 9 | M82: =TBLBAHANKELUAR[[#This Row],[KEB. BAHAN]]*TBLBAHANKELUAR[[#This Row],[JUMLAH KEB. BAHAN KELUAR]] -> 9 | N82: =TBLBAHANKELUAR[[#This Row],[MODAL SATUAN]]*TBLBAHANKELUAR[[#This Row],[TOTAL BAHAN KELUAR]] -> 495
A83: 2026 | B83: JULI | E83: KEBAB AYAM + SOSIZ (MEDIUM) PEDAS | F83: 1 | G83: =VLOOKUP(TBLBAHANKELUAR[[#This Row],[KODE BAHAN]],[4]!TBLKEBABSOSYAMMEDIUM[#Data],2,FALSE) -> SAOS TOMAT GRAM | H83: =VLOOKUP(TBLBAHANKELUAR[[#This Row],[NAMA BAHAN]],TBLREKAPBAHAN[[NAMA BAHAN]:[MODAL SATUAN]],2,FALSE) -> 20000 | I83: =VLOOKUP(TBLBAHANKELUAR[[#This Row],[NAMA BAHAN]],TBLREKAPBAHAN[[NAMA BAHAN]:[MODAL SATUAN]],3,FALSE) -> 1000 | J83: =VLOOKUP(TBLBAHANKELUAR[[#This Row],[NAMA BAHAN]],TBLREKAPBAHAN[[NAMA BAHAN]:[MODAL SATUAN]],4,FALSE) -> 20 | K83: =VLOOKUP(TBLBAHANKELUAR[[#This Row],[KODE BAHAN]],[4]!TBLKEBABSOSYAMMEDIUM[#Data],10,FALSE) -> 0 | L83: =SUMIF(TBLPRODUKKELUARJULI[NAMA PRODUK],TBLBAHANKELUAR[[#This Row],[NAMA PRODUK]],TBLPRODUKKELUARJULI[JUMLAH TERJUAL]) -> 9 | M83: =TBLBAHANKELUAR[[#This Row],[KEB. BAHAN]]*TBLBAHANKELUAR[[#This Row],[JUMLAH KEB. BAHAN KELUAR]] -> 0 | N83: =TBLBAHANKELUAR[[#This Row],[MODAL SATUAN]]*TBLBAHANKELUAR[[#This Row],[TOTAL BAHAN KELUAR]] -> 0
A84: 2026 | B84: JULI | E84: KEBAB AYAM + SOSIZ (MEDIUM) PEDAS | F84: 2 | G84: =VLOOKUP(TBLBAHANKELUAR[[#This Row],[KODE BAHAN]],[4]!TBLKEBABSOSYAMMEDIUM[#Data],2,FALSE) -> SAOS SAMBAL GRAM | H84: =VLOOKUP(TBLBAHANKELUAR[[#This Row],[NAMA BAHAN]],TBLREKAPBAHAN[[NAMA BAHAN]:[MODAL SATUAN]],2,FALSE) -> 18000 | I84: =VLOOKUP(TBLBAHANKELUAR[[#This Row],[NAMA BAHAN]],TBLREKAPBAHAN[[NAMA BAHAN]:[MODAL SATUAN]],3,FALSE) -> 1000 | J84: =VLOOKUP(TBLBAHANKELUAR[[#This Row],[NAMA BAHAN]],TBLREKAPBAHAN[[NAMA BAHAN]:[MODAL SATUAN]],4,FALSE) -> 18 | K84: =VLOOKUP(TBLBAHANKELUAR[[#This Row],[KODE BAHAN]],[4]!TBLKEBABSOSYAMMEDIUM[#Data],10,FALSE) -> 25 | L84: =SUMIF(TBLPRODUKKELUARJULI[NAMA PRODUK],TBLBAHANKELUAR[[#This Row],[NAMA PRODUK]],TBLPRODUKKELUARJULI[JUMLAH TERJUAL]) -> 9 | M84: =TBLBAHANKELUAR[[#This Row],[KEB. BAHAN]]*TBLBAHANKELUAR[[#This Row],[JUMLAH KEB. BAHAN KELUAR]] -> 225 | N84: =TBLBAHANKELUAR[[#This Row],[MODAL SATUAN]]*TBLBAHANKELUAR[[#This Row],[TOTAL BAHAN KELUAR]] -> 4050
A85: 2026 | B85: JULI | E85: KEBAB AYAM + SOSIZ (MEDIUM) PEDAS | F85: 3 | G85: =VLOOKUP(TBLBAHANKELUAR[[#This Row],[KODE BAHAN]],[4]!TBLKEBABSOSYAMMEDIUM[#Data],2,FALSE) -> SAOS BBQ GRAM | H85: =VLOOKUP(TBLBAHANKELUAR[[#This Row],[NAMA BAHAN]],TBLREKAPBAHAN[[NAMA BAHAN]:[MODAL SATUAN]],2,FALSE) -> 12000 | I85: =VLOOKUP(TBLBAHANKELUAR[[#This Row],[NAMA BAHAN]],TBLREKAPBAHAN[[NAMA BAHAN]:[MODAL SATUAN]],3,FALSE) -> 250 | J85: =VLOOKUP(TBLBAHANKELUAR[[#This Row],[NAMA BAHAN]],TBLREKAPBAHAN[[NAMA BAHAN]:[MODAL SATUAN]],4,FALSE) -> 48 | K85: =VLOOKUP(TBLBAHANKELUAR[[#This Row],[KODE BAHAN]],[4]!TBLKEBABSOSYAMMEDIUM[#Data],10,FALSE) -> 7 | L85: =SUMIF(TBLPRODUKKELUARJULI[NAMA PRODUK],TBLBAHANKELUAR[[#This Row],[NAMA PRODUK]],TBLPRODUKKELUARJULI[JUMLAH TERJUAL]) -> 9 | M85: =TBLBAHANKELUAR[[#This Row],[KEB. BAHAN]]*TBLBAHANKELUAR[[#This Row],[JUMLAH KEB. BAHAN KELUAR]] -> 63 | N85: =TBLBAHANKELUAR[[#This Row],[MODAL SATUAN]]*TBLBAHANKELUAR[[#This Row],[TOTAL BAHAN KELUAR]] -> 3024
A86: 2026 | B86: JULI | E86: KEBAB AYAM + SOSIZ (MEDIUM) PEDAS | F86: 4 | G86: =VLOOKUP(TBLBAHANKELUAR[[#This Row],[KODE BAHAN]],[4]!TBLKEBABSOSYAMMEDIUM[#Data],2,FALSE) -> MAYONAIS GRAM | H86: =VLOOKUP(TBLBAHANKELUAR[[#This Row],[NAMA BAHAN]],TBLREKAPBAHAN[[NAMA BAHAN]:[MODAL SATUAN]],2,FALSE) -> 50000 | I86: =VLOOKUP(TBLBAHANKELUAR[[#This Row],[NAMA BAHAN]],TBLREKAPBAHAN[[NAMA BAHAN]:[MODAL SATUAN]],3,FALSE) -> 1000 | J86: =VLOOKUP(TBLBAHANKELUAR[[#This Row],[NAMA BAHAN]],TBLREKAPBAHAN[[NAMA BAHAN]:[MODAL SATUAN]],4,FALSE) -> 50 | K86: =VLOOKUP(TBLBAHANKELUAR[[#This Row],[KODE BAHAN]],[4]!TBLKEBABSOSYAMMEDIUM[#Data],10,FALSE) -> 10 | L86: =SUMIF(TBLPRODUKKELUARJULI[NAMA PRODUK],TBLBAHANKELUAR[[#This Row],[NAMA PRODUK]],TBLPRODUKKELUARJULI[JUMLAH TERJUAL]) -> 9 | M86: =TBLBAHANKELUAR[[#This Row],[KEB. BAHAN]]*TBLBAHANKELUAR[[#This Row],[JUMLAH KEB. BAHAN KELUAR]] -> 90 | N86: =TBLBAHANKELUAR[[#This Row],[MODAL SATUAN]]*TBLBAHANKELUAR[[#This Row],[TOTAL BAHAN KELUAR]] -> 4500
A87: 2026 | B87: JULI | E87: KEBAB AYAM + SOSIZ (MEDIUM) PEDAS | F87: 5 | G87: =VLOOKUP(TBLBAHANKELUAR[[#This Row],[KODE BAHAN]],[4]!TBLKEBABSOSYAMMEDIUM[#Data],2,FALSE) -> SAOS SPAGHETI GRAM | H87: =VLOOKUP(TBLBAHANKELUAR[[#This Row],[NAMA BAHAN]],TBLREKAPBAHAN[[NAMA BAHAN]:[MODAL SATUAN]],2,FALSE) -> 12000 | I87: =VLOOKUP(TBLBAHANKELUAR[[#This Row],[NAMA BAHAN]],TBLREKAPBAHAN[[NAMA BAHAN]:[MODAL SATUAN]],3,FALSE) -> 250 | J87: =VLOOKUP(TBLBAHANKELUAR[[#This Row],[NAMA BAHAN]],TBLREKAPBAHAN[[NAMA BAHAN]:[MODAL SATUAN]],4,FALSE) -> 48 | K87: =VLOOKUP(TBLBAHANKELUAR[[#This Row],[KODE BAHAN]],[4]!TBLKEBABSOSYAMMEDIUM[#Data],10,FALSE) -> 7 | L87: =SUMIF(TBLPRODUKKELUARJULI[NAMA PRODUK],TBLBAHANKELUAR[[#This Row],[NAMA PRODUK]],TBLPRODUKKELUARJULI[JUMLAH TERJUAL]) -> 9 | M87: =TBLBAHANKELUAR[[#This Row],[KEB. BAHAN]]*TBLBAHANKELUAR[[#This Row],[JUMLAH KEB. BAHAN KELUAR]] -> 63 | N87: =TBLBAHANKELUAR[[#This Row],[MODAL SATUAN]]*TBLBAHANKELUAR[[#This Row],[TOTAL BAHAN KELUAR]] -> 3024
A88: 2026 | B88: JULI | E88: KEBAB AYAM + SOSIZ (MEDIUM) PEDAS | F88: 6 | G88: =VLOOKUP(TBLBAHANKELUAR[[#This Row],[KODE BAHAN]],[4]!TBLKEBABSOSYAMMEDIUM[#Data],2,FALSE) -> SOSIZ BATANG | H88: =VLOOKUP(TBLBAHANKELUAR[[#This Row],[NAMA BAHAN]],TBLREKAPBAHAN[[NAMA BAHAN]:[MODAL SATUAN]],2,FALSE) -> 35000 | I88: =VLOOKUP(TBLBAHANKELUAR[[#This Row],[NAMA BAHAN]],TBLREKAPBAHAN[[NAMA BAHAN]:[MODAL SATUAN]],3,FALSE) -> 38 | J88: =VLOOKUP(TBLBAHANKELUAR[[#This Row],[NAMA BAHAN]],TBLREKAPBAHAN[[NAMA BAHAN]:[MODAL SATUAN]],4,FALSE) -> 921.05263 | K88: =VLOOKUP(TBLBAHANKELUAR[[#This Row],[KODE BAHAN]],[4]!TBLKEBABSOSYAMMEDIUM[#Data],10,FALSE) -> 1 | L88: =SUMIF(TBLPRODUKKELUARJULI[NAMA PRODUK],TBLBAHANKELUAR[[#This Row],[NAMA PRODUK]],TBLPRODUKKELUARJULI[JUMLAH TERJUAL]) -> 9 | M88: =TBLBAHANKELUAR[[#This Row],[KEB. BAHAN]]*TBLBAHANKELUAR[[#This Row],[JUMLAH KEB. BAHAN KELUAR]] -> 9 | N88: =TBLBAHANKELUAR[[#This Row],[MODAL SATUAN]]*TBLBAHANKELUAR[[#This Row],[TOTAL BAHAN KELUAR]] -> 8289.4737
A89: 2026 | B89: JULI | E89: KEBAB AYAM + SOSIZ (MEDIUM) PEDAS | F89: 7 | G89: =VLOOKUP(TBLBAHANKELUAR[[#This Row],[KODE BAHAN]],[4]!TBLKEBABSOSYAMMEDIUM[#Data],2,FALSE) -> AYAM SUWIR | H89: =VLOOKUP(TBLBAHANKELUAR[[#This Row],[NAMA BAHAN]],TBLREKAPBAHAN[[NAMA BAHAN]:[MODAL SATUAN]],2,FALSE) -> 45000 | I89: =VLOOKUP(TBLBAHANKELUAR[[#This Row],[NAMA BAHAN]],TBLREKAPBAHAN[[NAMA BAHAN]:[MODAL SATUAN]],3,FALSE) -> 400 | J89: =VLOOKUP(TBLBAHANKELUAR[[#This Row],[NAMA BAHAN]],TBLREKAPBAHAN[[NAMA BAHAN]:[MODAL SATUAN]],4,FALSE) -> 112.5 | K89: =VLOOKUP(TBLBAHANKELUAR[[#This Row],[KODE BAHAN]],[4]!TBLKEBABSOSYAMMEDIUM[#Data],10,FALSE) -> 20 | L89: =SUMIF(TBLPRODUKKELUARJULI[NAMA PRODUK],TBLBAHANKELUAR[[#This Row],[NAMA PRODUK]],TBLPRODUKKELUARJULI[JUMLAH TERJUAL]) -> 9 | M89: =TBLBAHANKELUAR[[#This Row],[KEB. BAHAN]]*TBLBAHANKELUAR[[#This Row],[JUMLAH KEB. BAHAN KELUAR]] -> 180 | N89: =TBLBAHANKELUAR[[#This Row],[MODAL SATUAN]]*TBLBAHANKELUAR[[#This Row],[TOTAL BAHAN KELUAR]] -> 20250
A90: 2026 | B90: JULI | E90: KEBAB AYAM + SOSIZ (MEDIUM) PEDAS | F90: 8 | G90: =VLOOKUP(TBLBAHANKELUAR[[#This Row],[KODE BAHAN]],[4]!TBLKEBABSOSYAMMEDIUM[#Data],2,FALSE) -> KULIT KEBAB 19/20 CM | H90: =VLOOKUP(TBLBAHANKELUAR[[#This Row],[NAMA BAHAN]],TBLREKAPBAHAN[[NAMA BAHAN]:[MODAL SATUAN]],2,FALSE) -> 29000 | I90: =VLOOKUP(TBLBAHANKELUAR[[#This Row],[NAMA BAHAN]],TBLREKAPBAHAN[[NAMA BAHAN]:[MODAL SATUAN]],3,FALSE) -> 20 | J90: =VLOOKUP(TBLBAHANKELUAR[[#This Row],[NAMA BAHAN]],TBLREKAPBAHAN[[NAMA BAHAN]:[MODAL SATUAN]],4,FALSE) -> 1450 | K90: =VLOOKUP(TBLBAHANKELUAR[[#This Row],[KODE BAHAN]],[4]!TBLKEBABSOSYAMMEDIUM[#Data],10,FALSE) -> 1 | L90: =SUMIF(TBLPRODUKKELUARJULI[NAMA PRODUK],TBLBAHANKELUAR[[#This Row],[NAMA PRODUK]],TBLPRODUKKELUARJULI[JUMLAH TERJUAL]) -> 9 | M90: =TBLBAHANKELUAR[[#This Row],[KEB. BAHAN]]*TBLBAHANKELUAR[[#This Row],[JUMLAH KEB. BAHAN KELUAR]] -> 9 | N90: =TBLBAHANKELUAR[[#This Row],[MODAL SATUAN]]*TBLBAHANKELUAR[[#This Row],[TOTAL BAHAN KELUAR]] -> 13050
A91: 2026 | B91: JULI | E91: KEBAB AYAM + SOSIZ (MEDIUM) PEDAS | F91: 9 | G91: =VLOOKUP(TBLBAHANKELUAR[[#This Row],[KODE BAHAN]],[4]!TBLKEBABSOSYAMMEDIUM[#Data],2,FALSE) -> SLADA | H91: =VLOOKUP(TBLBAHANKELUAR[[#This Row],[NAMA BAHAN]],TBLREKAPBAHAN[[NAMA BAHAN]:[MODAL SATUAN]],2,FALSE) -> 60000 | I91: =VLOOKUP(TBLBAHANKELUAR[[#This Row],[NAMA BAHAN]],TBLREKAPBAHAN[[NAMA BAHAN]:[MODAL SATUAN]],3,FALSE) -> 50 | J91: =VLOOKUP(TBLBAHANKELUAR[[#This Row],[NAMA BAHAN]],TBLREKAPBAHAN[[NAMA BAHAN]:[MODAL SATUAN]],4,FALSE) -> 1200 | K91: =VLOOKUP(TBLBAHANKELUAR[[#This Row],[KODE BAHAN]],[4]!TBLKEBABSOSYAMMEDIUM[#Data],10,FALSE) -> 1 | L91: =SUMIF(TBLPRODUKKELUARJULI[NAMA PRODUK],TBLBAHANKELUAR[[#This Row],[NAMA PRODUK]],TBLPRODUKKELUARJULI[JUMLAH TERJUAL]) -> 9 | M91: =TBLBAHANKELUAR[[#This Row],[KEB. BAHAN]]*TBLBAHANKELUAR[[#This Row],[JUMLAH KEB. BAHAN KELUAR]] -> 9 | N91: =TBLBAHANKELUAR[[#This Row],[MODAL SATUAN]]*TBLBAHANKELUAR[[#This Row],[TOTAL BAHAN KELUAR]] -> 10800
A92: 2026 | B92: JULI | E92: KEBAB AYAM + SOSIZ (MEDIUM) PEDAS | F92: 10 | G92: =VLOOKUP(TBLBAHANKELUAR[[#This Row],[KODE BAHAN]],[4]!TBLKEBABSOSYAMMEDIUM[#Data],2,FALSE) -> MENTEGA | H92: =VLOOKUP(TBLBAHANKELUAR[[#This Row],[NAMA BAHAN]],TBLREKAPBAHAN[[NAMA BAHAN]:[MODAL SATUAN]],2,FALSE) -> 35000 | I92: =VLOOKUP(TBLBAHANKELUAR[[#This Row],[NAMA BAHAN]],TBLREKAPBAHAN[[NAMA BAHAN]:[MODAL SATUAN]],3,FALSE) -> 1000 | J92: =VLOOKUP(TBLBAHANKELUAR[[#This Row],[NAMA BAHAN]],TBLREKAPBAHAN[[NAMA BAHAN]:[MODAL SATUAN]],4,FALSE) -> 35 | K92: =VLOOKUP(TBLBAHANKELUAR[[#This Row],[KODE BAHAN]],[4]!TBLKEBABSOSYAMMEDIUM[#Data],10,FALSE) -> 10 | L92: =SUMIF(TBLPRODUKKELUARJULI[NAMA PRODUK],TBLBAHANKELUAR[[#This Row],[NAMA PRODUK]],TBLPRODUKKELUARJULI[JUMLAH TERJUAL]) -> 9 | M92: =TBLBAHANKELUAR[[#This Row],[KEB. BAHAN]]*TBLBAHANKELUAR[[#This Row],[JUMLAH KEB. BAHAN KELUAR]] -> 90 | N92: =TBLBAHANKELUAR[[#This Row],[MODAL SATUAN]]*TBLBAHANKELUAR[[#This Row],[TOTAL BAHAN KELUAR]] -> 3150
A93: 2026 | B93: JULI | E93: KEBAB AYAM + SOSIZ (MEDIUM) PEDAS | F93: 11 | G93: =VLOOKUP(TBLBAHANKELUAR[[#This Row],[KODE BAHAN]],[4]!TBLKEBABSOSYAMMEDIUM[#Data],2,FALSE) -> GAS ELPIJI | H93: =VLOOKUP(TBLBAHANKELUAR[[#This Row],[NAMA BAHAN]],TBLREKAPBAHAN[[NAMA BAHAN]:[MODAL SATUAN]],2,FALSE) -> 23000 | I93: =VLOOKUP(TBLBAHANKELUAR[[#This Row],[NAMA BAHAN]],TBLREKAPBAHAN[[NAMA BAHAN]:[MODAL SATUAN]],3,FALSE) -> 3000 | J93: =VLOOKUP(TBLBAHANKELUAR[[#This Row],[NAMA BAHAN]],TBLREKAPBAHAN[[NAMA BAHAN]:[MODAL SATUAN]],4,FALSE) -> 7.6666667 | K93: =VLOOKUP(TBLBAHANKELUAR[[#This Row],[KODE BAHAN]],[4]!TBLKEBABSOSYAMMEDIUM[#Data],10,FALSE) -> 10 | L93: =SUMIF(TBLPRODUKKELUARJULI[NAMA PRODUK],TBLBAHANKELUAR[[#This Row],[NAMA PRODUK]],TBLPRODUKKELUARJULI[JUMLAH TERJUAL]) -> 9 | M93: =TBLBAHANKELUAR[[#This Row],[KEB. BAHAN]]*TBLBAHANKELUAR[[#This Row],[JUMLAH KEB. BAHAN KELUAR]] -> 90 | N93: =TBLBAHANKELUAR[[#This Row],[MODAL SATUAN]]*TBLBAHANKELUAR[[#This Row],[TOTAL BAHAN KELUAR]] -> 690
A94: 2026 | B94: JULI | E94: KEBAB AYAM + SOSIZ (MEDIUM) PEDAS | F94: 12 | G94: =VLOOKUP(TBLBAHANKELUAR[[#This Row],[KODE BAHAN]],[4]!TBLKEBABSOSYAMMEDIUM[#Data],2,FALSE) -> KERTAS KEBAB | H94: =VLOOKUP(TBLBAHANKELUAR[[#This Row],[NAMA BAHAN]],TBLREKAPBAHAN[[NAMA BAHAN]:[MODAL SATUAN]],2,FALSE) -> 25000 | I94: =VLOOKUP(TBLBAHANKELUAR[[#This Row],[NAMA BAHAN]],TBLREKAPBAHAN[[NAMA BAHAN]:[MODAL SATUAN]],3,FALSE) -> 100 | J94: =VLOOKUP(TBLBAHANKELUAR[[#This Row],[NAMA BAHAN]],TBLREKAPBAHAN[[NAMA BAHAN]:[MODAL SATUAN]],4,FALSE) -> 250 | K94: =VLOOKUP(TBLBAHANKELUAR[[#This Row],[KODE BAHAN]],[4]!TBLKEBABSOSYAMMEDIUM[#Data],10,FALSE) -> 1 | L94: =SUMIF(TBLPRODUKKELUARJULI[NAMA PRODUK],TBLBAHANKELUAR[[#This Row],[NAMA PRODUK]],TBLPRODUKKELUARJULI[JUMLAH TERJUAL]) -> 9 | M94: =TBLBAHANKELUAR[[#This Row],[KEB. BAHAN]]*TBLBAHANKELUAR[[#This Row],[JUMLAH KEB. BAHAN KELUAR]] -> 9 | N94: =TBLBAHANKELUAR[[#This Row],[MODAL SATUAN]]*TBLBAHANKELUAR[[#This Row],[TOTAL BAHAN KELUAR]] -> 2250
A95: 2026 | B95: JULI | E95: KEBAB AYAM + SOSIZ (MEDIUM) PEDAS | F95: 13 | G95: =VLOOKUP(TBLBAHANKELUAR[[#This Row],[KODE BAHAN]],[4]!TBLKEBABSOSYAMMEDIUM[#Data],2,FALSE) -> KRESEK 10 CM | H95: =VLOOKUP(TBLBAHANKELUAR[[#This Row],[NAMA BAHAN]],TBLREKAPBAHAN[[NAMA BAHAN]:[MODAL SATUAN]],2,FALSE) -> 5500 | I95: =VLOOKUP(TBLBAHANKELUAR[[#This Row],[NAMA BAHAN]],TBLREKAPBAHAN[[NAMA BAHAN]:[MODAL SATUAN]],3,FALSE) -> 100 | J95: =VLOOKUP(TBLBAHANKELUAR[[#This Row],[NAMA BAHAN]],TBLREKAPBAHAN[[NAMA BAHAN]:[MODAL SATUAN]],4,FALSE) -> 55 | K95: =VLOOKUP(TBLBAHANKELUAR[[#This Row],[KODE BAHAN]],[4]!TBLKEBABSOSYAMMEDIUM[#Data],10,FALSE) -> 1 | L95: =SUMIF(TBLPRODUKKELUARJULI[NAMA PRODUK],TBLBAHANKELUAR[[#This Row],[NAMA PRODUK]],TBLPRODUKKELUARJULI[JUMLAH TERJUAL]) -> 9 | M95: =TBLBAHANKELUAR[[#This Row],[KEB. BAHAN]]*TBLBAHANKELUAR[[#This Row],[JUMLAH KEB. BAHAN KELUAR]] -> 9 | N95: =TBLBAHANKELUAR[[#This Row],[MODAL SATUAN]]*TBLBAHANKELUAR[[#This Row],[TOTAL BAHAN KELUAR]] -> 495
A96: 2026 | B96: JULI | E96: KEBAB AYAM + SOSIZ (KECIL) | F96: 1 | G96: =VLOOKUP(TBLBAHANKELUAR[[#This Row],[KODE BAHAN]],[4]!TBLKEBABSOSYAMKECIL[#Data],2,FALSE) -> SAOS TOMAT GRAM | H96: =VLOOKUP(TBLBAHANKELUAR[[#This Row],[NAMA BAHAN]],TBLREKAPBAHAN[[NAMA BAHAN]:[MODAL SATUAN]],2,FALSE) -> 20000 | I96: =VLOOKUP(TBLBAHANKELUAR[[#This Row],[NAMA BAHAN]],TBLREKAPBAHAN[[NAMA BAHAN]:[MODAL SATUAN]],3,FALSE) -> 1000 | J96: =VLOOKUP(TBLBAHANKELUAR[[#This Row],[NAMA BAHAN]],TBLREKAPBAHAN[[NAMA BAHAN]:[MODAL SATUAN]],4,FALSE) -> 20 | K96: =VLOOKUP(TBLBAHANKELUAR[[#This Row],[KODE BAHAN]],[4]!TBLKEBABSOSYAMKECIL[#Data],8,FALSE) -> 10 | L96: =SUMIF(TBLPRODUKKELUARJULI[NAMA PRODUK],TBLBAHANKELUAR[[#This Row],[NAMA PRODUK]],TBLPRODUKKELUARJULI[JUMLAH TERJUAL]) -> 58 | M96: =TBLBAHANKELUAR[[#This Row],[KEB. BAHAN]]*TBLBAHANKELUAR[[#This Row],[JUMLAH KEB. BAHAN KELUAR]] -> 580 | N96: =TBLBAHANKELUAR[[#This Row],[MODAL SATUAN]]*TBLBAHANKELUAR[[#This Row],[TOTAL BAHAN KELUAR]] -> 11600
A97: 2026 | B97: JULI | E97: KEBAB AYAM + SOSIZ (KECIL) | F97: 2 | G97: =VLOOKUP(TBLBAHANKELUAR[[#This Row],[KODE BAHAN]],[4]!TBLKEBABSOSYAMKECIL[#Data],2,FALSE) -> SAOS SAMBAL GRAM | H97: =VLOOKUP(TBLBAHANKELUAR[[#This Row],[NAMA BAHAN]],TBLREKAPBAHAN[[NAMA BAHAN]:[MODAL SATUAN]],2,FALSE) -> 18000 | I97: =VLOOKUP(TBLBAHANKELUAR[[#This Row],[NAMA BAHAN]],TBLREKAPBAHAN[[NAMA BAHAN]:[MODAL SATUAN]],3,FALSE) -> 1000 | J97: =VLOOKUP(TBLBAHANKELUAR[[#This Row],[NAMA BAHAN]],TBLREKAPBAHAN[[NAMA BAHAN]:[MODAL SATUAN]],4,FALSE) -> 18 | K97: =VLOOKUP(TBLBAHANKELUAR[[#This Row],[KODE BAHAN]],[4]!TBLKEBABSOSYAMKECIL[#Data],8,FALSE) -> 0 | L97: =SUMIF(TBLPRODUKKELUARJULI[NAMA PRODUK],TBLBAHANKELUAR[[#This Row],[NAMA PRODUK]],TBLPRODUKKELUARJULI[JUMLAH TERJUAL]) -> 58 | M97: =TBLBAHANKELUAR[[#This Row],[KEB. BAHAN]]*TBLBAHANKELUAR[[#This Row],[JUMLAH KEB. BAHAN KELUAR]] -> 0 | N97: =TBLBAHANKELUAR[[#This Row],[MODAL SATUAN]]*TBLBAHANKELUAR[[#This Row],[TOTAL BAHAN KELUAR]] -> 0
A98: 2026 | B98: JULI | E98: KEBAB AYAM + SOSIZ (KECIL) | F98: 3 | G98: =VLOOKUP(TBLBAHANKELUAR[[#This Row],[KODE BAHAN]],[4]!TBLKEBABSOSYAMKECIL[#Data],2,FALSE) -> SAOS BBQ GRAM | H98: =VLOOKUP(TBLBAHANKELUAR[[#This Row],[NAMA BAHAN]],TBLREKAPBAHAN[[NAMA BAHAN]:[MODAL SATUAN]],2,FALSE) -> 12000 | I98: =VLOOKUP(TBLBAHANKELUAR[[#This Row],[NAMA BAHAN]],TBLREKAPBAHAN[[NAMA BAHAN]:[MODAL SATUAN]],3,FALSE) -> 250 | J98: =VLOOKUP(TBLBAHANKELUAR[[#This Row],[NAMA BAHAN]],TBLREKAPBAHAN[[NAMA BAHAN]:[MODAL SATUAN]],4,FALSE) -> 48 | K98: =VLOOKUP(TBLBAHANKELUAR[[#This Row],[KODE BAHAN]],[4]!TBLKEBABSOSYAMKECIL[#Data],8,FALSE) -> 5 | L98: =SUMIF(TBLPRODUKKELUARJULI[NAMA PRODUK],TBLBAHANKELUAR[[#This Row],[NAMA PRODUK]],TBLPRODUKKELUARJULI[JUMLAH TERJUAL]) -> 58 | M98: =TBLBAHANKELUAR[[#This Row],[KEB. BAHAN]]*TBLBAHANKELUAR[[#This Row],[JUMLAH KEB. BAHAN KELUAR]] -> 290 | N98: =TBLBAHANKELUAR[[#This Row],[MODAL SATUAN]]*TBLBAHANKELUAR[[#This Row],[TOTAL BAHAN KELUAR]] -> 13920
A99: 2026 | B99: JULI | E99: KEBAB AYAM + SOSIZ (KECIL) | F99: 4 | G99: =VLOOKUP(TBLBAHANKELUAR[[#This Row],[KODE BAHAN]],[4]!TBLKEBABSOSYAMKECIL[#Data],2,FALSE) -> MAYONAIS GRAM | H99: =VLOOKUP(TBLBAHANKELUAR[[#This Row],[NAMA BAHAN]],TBLREKAPBAHAN[[NAMA BAHAN]:[MODAL SATUAN]],2,FALSE) -> 50000 | I99: =VLOOKUP(TBLBAHANKELUAR[[#This Row],[NAMA BAHAN]],TBLREKAPBAHAN[[NAMA BAHAN]:[MODAL SATUAN]],3,FALSE) -> 1000 | J99: =VLOOKUP(TBLBAHANKELUAR[[#This Row],[NAMA BAHAN]],TBLREKAPBAHAN[[NAMA BAHAN]:[MODAL SATUAN]],4,FALSE) -> 50 | K99: =VLOOKUP(TBLBAHANKELUAR[[#This Row],[KODE BAHAN]],[4]!TBLKEBABSOSYAMKECIL[#Data],8,FALSE) -> 7 | L99: =SUMIF(TBLPRODUKKELUARJULI[NAMA PRODUK],TBLBAHANKELUAR[[#This Row],[NAMA PRODUK]],TBLPRODUKKELUARJULI[JUMLAH TERJUAL]) -> 58 | M99: =TBLBAHANKELUAR[[#This Row],[KEB. BAHAN]]*TBLBAHANKELUAR[[#This Row],[JUMLAH KEB. BAHAN KELUAR]] -> 406 | N99: =TBLBAHANKELUAR[[#This Row],[MODAL SATUAN]]*TBLBAHANKELUAR[[#This Row],[TOTAL BAHAN KELUAR]] -> 20300
A100: 2026 | B100: JULI | E100: KEBAB AYAM + SOSIZ (KECIL) | F100: 5 | G100: =VLOOKUP(TBLBAHANKELUAR[[#This Row],[KODE BAHAN]],[4]!TBLKEBABSOSYAMKECIL[#Data],2,FALSE) -> SAOS SPAGHETI GRAM | H100: =VLOOKUP(TBLBAHANKELUAR[[#This Row],[NAMA BAHAN]],TBLREKAPBAHAN[[NAMA BAHAN]:[MODAL SATUAN]],2,FALSE) -> 12000 | I100: =VLOOKUP(TBLBAHANKELUAR[[#This Row],[NAMA BAHAN]],TBLREKAPBAHAN[[NAMA BAHAN]:[MODAL SATUAN]],3,FALSE) -> 250 | J100: =VLOOKUP(TBLBAHANKELUAR[[#This Row],[NAMA BAHAN]],TBLREKAPBAHAN[[NAMA BAHAN]:[MODAL SATUAN]],4,FALSE) -> 48 | K100: =VLOOKUP(TBLBAHANKELUAR[[#This Row],[KODE BAHAN]],[4]!TBLKEBABSOSYAMKECIL[#Data],8,FALSE) -> 5 | L100: =SUMIF(TBLPRODUKKELUARJULI[NAMA PRODUK],TBLBAHANKELUAR[[#This Row],[NAMA PRODUK]],TBLPRODUKKELUARJULI[JUMLAH TERJUAL]) -> 58 | M100: =TBLBAHANKELUAR[[#This Row],[KEB. BAHAN]]*TBLBAHANKELUAR[[#This Row],[JUMLAH KEB. BAHAN KELUAR]] -> 290 | N100: =TBLBAHANKELUAR[[#This Row],[MODAL SATUAN]]*TBLBAHANKELUAR[[#This Row],[TOTAL BAHAN KELUAR]] -> 13920
A101: 2026 | B101: JULI | E101: KEBAB AYAM + SOSIZ (KECIL) | F101: 6 | G101: =VLOOKUP(TBLBAHANKELUAR[[#This Row],[KODE BAHAN]],[4]!TBLKEBABSOSYAMKECIL[#Data],2,FALSE) -> SOSIZ BATANG | H101: =VLOOKUP(TBLBAHANKELUAR[[#This Row],[NAMA BAHAN]],TBLREKAPBAHAN[[NAMA BAHAN]:[MODAL SATUAN]],2,FALSE) -> 35000 | I101: =VLOOKUP(TBLBAHANKELUAR[[#This Row],[NAMA BAHAN]],TBLREKAPBAHAN[[NAMA BAHAN]:[MODAL SATUAN]],3,FALSE) -> 38 | J101: =VLOOKUP(TBLBAHANKELUAR[[#This Row],[NAMA BAHAN]],TBLREKAPBAHAN[[NAMA BAHAN]:[MODAL SATUAN]],4,FALSE) -> 921.05263 | K101: =VLOOKUP(TBLBAHANKELUAR[[#This Row],[KODE BAHAN]],[4]!TBLKEBABSOSYAMKECIL[#Data],8,FALSE) -> 0.5 | L101: =SUMIF(TBLPRODUKKELUARJULI[NAMA PRODUK],TBLBAHANKELUAR[[#This Row],[NAMA PRODUK]],TBLPRODUKKELUARJULI[JUMLAH TERJUAL]) -> 58 | M101: =TBLBAHANKELUAR[[#This Row],[KEB. BAHAN]]*TBLBAHANKELUAR[[#This Row],[JUMLAH KEB. BAHAN KELUAR]] -> 29 | N101: =TBLBAHANKELUAR[[#This Row],[MODAL SATUAN]]*TBLBAHANKELUAR[[#This Row],[TOTAL BAHAN KELUAR]] -> 26710.526
A102: 2026 | B102: JULI | E102: KEBAB AYAM + SOSIZ (KECIL) | F102: 7 | G102: =VLOOKUP(TBLBAHANKELUAR[[#This Row],[KODE BAHAN]],[4]!TBLKEBABSOSYAMKECIL[#Data],2,FALSE) -> AYAM SUWIR | H102: =VLOOKUP(TBLBAHANKELUAR[[#This Row],[NAMA BAHAN]],TBLREKAPBAHAN[[NAMA BAHAN]:[MODAL SATUAN]],2,FALSE) -> 45000 | I102: =VLOOKUP(TBLBAHANKELUAR[[#This Row],[NAMA BAHAN]],TBLREKAPBAHAN[[NAMA BAHAN]:[MODAL SATUAN]],3,FALSE) -> 400 | J102: =VLOOKUP(TBLBAHANKELUAR[[#This Row],[NAMA BAHAN]],TBLREKAPBAHAN[[NAMA BAHAN]:[MODAL SATUAN]],4,FALSE) -> 112.5 | K102: =VLOOKUP(TBLBAHANKELUAR[[#This Row],[KODE BAHAN]],[4]!TBLKEBABSOSYAMKECIL[#Data],8,FALSE) -> 12 | L102: =SUMIF(TBLPRODUKKELUARJULI[NAMA PRODUK],TBLBAHANKELUAR[[#This Row],[NAMA PRODUK]],TBLPRODUKKELUARJULI[JUMLAH TERJUAL]) -> 58 | M102: =TBLBAHANKELUAR[[#This Row],[KEB. BAHAN]]*TBLBAHANKELUAR[[#This Row],[JUMLAH KEB. BAHAN KELUAR]] -> 696 | N102: =TBLBAHANKELUAR[[#This Row],[MODAL SATUAN]]*TBLBAHANKELUAR[[#This Row],[TOTAL BAHAN KELUAR]] -> 78300
...

Sheet PRODUK KELUAR
A1: PRODUK KELUAR KE CUSTOMER
A2: JUNI
A3: TAHUN | B3: BULAN | C3: TANGGAL | D3: NAMA PRODUK | E3: NAMA CUSTOMER | F3: NAMA MITRA | G3: MODAL | H3: BUDGET KOMISI | I3: MODAL DITAMBAH BUDGET KOMISI | J3: HARGA JUAL | K3: SELISIH | L3: LABA MITRA 8 % | M3: LABA KIRIM 8 % | N3: LABA BERSIH TOKO | O3: JUMLAH TERJUAL | P3: JUMLAH TERKIRIM | Q3: TOTAL MODAL | R3: TOTAL JUMLAH LABA | S3: TOTAL MODAL DITAMBAH LABA | T3: TOTAL HARGA JUAL | U3: TOTAL SELISIH | V3: TOTAL LABA MITRA 5% | W3: TOTAL LABA KIRIM 5% | X3: TAKE HOME KOMISI UTAMA | Y3: TOTAL LABA BERSIH TOKO
A4: 2026 | B4: JUNI | C4: 46198 | D4: KEBAB AYAM + SOSIZ (KECIL) PEDAS | E4: RASTI | F4: =VLOOKUP(TBLPRODUKKELUARJUNI[[#This Row],[NAMA CUSTOMER]],TBLDATACUSTOMER[],4,FALSE) -> NURUL HIDAYATU SAMSIAH | G4: =VLOOKUP(TBLPRODUKKELUARJUNI[[#This Row],[NAMA PRODUK]],TBLKATALOG[],2,FALSE) -> 6192.193 | H4: =VLOOKUP(TBLPRODUKKELUARJUNI[[#This Row],[NAMA PRODUK]],TBLKATALOG[],3,FALSE) -> 619.2193 | I4: =VLOOKUP(TBLPRODUKKELUARJUNI[[#This Row],[NAMA PRODUK]],TBLKATALOG[],4,FALSE) -> 6811.4123 | J4: =VLOOKUP(TBLPRODUKKELUARJUNI[[#This Row],[NAMA PRODUK]],TBLKATALOG[],5,FALSE) -> 9000 | K4: =VLOOKUP(TBLPRODUKKELUARJUNI[[#This Row],[NAMA PRODUK]],TBLKATALOG[],6,FALSE) -> 2188.5877 | L4: =VLOOKUP(TBLPRODUKKELUARJUNI[[#This Row],[NAMA PRODUK]],TBLKATALOG[],7,FALSE) -> 309.60965 | M4: =VLOOKUP(TBLPRODUKKELUARJUNI[[#This Row],[NAMA PRODUK]],TBLKATALOG[],8,FALSE) -> 309.60965 | N4: =VLOOKUP(TBLPRODUKKELUARJUNI[[#This Row],[NAMA PRODUK]],TBLKATALOG[],9,FALSE) -> 2188.5877 | O4: 2 | P4: 2 | Q4: =TBLPRODUKKELUARJUNI[[#This Row],[MODAL]]*TBLPRODUKKELUARJUNI[[#This Row],[JUMLAH TERJUAL]] -> 12384.386 | R4: =TBLPRODUKKELUARJUNI[[#This Row],[BUDGET KOMISI]]*TBLPRODUKKELUARJUNI[[#This Row],[JUMLAH TERJUAL]] -> 1238.4386 | S4: =TBLPRODUKKELUARJUNI[[#This Row],[MODAL DITAMBAH BUDGET KOMISI]]*TBLPRODUKKELUARJUNI[[#This Row],[JUMLAH TERJUAL]] -> 13622.825 | T4: =TBLPRODUKKELUARJUNI[[#This Row],[HARGA JUAL]]*TBLPRODUKKELUARJUNI[[#This Row],[JUMLAH TERJUAL]] -> 18000 | U4: =TBLPRODUKKELUARJUNI[[#This Row],[SELISIH]]*TBLPRODUKKELUARJUNI[[#This Row],[JUMLAH TERJUAL]] -> 4377.1754 | V4: =TBLPRODUKKELUARJUNI[[#This Row],[LABA MITRA 8 %]]*TBLPRODUKKELUARJUNI[[#This Row],[JUMLAH TERJUAL]] -> 619.2193 | W4: =TBLPRODUKKELUARJUNI[[#This Row],[LABA KIRIM 8 %]]*TBLPRODUKKELUARJUNI[[#This Row],[JUMLAH TERKIRIM]] -> 619.2193 | X4: =TBLPRODUKKELUARJUNI[[#This Row],[TOTAL LABA MITRA 5%]]+TBLPRODUKKELUARJUNI[[#This Row],[TOTAL LABA KIRIM 5%]] -> 1238.4386 | Y4: =TBLPRODUKKELUARJUNI[[#This Row],[LABA BERSIH TOKO]]*TBLPRODUKKELUARJUNI[[#This Row],[JUMLAH TERJUAL]] -> 4377.1754
A5: 2026 | B5: JUNI | C5: 46198 | D5: KEBAB AYAM + SOSIZ (KECIL) PEDAS | E5: LUT CG | F5: =VLOOKUP(TBLPRODUKKELUARJUNI[[#This Row],[NAMA CUSTOMER]],TBLDATACUSTOMER[],4,FALSE) -> CAHYA GALLERY | G5: =VLOOKUP(TBLPRODUKKELUARJUNI[[#This Row],[NAMA PRODUK]],TBLKATALOG[],2,FALSE) -> 6192.193 | H5: =VLOOKUP(TBLPRODUKKELUARJUNI[[#This Row],[NAMA PRODUK]],TBLKATALOG[],3,FALSE) -> 619.2193 | I5: =VLOOKUP(TBLPRODUKKELUARJUNI[[#This Row],[NAMA PRODUK]],TBLKATALOG[],4,FALSE) -> 6811.4123 | J5: =VLOOKUP(TBLPRODUKKELUARJUNI[[#This Row],[NAMA PRODUK]],TBLKATALOG[],5,FALSE) -> 9000 | K5: =VLOOKUP(TBLPRODUKKELUARJUNI[[#This Row],[NAMA PRODUK]],TBLKATALOG[],6,FALSE) -> 2188.5877 | L5: =VLOOKUP(TBLPRODUKKELUARJUNI[[#This Row],[NAMA PRODUK]],TBLKATALOG[],7,FALSE) -> 309.60965 | M5: =VLOOKUP(TBLPRODUKKELUARJUNI[[#This Row],[NAMA PRODUK]],TBLKATALOG[],8,FALSE) -> 309.60965 | N5: =VLOOKUP(TBLPRODUKKELUARJUNI[[#This Row],[NAMA PRODUK]],TBLKATALOG[],9,FALSE) -> 2188.5877 | O5: 1 | P5: 1 | Q5: =TBLPRODUKKELUARJUNI[[#This Row],[MODAL]]*TBLPRODUKKELUARJUNI[[#This Row],[JUMLAH TERJUAL]] -> 6192.193 | R5: =TBLPRODUKKELUARJUNI[[#This Row],[BUDGET KOMISI]]*TBLPRODUKKELUARJUNI[[#This Row],[JUMLAH TERJUAL]] -> 619.2193 | S5: =TBLPRODUKKELUARJUNI[[#This Row],[MODAL DITAMBAH BUDGET KOMISI]]*TBLPRODUKKELUARJUNI[[#This Row],[JUMLAH TERJUAL]] -> 6811.4123 | T5: =TBLPRODUKKELUARJUNI[[#This Row],[HARGA JUAL]]*TBLPRODUKKELUARJUNI[[#This Row],[JUMLAH TERJUAL]] -> 9000 | U5: =TBLPRODUKKELUARJUNI[[#This Row],[SELISIH]]*TBLPRODUKKELUARJUNI[[#This Row],[JUMLAH TERJUAL]] -> 2188.5877 | V5: =TBLPRODUKKELUARJUNI[[#This Row],[LABA MITRA 8 %]]*TBLPRODUKKELUARJUNI[[#This Row],[JUMLAH TERJUAL]] -> 309.60965 | W5: =TBLPRODUKKELUARJUNI[[#This Row],[LABA KIRIM 8 %]]*TBLPRODUKKELUARJUNI[[#This Row],[JUMLAH TERKIRIM]] -> 309.60965 | X5: =TBLPRODUKKELUARJUNI[[#This Row],[TOTAL LABA MITRA 5%]]+TBLPRODUKKELUARJUNI[[#This Row],[TOTAL LABA KIRIM 5%]] -> 619.2193 | Y5: =TBLPRODUKKELUARJUNI[[#This Row],[LABA BERSIH TOKO]]*TBLPRODUKKELUARJUNI[[#This Row],[JUMLAH TERJUAL]] -> 2188.5877
A6: 2026 | B6: JUNI | C6: 46198 | D6: KEBAB AYAM MEDIUM PEDAS | E6: ANA | F6: =VLOOKUP(TBLPRODUKKELUARJUNI[[#This Row],[NAMA CUSTOMER]],TBLDATACUSTOMER[],4,FALSE) -> NURUL HIDAYATU SAMSIAH | G6: =VLOOKUP(TBLPRODUKKELUARJUNI[[#This Row],[NAMA PRODUK]],TBLKATALOG[],2,FALSE) -> 8378.6667 | H6: =VLOOKUP(TBLPRODUKKELUARJUNI[[#This Row],[NAMA PRODUK]],TBLKATALOG[],3,FALSE) -> 837.86667 | I6: =VLOOKUP(TBLPRODUKKELUARJUNI[[#This Row],[NAMA PRODUK]],TBLKATALOG[],4,FALSE) -> 9216.5333 | J6: =VLOOKUP(TBLPRODUKKELUARJUNI[[#This Row],[NAMA PRODUK]],TBLKATALOG[],5,FALSE) -> 12000 | K6: =VLOOKUP(TBLPRODUKKELUARJUNI[[#This Row],[NAMA PRODUK]],TBLKATALOG[],6,FALSE) -> 2783.4667 | L6: =VLOOKUP(TBLPRODUKKELUARJUNI[[#This Row],[NAMA PRODUK]],TBLKATALOG[],7,FALSE) -> 418.93333 | M6: =VLOOKUP(TBLPRODUKKELUARJUNI[[#This Row],[NAMA PRODUK]],TBLKATALOG[],8,FALSE) -> 418.93333 | N6: =VLOOKUP(TBLPRODUKKELUARJUNI[[#This Row],[NAMA PRODUK]],TBLKATALOG[],9,FALSE) -> 2783.4667 | O6: 3 | P6: 3 | Q6: =TBLPRODUKKELUARJUNI[[#This Row],[MODAL]]*TBLPRODUKKELUARJUNI[[#This Row],[JUMLAH TERJUAL]] -> 25136 | R6: =TBLPRODUKKELUARJUNI[[#This Row],[BUDGET KOMISI]]*TBLPRODUKKELUARJUNI[[#This Row],[JUMLAH TERJUAL]] -> 2513.6 | S6: =TBLPRODUKKELUARJUNI[[#This Row],[MODAL DITAMBAH BUDGET KOMISI]]*TBLPRODUKKELUARJUNI[[#This Row],[JUMLAH TERJUAL]] -> 27649.6 | T6: =TBLPRODUKKELUARJUNI[[#This Row],[HARGA JUAL]]*TBLPRODUKKELUARJUNI[[#This Row],[JUMLAH TERJUAL]] -> 36000 | U6: =TBLPRODUKKELUARJUNI[[#This Row],[SELISIH]]*TBLPRODUKKELUARJUNI[[#This Row],[JUMLAH TERJUAL]] -> 8350.4 | V6: =TBLPRODUKKELUARJUNI[[#This Row],[LABA MITRA 8 %]]*TBLPRODUKKELUARJUNI[[#This Row],[JUMLAH TERJUAL]] -> 1256.8 | W6: =TBLPRODUKKELUARJUNI[[#This Row],[LABA KIRIM 8 %]]*TBLPRODUKKELUARJUNI[[#This Row],[JUMLAH TERKIRIM]] -> 1256.8 | X6: =TBLPRODUKKELUARJUNI[[#This Row],[TOTAL LABA MITRA 5%]]+TBLPRODUKKELUARJUNI[[#This Row],[TOTAL LABA KIRIM 5%]] -> 2513.6 | Y6: =TBLPRODUKKELUARJUNI[[#This Row],[LABA BERSIH TOKO]]*TBLPRODUKKELUARJUNI[[#This Row],[JUMLAH TERJUAL]] -> 8350.4
A7: 2026 | B7: JUNI | C7: 46198 | D7: KEBAB AYAM MEDIUM PEDAS | E7: ANIS COKLATAN CG | F7: =VLOOKUP(TBLPRODUKKELUARJUNI[[#This Row],[NAMA CUSTOMER]],TBLDATACUSTOMER[],4,FALSE) -> CAHYA GALLERY | G7: =VLOOKUP(TBLPRODUKKELUARJUNI[[#This Row],[NAMA PRODUK]],TBLKATALOG[],2,FALSE) -> 8378.6667 | H7: =VLOOKUP(TBLPRODUKKELUARJUNI[[#This Row],[NAMA PRODUK]],TBLKATALOG[],3,FALSE) -> 837.86667 | I7: =VLOOKUP(TBLPRODUKKELUARJUNI[[#This Row],[NAMA PRODUK]],TBLKATALOG[],4,FALSE) -> 9216.5333 | J7: =VLOOKUP(TBLPRODUKKELUARJUNI[[#This Row],[NAMA PRODUK]],TBLKATALOG[],5,FALSE) -> 12000 | K7: =VLOOKUP(TBLPRODUKKELUARJUNI[[#This Row],[NAMA PRODUK]],TBLKATALOG[],6,FALSE) -> 2783.4667 | L7: =VLOOKUP(TBLPRODUKKELUARJUNI[[#This Row],[NAMA PRODUK]],TBLKATALOG[],7,FALSE) -> 418.93333 | M7: =VLOOKUP(TBLPRODUKKELUARJUNI[[#This Row],[NAMA PRODUK]],TBLKATALOG[],8,FALSE) -> 418.93333 | N7: =VLOOKUP(TBLPRODUKKELUARJUNI[[#This Row],[NAMA PRODUK]],TBLKATALOG[],9,FALSE) -> 2783.4667 | O7: 1 | P7: 1 | Q7: =TBLPRODUKKELUARJUNI[[#This Row],[MODAL]]*TBLPRODUKKELUARJUNI[[#This Row],[JUMLAH TERJUAL]] -> 8378.6667 | R7: =TBLPRODUKKELUARJUNI[[#This Row],[BUDGET KOMISI]]*TBLPRODUKKELUARJUNI[[#This Row],[JUMLAH TERJUAL]] -> 837.86667 | S7: =TBLPRODUKKELUARJUNI[[#This Row],[MODAL DITAMBAH BUDGET KOMISI]]*TBLPRODUKKELUARJUNI[[#This Row],[JUMLAH TERJUAL]] -> 9216.5333 | T7: =TBLPRODUKKELUARJUNI[[#This Row],[HARGA JUAL]]*TBLPRODUKKELUARJUNI[[#This Row],[JUMLAH TERJUAL]] -> 12000 | U7: =TBLPRODUKKELUARJUNI[[#This Row],[SELISIH]]*TBLPRODUKKELUARJUNI[[#This Row],[JUMLAH TERJUAL]] -> 2783.4667 | V7: =TBLPRODUKKELUARJUNI[[#This Row],[LABA MITRA 8 %]]*TBLPRODUKKELUARJUNI[[#This Row],[JUMLAH TERJUAL]] -> 418.93333 | W7: =TBLPRODUKKELUARJUNI[[#This Row],[LABA KIRIM 8 %]]*TBLPRODUKKELUARJUNI[[#This Row],[JUMLAH TERKIRIM]] -> 418.93333 | X7: =TBLPRODUKKELUARJUNI[[#This Row],[TOTAL LABA MITRA 5%]]+TBLPRODUKKELUARJUNI[[#This Row],[TOTAL LABA KIRIM 5%]] -> 837.86667 | Y7: =TBLPRODUKKELUARJUNI[[#This Row],[LABA BERSIH TOKO]]*TBLPRODUKKELUARJUNI[[#This Row],[JUMLAH TERJUAL]] -> 2783.4667
A8: 2026 | B8: JUNI | C8: 46198 | D8: KEBAB AYAM + SOSIZ (MEDIUM) PEDAS | E8: BIBI CG | F8: =VLOOKUP(TBLPRODUKKELUARJUNI[[#This Row],[NAMA CUSTOMER]],TBLDATACUSTOMER[],4,FALSE) -> CAHYA GALLERY | G8: =VLOOKUP(TBLPRODUKKELUARJUNI[[#This Row],[NAMA PRODUK]],TBLKATALOG[],2,FALSE) -> 8174.7193 | H8: =VLOOKUP(TBLPRODUKKELUARJUNI[[#This Row],[NAMA PRODUK]],TBLKATALOG[],3,FALSE) -> 817.47193 | I8: =VLOOKUP(TBLPRODUKKELUARJUNI[[#This Row],[NAMA PRODUK]],TBLKATALOG[],4,FALSE) -> 8992.1912 | J8: =VLOOKUP(TBLPRODUKKELUARJUNI[[#This Row],[NAMA PRODUK]],TBLKATALOG[],5,FALSE) -> 12000 | K8: =VLOOKUP(TBLPRODUKKELUARJUNI[[#This Row],[NAMA PRODUK]],TBLKATALOG[],6,FALSE) -> 3007.8088 | L8: =VLOOKUP(TBLPRODUKKELUARJUNI[[#This Row],[NAMA PRODUK]],TBLKATALOG[],7,FALSE) -> 408.73596 | M8: =VLOOKUP(TBLPRODUKKELUARJUNI[[#This Row],[NAMA PRODUK]],TBLKATALOG[],8,FALSE) -> 408.73596 | N8: =VLOOKUP(TBLPRODUKKELUARJUNI[[#This Row],[NAMA PRODUK]],TBLKATALOG[],9,FALSE) -> 3007.8088 | O8: 2 | P8: 2 | Q8: =TBLPRODUKKELUARJUNI[[#This Row],[MODAL]]*TBLPRODUKKELUARJUNI[[#This Row],[JUMLAH TERJUAL]] -> 16349.439 | R8: =TBLPRODUKKELUARJUNI[[#This Row],[BUDGET KOMISI]]*TBLPRODUKKELUARJUNI[[#This Row],[JUMLAH TERJUAL]] -> 1634.9439 | S8: =TBLPRODUKKELUARJUNI[[#This Row],[MODAL DITAMBAH BUDGET KOMISI]]*TBLPRODUKKELUARJUNI[[#This Row],[JUMLAH TERJUAL]] -> 17984.382 | T8: =TBLPRODUKKELUARJUNI[[#This Row],[HARGA JUAL]]*TBLPRODUKKELUARJUNI[[#This Row],[JUMLAH TERJUAL]] -> 24000 | U8: =TBLPRODUKKELUARJUNI[[#This Row],[SELISIH]]*TBLPRODUKKELUARJUNI[[#This Row],[JUMLAH TERJUAL]] -> 6015.6175 | V8: =TBLPRODUKKELUARJUNI[[#This Row],[LABA MITRA 8 %]]*TBLPRODUKKELUARJUNI[[#This Row],[JUMLAH TERJUAL]] -> 817.47193 | W8: =TBLPRODUKKELUARJUNI[[#This Row],[LABA KIRIM 8 %]]*TBLPRODUKKELUARJUNI[[#This Row],[JUMLAH TERKIRIM]] -> 817.47193 | X8: =TBLPRODUKKELUARJUNI[[#This Row],[TOTAL LABA MITRA 5%]]+TBLPRODUKKELUARJUNI[[#This Row],[TOTAL LABA KIRIM 5%]] -> 1634.9439 | Y8: =TBLPRODUKKELUARJUNI[[#This Row],[LABA BERSIH TOKO]]*TBLPRODUKKELUARJUNI[[#This Row],[JUMLAH TERJUAL]] -> 6015.6175
A9: 2026 | B9: JUNI | C9: 46198 | D9: KEBAB AYAM MEDIUM | E9: ANIS COKLATAN CG | F9: =VLOOKUP(TBLPRODUKKELUARJUNI[[#This Row],[NAMA CUSTOMER]],TBLDATACUSTOMER[],4,FALSE) -> CAHYA GALLERY | G9: =VLOOKUP(TBLPRODUKKELUARJUNI[[#This Row],[NAMA PRODUK]],TBLKATALOG[],2,FALSE) -> 8478.6667 | H9: =VLOOKUP(TBLPRODUKKELUARJUNI[[#This Row],[NAMA PRODUK]],TBLKATALOG[],3,FALSE) -> 847.86667 | I9: =VLOOKUP(TBLPRODUKKELUARJUNI[[#This Row],[NAMA PRODUK]],TBLKATALOG[],4,FALSE) -> 9326.5333 | J9: =VLOOKUP(TBLPRODUKKELUARJUNI[[#This Row],[NAMA PRODUK]],TBLKATALOG[],5,FALSE) -> 12000 | K9: =VLOOKUP(TBLPRODUKKELUARJUNI[[#This Row],[NAMA PRODUK]],TBLKATALOG[],6,FALSE) -> 2673.4667 | L9: =VLOOKUP(TBLPRODUKKELUARJUNI[[#This Row],[NAMA PRODUK]],TBLKATALOG[],7,FALSE) -> 423.93333 | M9: =VLOOKUP(TBLPRODUKKELUARJUNI[[#This Row],[NAMA PRODUK]],TBLKATALOG[],8,FALSE) -> 423.93333 | N9: =VLOOKUP(TBLPRODUKKELUARJUNI[[#This Row],[NAMA PRODUK]],TBLKATALOG[],9,FALSE) -> 2673.4667 | O9: 1 | P9: 1 | Q9: =TBLPRODUKKELUARJUNI[[#This Row],[MODAL]]*TBLPRODUKKELUARJUNI[[#This Row],[JUMLAH TERJUAL]] -> 8478.6667 | R9: =TBLPRODUKKELUARJUNI[[#This Row],[BUDGET KOMISI]]*TBLPRODUKKELUARJUNI[[#This Row],[JUMLAH TERJUAL]] -> 847.86667 | S9: =TBLPRODUKKELUARJUNI[[#This Row],[MODAL DITAMBAH BUDGET KOMISI]]*TBLPRODUKKELUARJUNI[[#This Row],[JUMLAH TERJUAL]] -> 9326.5333 | T9: =TBLPRODUKKELUARJUNI[[#This Row],[HARGA JUAL]]*TBLPRODUKKELUARJUNI[[#This Row],[JUMLAH TERJUAL]] -> 12000 | U9: =TBLPRODUKKELUARJUNI[[#This Row],[SELISIH]]*TBLPRODUKKELUARJUNI[[#This Row],[JUMLAH TERJUAL]] -> 2673.4667 | V9: =TBLPRODUKKELUARJUNI[[#This Row],[LABA MITRA 8 %]]*TBLPRODUKKELUARJUNI[[#This Row],[JUMLAH TERJUAL]] -> 423.93333 | W9: =TBLPRODUKKELUARJUNI[[#This Row],[LABA KIRIM 8 %]]*TBLPRODUKKELUARJUNI[[#This Row],[JUMLAH TERKIRIM]] -> 423.93333 | X9: =TBLPRODUKKELUARJUNI[[#This Row],[TOTAL LABA MITRA 5%]]+TBLPRODUKKELUARJUNI[[#This Row],[TOTAL LABA KIRIM 5%]] -> 847.86667 | Y9: =TBLPRODUKKELUARJUNI[[#This Row],[LABA BERSIH TOKO]]*TBLPRODUKKELUARJUNI[[#This Row],[JUMLAH TERJUAL]] -> 2673.4667
A10: 2026 | B10: JUNI | C10: 46198 | D10: KEBAB AYAM + SOSIZ (KECIL) | E10: ANDRI ARIF CAHYONO | F10: =VLOOKUP(TBLPRODUKKELUARJUNI[[#This Row],[NAMA CUSTOMER]],TBLDATACUSTOMER[],4,FALSE) -> NURUL HIDAYATU SAMSIAH | G10: =VLOOKUP(TBLPRODUKKELUARJUNI[[#This Row],[NAMA PRODUK]],TBLKATALOG[],2,FALSE) -> 6122.193 | H10: =VLOOKUP(TBLPRODUKKELUARJUNI[[#This Row],[NAMA PRODUK]],TBLKATALOG[],3,FALSE) -> 612.2193 | I10: =VLOOKUP(TBLPRODUKKELUARJUNI[[#This Row],[NAMA PRODUK]],TBLKATALOG[],4,FALSE) -> 6734.4123 | J10: =VLOOKUP(TBLPRODUKKELUARJUNI[[#This Row],[NAMA PRODUK]],TBLKATALOG[],5,FALSE) -> 9000 | K10: =VLOOKUP(TBLPRODUKKELUARJUNI[[#This Row],[NAMA PRODUK]],TBLKATALOG[],6,FALSE) -> 2265.5877 | L10: =VLOOKUP(TBLPRODUKKELUARJUNI[[#This Row],[NAMA PRODUK]],TBLKATALOG[],7,FALSE) -> 306.10965 | M10: =VLOOKUP(TBLPRODUKKELUARJUNI[[#This Row],[NAMA PRODUK]],TBLKATALOG[],8,FALSE) -> 306.10965 | N10: =VLOOKUP(TBLPRODUKKELUARJUNI[[#This Row],[NAMA PRODUK]],TBLKATALOG[],9,FALSE) -> 2265.5877 | O10: 2 | P10: 2 | Q10: =TBLPRODUKKELUARJUNI[[#This Row],[MODAL]]*TBLPRODUKKELUARJUNI[[#This Row],[JUMLAH TERJUAL]] -> 12244.386 | R10: =TBLPRODUKKELUARJUNI[[#This Row],[BUDGET KOMISI]]*TBLPRODUKKELUARJUNI[[#This Row],[JUMLAH TERJUAL]] -> 1224.4386 | S10: =TBLPRODUKKELUARJUNI[[#This Row],[MODAL DITAMBAH BUDGET KOMISI]]*TBLPRODUKKELUARJUNI[[#This Row],[JUMLAH TERJUAL]] -> 13468.825 | T10: =TBLPRODUKKELUARJUNI[[#This Row],[HARGA JUAL]]*TBLPRODUKKELUARJUNI[[#This Row],[JUMLAH TERJUAL]] -> 18000 | U10: =TBLPRODUKKELUARJUNI[[#This Row],[SELISIH]]*TBLPRODUKKELUARJUNI[[#This Row],[JUMLAH TERJUAL]] -> 4531.1754 | V10: =TBLPRODUKKELUARJUNI[[#This Row],[LABA MITRA 8 %]]*TBLPRODUKKELUARJUNI[[#This Row],[JUMLAH TERJUAL]] -> 612.2193 | W10: =TBLPRODUKKELUARJUNI[[#This Row],[LABA KIRIM 8 %]]*TBLPRODUKKELUARJUNI[[#This Row],[JUMLAH TERKIRIM]] -> 612.2193 | X10: =TBLPRODUKKELUARJUNI[[#This Row],[TOTAL LABA MITRA 5%]]+TBLPRODUKKELUARJUNI[[#This Row],[TOTAL LABA KIRIM 5%]] -> 1224.4386 | Y10: =TBLPRODUKKELUARJUNI[[#This Row],[LABA BERSIH TOKO]]*TBLPRODUKKELUARJUNI[[#This Row],[JUMLAH TERJUAL]] -> 4531.1754
A14: JULI
A15: TAHUN | B15: BULAN | C15: TANGGAL | D15: NAMA PRODUK | E15: NAMA CUSTOMER | F15: NAMA MITRA | G15: MODAL | H15: BUDGET KOMISI | I15: MODAL DITAMBAH BUDGET KOMISI | J15: HARGA JUAL | K15: SELISIH | L15: LABA MITRA 8 % | M15: LABA KIRIM 8 % | N15: LABA BERSIH TOKO | O15: JUMLAH TERJUAL | P15: JUMLAH TERKIRIM | Q15: TOTAL MODAL | R15: TOTAL JUMLAH LABA | S15: TOTAL MODAL DITAMBAH LABA | T15: TOTAL HARGA JUAL | U15: TOTAL SELISIH | V15: TOTAL LABA MITRA 5% | W15: TOTAL LABA KIRIM 5% | X15: TAKE HOME KOMISI UTAMA | Y15: TOTAL LABA BERSIH TOKO
A16: 2026 | B16: JULI | C16: 46206 | D16: KEBAB AYAM + SOSIZ (KECIL) PEDAS | E16: RIA NDU | F16: =VLOOKUP(TBLPRODUKKELUARJULI[[#This Row],[NAMA CUSTOMER]],TBLDATACUSTOMER[],4,FALSE) -> RIA | G16: =VLOOKUP(TBLPRODUKKELUARJULI[[#This Row],[NAMA PRODUK]],TBLKATALOG[],2,FALSE) -> 6192.193 | H16: =VLOOKUP(TBLPRODUKKELUARJULI[[#This Row],[NAMA PRODUK]],TBLKATALOG[],3,FALSE) -> 619.2193 | I16: =VLOOKUP(TBLPRODUKKELUARJULI[[#This Row],[NAMA PRODUK]],TBLKATALOG[],4,FALSE) -> 6811.4123 | J16: =VLOOKUP(TBLPRODUKKELUARJULI[[#This Row],[NAMA PRODUK]],TBLKATALOG[],5,FALSE) -> 9000 | K16: =VLOOKUP(TBLPRODUKKELUARJULI[[#This Row],[NAMA PRODUK]],TBLKATALOG[],6,FALSE) -> 2188.5877 | L16: =VLOOKUP(TBLPRODUKKELUARJULI[[#This Row],[NAMA PRODUK]],TBLKATALOG[],7,FALSE) -> 309.60965 | M16: =VLOOKUP(TBLPRODUKKELUARJULI[[#This Row],[NAMA PRODUK]],TBLKATALOG[],8,FALSE) -> 309.60965 | N16: =VLOOKUP(TBLPRODUKKELUARJULI[[#This Row],[NAMA PRODUK]],TBLKATALOG[],9,FALSE) -> 2188.5877 | O16: 2 | P16: 2 | Q16: =TBLPRODUKKELUARJULI[[#This Row],[MODAL]]*TBLPRODUKKELUARJULI[[#This Row],[JUMLAH TERJUAL]] -> 12384.386 | R16: =TBLPRODUKKELUARJULI[[#This Row],[BUDGET KOMISI]]*TBLPRODUKKELUARJULI[[#This Row],[JUMLAH TERJUAL]] -> 1238.4386 | S16: =TBLPRODUKKELUARJULI[[#This Row],[MODAL DITAMBAH BUDGET KOMISI]]*TBLPRODUKKELUARJULI[[#This Row],[JUMLAH TERJUAL]] -> 13622.825 | T16: =TBLPRODUKKELUARJULI[[#This Row],[HARGA JUAL]]*TBLPRODUKKELUARJULI[[#This Row],[JUMLAH TERJUAL]] -> 18000 | U16: =TBLPRODUKKELUARJULI[[#This Row],[SELISIH]]*TBLPRODUKKELUARJULI[[#This Row],[JUMLAH TERJUAL]] -> 4377.1754 | V16: =TBLPRODUKKELUARJULI[[#This Row],[LABA MITRA 8 %]]*TBLPRODUKKELUARJULI[[#This Row],[JUMLAH TERJUAL]] -> 619.2193 | W16: =TBLPRODUKKELUARJULI[[#This Row],[LABA KIRIM 8 %]]*TBLPRODUKKELUARJULI[[#This Row],[JUMLAH TERKIRIM]] -> 619.2193 | X16: =TBLPRODUKKELUARJULI[[#This Row],[TOTAL LABA MITRA 5%]]+TBLPRODUKKELUARJULI[[#This Row],[TOTAL LABA KIRIM 5%]] -> 1238.4386 | Y16: =TBLPRODUKKELUARJULI[[#This Row],[LABA BERSIH TOKO]]*TBLPRODUKKELUARJULI[[#This Row],[JUMLAH TERJUAL]] -> 4377.1754
A17: 2026 | B17: JULI | C17: 46206 | D17: KEBAB AYAM + SOSIZ (KECIL) | E17: RIA NDU | F17: =VLOOKUP(TBLPRODUKKELUARJULI[[#This Row],[NAMA CUSTOMER]],TBLDATACUSTOMER[],4,FALSE) -> RIA | G17: =VLOOKUP(TBLPRODUKKELUARJULI[[#This Row],[NAMA PRODUK]],TBLKATALOG[],2,FALSE) -> 6122.193 | H17: =VLOOKUP(TBLPRODUKKELUARJULI[[#This Row],[NAMA PRODUK]],TBLKATALOG[],3,FALSE) -> 612.2193 | I17: =VLOOKUP(TBLPRODUKKELUARJULI[[#This Row],[NAMA PRODUK]],TBLKATALOG[],4,FALSE) -> 6734.4123 | J17: =VLOOKUP(TBLPRODUKKELUARJULI[[#This Row],[NAMA PRODUK]],TBLKATALOG[],5,FALSE) -> 9000 | K17: =VLOOKUP(TBLPRODUKKELUARJULI[[#This Row],[NAMA PRODUK]],TBLKATALOG[],6,FALSE) -> 2265.5877 | L17: =VLOOKUP(TBLPRODUKKELUARJULI[[#This Row],[NAMA PRODUK]],TBLKATALOG[],7,FALSE) -> 306.10965 | M17: =VLOOKUP(TBLPRODUKKELUARJULI[[#This Row],[NAMA PRODUK]],TBLKATALOG[],8,FALSE) -> 306.10965 | N17: =VLOOKUP(TBLPRODUKKELUARJULI[[#This Row],[NAMA PRODUK]],TBLKATALOG[],9,FALSE) -> 2265.5877 | O17: 2 | P17: 2 | Q17: =TBLPRODUKKELUARJULI[[#This Row],[MODAL]]*TBLPRODUKKELUARJULI[[#This Row],[JUMLAH TERJUAL]] -> 12244.386 | R17: =TBLPRODUKKELUARJULI[[#This Row],[BUDGET KOMISI]]*TBLPRODUKKELUARJULI[[#This Row],[JUMLAH TERJUAL]] -> 1224.4386 | S17: =TBLPRODUKKELUARJULI[[#This Row],[MODAL DITAMBAH BUDGET KOMISI]]*TBLPRODUKKELUARJULI[[#This Row],[JUMLAH TERJUAL]] -> 13468.825 | T17: =TBLPRODUKKELUARJULI[[#This Row],[HARGA JUAL]]*TBLPRODUKKELUARJULI[[#This Row],[JUMLAH TERJUAL]] -> 18000 | U17: =TBLPRODUKKELUARJULI[[#This Row],[SELISIH]]*TBLPRODUKKELUARJULI[[#This Row],[JUMLAH TERJUAL]] -> 4531.1754 | V17: =TBLPRODUKKELUARJULI[[#This Row],[LABA MITRA 8 %]]*TBLPRODUKKELUARJULI[[#This Row],[JUMLAH TERJUAL]] -> 612.2193 | W17: =TBLPRODUKKELUARJULI[[#This Row],[LABA KIRIM 8 %]]*TBLPRODUKKELUARJULI[[#This Row],[JUMLAH TERKIRIM]] -> 612.2193 | X17: =TBLPRODUKKELUARJULI[[#This Row],[TOTAL LABA MITRA 5%]]+TBLPRODUKKELUARJULI[[#This Row],[TOTAL LABA KIRIM 5%]] -> 1224.4386 | Y17: =TBLPRODUKKELUARJULI[[#This Row],[LABA BERSIH TOKO]]*TBLPRODUKKELUARJULI[[#This Row],[JUMLAH TERJUAL]] -> 4531.1754
A18: 2026 | B18: JULI | C18: 46207 | D18: KEBAB AYAM + SOSIZ (KECIL) PEDAS | E18: RIA NDU | F18: =VLOOKUP(TBLPRODUKKELUARJULI[[#This Row],[NAMA CUSTOMER]],TBLDATACUSTOMER[],4,FALSE) -> RIA | G18: =VLOOKUP(TBLPRODUKKELUARJULI[[#This Row],[NAMA PRODUK]],TBLKATALOG[],2,FALSE) -> 6192.193 | H18: =VLOOKUP(TBLPRODUKKELUARJULI[[#This Row],[NAMA PRODUK]],TBLKATALOG[],3,FALSE) -> 619.2193 | I18: =VLOOKUP(TBLPRODUKKELUARJULI[[#This Row],[NAMA PRODUK]],TBLKATALOG[],4,FALSE) -> 6811.4123 | J18: =VLOOKUP(TBLPRODUKKELUARJULI[[#This Row],[NAMA PRODUK]],TBLKATALOG[],5,FALSE) -> 9000 | K18: =VLOOKUP(TBLPRODUKKELUARJULI[[#This Row],[NAMA PRODUK]],TBLKATALOG[],6,FALSE) -> 2188.5877 | L18: =VLOOKUP(TBLPRODUKKELUARJULI[[#This Row],[NAMA PRODUK]],TBLKATALOG[],7,FALSE) -> 309.60965 | M18: =VLOOKUP(TBLPRODUKKELUARJULI[[#This Row],[NAMA PRODUK]],TBLKATALOG[],8,FALSE) -> 309.60965 | N18: =VLOOKUP(TBLPRODUKKELUARJULI[[#This Row],[NAMA PRODUK]],TBLKATALOG[],9,FALSE) -> 2188.5877 | O18: 2 | P18: 2 | Q18: =TBLPRODUKKELUARJULI[[#This Row],[MODAL]]*TBLPRODUKKELUARJULI[[#This Row],[JUMLAH TERJUAL]] -> 12384.386 | R18: =TBLPRODUKKELUARJULI[[#This Row],[BUDGET KOMISI]]*TBLPRODUKKELUARJULI[[#This Row],[JUMLAH TERJUAL]] -> 1238.4386 | S18: =TBLPRODUKKELUARJULI[[#This Row],[MODAL DITAMBAH BUDGET KOMISI]]*TBLPRODUKKELUARJULI[[#This Row],[JUMLAH TERJUAL]] -> 13622.825 | T18: =TBLPRODUKKELUARJULI[[#This Row],[HARGA JUAL]]*TBLPRODUKKELUARJULI[[#This Row],[JUMLAH TERJUAL]] -> 18000 | U18: =TBLPRODUKKELUARJULI[[#This Row],[SELISIH]]*TBLPRODUKKELUARJULI[[#This Row],[JUMLAH TERJUAL]] -> 4377.1754 | V18: =TBLPRODUKKELUARJULI[[#This Row],[LABA MITRA 8 %]]*TBLPRODUKKELUARJULI[[#This Row],[JUMLAH TERJUAL]] -> 619.2193 | W18: =TBLPRODUKKELUARJULI[[#This Row],[LABA KIRIM 8 %]]*TBLPRODUKKELUARJULI[[#This Row],[JUMLAH TERKIRIM]] -> 619.2193 | X18: =TBLPRODUKKELUARJULI[[#This Row],[TOTAL LABA MITRA 5%]]+TBLPRODUKKELUARJULI[[#This Row],[TOTAL LABA KIRIM 5%]] -> 1238.4386 | Y18: =TBLPRODUKKELUARJULI[[#This Row],[LABA BERSIH TOKO]]*TBLPRODUKKELUARJULI[[#This Row],[JUMLAH TERJUAL]] -> 4377.1754
A19: 2026 | B19: JULI | C19: 46207 | D19: KEBAB AYAM + SOSIZ (KECIL) | E19: RIA NDU | F19: =VLOOKUP(TBLPRODUKKELUARJULI[[#This Row],[NAMA CUSTOMER]],TBLDATACUSTOMER[],4,FALSE) -> RIA | G19: =VLOOKUP(TBLPRODUKKELUARJULI[[#This Row],[NAMA PRODUK]],TBLKATALOG[],2,FALSE) -> 6122.193 | H19: =VLOOKUP(TBLPRODUKKELUARJULI[[#This Row],[NAMA PRODUK]],TBLKATALOG[],3,FALSE) -> 612.2193 | I19: =VLOOKUP(TBLPRODUKKELUARJULI[[#This Row],[NAMA PRODUK]],TBLKATALOG[],4,FALSE) -> 6734.4123 | J19: =VLOOKUP(TBLPRODUKKELUARJULI[[#This Row],[NAMA PRODUK]],TBLKATALOG[],5,FALSE) -> 9000 | K19: =VLOOKUP(TBLPRODUKKELUARJULI[[#This Row],[NAMA PRODUK]],TBLKATALOG[],6,FALSE) -> 2265.5877 | L19: =VLOOKUP(TBLPRODUKKELUARJULI[[#This Row],[NAMA PRODUK]],TBLKATALOG[],7,FALSE) -> 306.10965 | M19: =VLOOKUP(TBLPRODUKKELUARJULI[[#This Row],[NAMA PRODUK]],TBLKATALOG[],8,FALSE) -> 306.10965 | N19: =VLOOKUP(TBLPRODUKKELUARJULI[[#This Row],[NAMA PRODUK]],TBLKATALOG[],9,FALSE) -> 2265.5877 | O19: 3 | P19: 3 | Q19: =TBLPRODUKKELUARJULI[[#This Row],[MODAL]]*TBLPRODUKKELUARJULI[[#This Row],[JUMLAH TERJUAL]] -> 18366.579 | R19: =TBLPRODUKKELUARJULI[[#This Row],[BUDGET KOMISI]]*TBLPRODUKKELUARJULI[[#This Row],[JUMLAH TERJUAL]] -> 1836.6579 | S19: =TBLPRODUKKELUARJULI[[#This Row],[MODAL DITAMBAH BUDGET KOMISI]]*TBLPRODUKKELUARJULI[[#This Row],[JUMLAH TERJUAL]] -> 20203.237 | T19: =TBLPRODUKKELUARJULI[[#This Row],[HARGA JUAL]]*TBLPRODUKKELUARJULI[[#This Row],[JUMLAH TERJUAL]] -> 27000 | U19: =TBLPRODUKKELUARJULI[[#This Row],[SELISIH]]*TBLPRODUKKELUARJULI[[#This Row],[JUMLAH TERJUAL]] -> 6796.7632 | V19: =TBLPRODUKKELUARJULI[[#This Row],[LABA MITRA 8 %]]*TBLPRODUKKELUARJULI[[#This Row],[JUMLAH TERJUAL]] -> 918.32895 | W19: =TBLPRODUKKELUARJULI[[#This Row],[LABA KIRIM 8 %]]*TBLPRODUKKELUARJULI[[#This Row],[JUMLAH TERKIRIM]] -> 918.32895 | X19: =TBLPRODUKKELUARJULI[[#This Row],[TOTAL LABA MITRA 5%]]+TBLPRODUKKELUARJULI[[#This Row],[TOTAL LABA KIRIM 5%]] -> 1836.6579 | Y19: =TBLPRODUKKELUARJULI[[#This Row],[LABA BERSIH TOKO]]*TBLPRODUKKELUARJULI[[#This Row],[JUMLAH TERJUAL]] -> 6796.7632
A20: 2026 | B20: JULI | C20: 46207 | D20: KEBAB AYAM + SOSIZ (MEDIUM) PEDAS | E20: BU RANI NURUL | F20: =VLOOKUP(TBLPRODUKKELUARJULI[[#This Row],[NAMA CUSTOMER]],TBLDATACUSTOMER[],4,FALSE) -> NURUL HIDAYATU SAMSIAH | G20: =VLOOKUP(TBLPRODUKKELUARJULI[[#This Row],[NAMA PRODUK]],TBLKATALOG[],2,FALSE) -> 8174.7193 | H20: =VLOOKUP(TBLPRODUKKELUARJULI[[#This Row],[NAMA PRODUK]],TBLKATALOG[],3,FALSE) -> 817.47193 | I20: =VLOOKUP(TBLPRODUKKELUARJULI[[#This Row],[NAMA PRODUK]],TBLKATALOG[],4,FALSE) -> 8992.1912 | J20: =VLOOKUP(TBLPRODUKKELUARJULI[[#This Row],[NAMA PRODUK]],TBLKATALOG[],5,FALSE) -> 12000 | K20: =VLOOKUP(TBLPRODUKKELUARJULI[[#This Row],[NAMA PRODUK]],TBLKATALOG[],6,FALSE) -> 3007.8088 | L20: =VLOOKUP(TBLPRODUKKELUARJULI[[#This Row],[NAMA PRODUK]],TBLKATALOG[],7,FALSE) -> 408.73596 | M20: =VLOOKUP(TBLPRODUKKELUARJULI[[#This Row],[NAMA PRODUK]],TBLKATALOG[],8,FALSE) -> 408.73596 | N20: =VLOOKUP(TBLPRODUKKELUARJULI[[#This Row],[NAMA PRODUK]],TBLKATALOG[],9,FALSE) -> 3007.8088 | O20: 5 | P20: 5 | Q20: =TBLPRODUKKELUARJULI[[#This Row],[MODAL]]*TBLPRODUKKELUARJULI[[#This Row],[JUMLAH TERJUAL]] -> 40873.596 | R20: =TBLPRODUKKELUARJULI[[#This Row],[BUDGET KOMISI]]*TBLPRODUKKELUARJULI[[#This Row],[JUMLAH TERJUAL]] -> 4087.3596 | S20: =TBLPRODUKKELUARJULI[[#This Row],[MODAL DITAMBAH BUDGET KOMISI]]*TBLPRODUKKELUARJULI[[#This Row],[JUMLAH TERJUAL]] -> 44960.956 | T20: =TBLPRODUKKELUARJULI[[#This Row],[HARGA JUAL]]*TBLPRODUKKELUARJULI[[#This Row],[JUMLAH TERJUAL]] -> 60000 | U20: =TBLPRODUKKELUARJULI[[#This Row],[SELISIH]]*TBLPRODUKKELUARJULI[[#This Row],[JUMLAH TERJUAL]] -> 15039.044 | V20: =TBLPRODUKKELUARJULI[[#This Row],[LABA MITRA 8 %]]*TBLPRODUKKELUARJULI[[#This Row],[JUMLAH TERJUAL]] -> 2043.6798 | W20: =TBLPRODUKKELUARJULI[[#This Row],[LABA KIRIM 8 %]]*TBLPRODUKKELUARJULI[[#This Row],[JUMLAH TERKIRIM]] -> 2043.6798 | X20: =TBLPRODUKKELUARJULI[[#This Row],[TOTAL LABA MITRA 5%]]+TBLPRODUKKELUARJULI[[#This Row],[TOTAL LABA KIRIM 5%]] -> 4087.3596 | Y20: =TBLPRODUKKELUARJULI[[#This Row],[LABA BERSIH TOKO]]*TBLPRODUKKELUARJULI[[#This Row],[JUMLAH TERJUAL]] -> 15039.044
A21: 2026 | B21: JULI | C21: 46207 | D21: KEBAB AYAM + SOSIZ (MEDIUM) | E21: BU RANI NURUL | F21: =VLOOKUP(TBLPRODUKKELUARJULI[[#This Row],[NAMA CUSTOMER]],TBLDATACUSTOMER[],4,FALSE) -> NURUL HIDAYATU SAMSIAH | G21: =VLOOKUP(TBLPRODUKKELUARJULI[[#This Row],[NAMA PRODUK]],TBLKATALOG[],2,FALSE) -> 8274.7193 | H21: =VLOOKUP(TBLPRODUKKELUARJULI[[#This Row],[NAMA PRODUK]],TBLKATALOG[],3,FALSE) -> 827.47193 | I21: =VLOOKUP(TBLPRODUKKELUARJULI[[#This Row],[NAMA PRODUK]],TBLKATALOG[],4,FALSE) -> 9102.1912 | J21: =VLOOKUP(TBLPRODUKKELUARJULI[[#This Row],[NAMA PRODUK]],TBLKATALOG[],5,FALSE) -> 12000 | K21: =VLOOKUP(TBLPRODUKKELUARJULI[[#This Row],[NAMA PRODUK]],TBLKATALOG[],6,FALSE) -> 2897.8088 | L21: =VLOOKUP(TBLPRODUKKELUARJULI[[#This Row],[NAMA PRODUK]],TBLKATALOG[],7,FALSE) -> 413.73596 | M21: =VLOOKUP(TBLPRODUKKELUARJULI[[#This Row],[NAMA PRODUK]],TBLKATALOG[],8,FALSE) -> 413.73596 | N21: =VLOOKUP(TBLPRODUKKELUARJULI[[#This Row],[NAMA PRODUK]],TBLKATALOG[],9,FALSE) -> 2897.8088 | O21: 2 | P21: 2 | Q21: =TBLPRODUKKELUARJULI[[#This Row],[MODAL]]*TBLPRODUKKELUARJULI[[#This Row],[JUMLAH TERJUAL]] -> 16549.439 | R21: =TBLPRODUKKELUARJULI[[#This Row],[BUDGET KOMISI]]*TBLPRODUKKELUARJULI[[#This Row],[JUMLAH TERJUAL]] -> 1654.9439 | S21: =TBLPRODUKKELUARJULI[[#This Row],[MODAL DITAMBAH BUDGET KOMISI]]*TBLPRODUKKELUARJULI[[#This Row],[JUMLAH TERJUAL]] -> 18204.382 | T21: =TBLPRODUKKELUARJULI[[#This Row],[HARGA JUAL]]*TBLPRODUKKELUARJULI[[#This Row],[JUMLAH TERJUAL]] -> 24000 | U21: =TBLPRODUKKELUARJULI[[#This Row],[SELISIH]]*TBLPRODUKKELUARJULI[[#This Row],[JUMLAH TERJUAL]] -> 5795.6175 | V21: =TBLPRODUKKELUARJULI[[#This Row],[LABA MITRA 8 %]]*TBLPRODUKKELUARJULI[[#This Row],[JUMLAH TERJUAL]] -> 827.47193 | W21: =TBLPRODUKKELUARJULI[[#This Row],[LABA KIRIM 8 %]]*TBLPRODUKKELUARJULI[[#This Row],[JUMLAH TERKIRIM]] -> 827.47193 | X21: =TBLPRODUKKELUARJULI[[#This Row],[TOTAL LABA MITRA 5%]]+TBLPRODUKKELUARJULI[[#This Row],[TOTAL LABA KIRIM 5%]] -> 1654.9439 | Y21: =TBLPRODUKKELUARJULI[[#This Row],[LABA BERSIH TOKO]]*TBLPRODUKKELUARJULI[[#This Row],[JUMLAH TERJUAL]] -> 5795.6175
A22: 2026 | B22: JULI | C22: 46207 | D22: KEBAB AYAM + SOSIZ (KECIL) PEDAS | E22: ANDRI ARIF CAHYONO | F22: =VLOOKUP(TBLPRODUKKELUARJULI[[#This Row],[NAMA CUSTOMER]],TBLDATACUSTOMER[],4,FALSE) -> NURUL HIDAYATU SAMSIAH | G22: =VLOOKUP(TBLPRODUKKELUARJULI[[#This Row],[NAMA PRODUK]],TBLKATALOG[],2,FALSE) -> 6192.193 | H22: =VLOOKUP(TBLPRODUKKELUARJULI[[#This Row],[NAMA PRODUK]],TBLKATALOG[],3,FALSE) -> 619.2193 | I22: =VLOOKUP(TBLPRODUKKELUARJULI[[#This Row],[NAMA PRODUK]],TBLKATALOG[],4,FALSE) -> 6811.4123 | J22: =VLOOKUP(TBLPRODUKKELUARJULI[[#This Row],[NAMA PRODUK]],TBLKATALOG[],5,FALSE) -> 9000 | K22: =VLOOKUP(TBLPRODUKKELUARJULI[[#This Row],[NAMA PRODUK]],TBLKATALOG[],6,FALSE) -> 2188.5877 | L22: =VLOOKUP(TBLPRODUKKELUARJULI[[#This Row],[NAMA PRODUK]],TBLKATALOG[],7,FALSE) -> 309.60965 | M22: =VLOOKUP(TBLPRODUKKELUARJULI[[#This Row],[NAMA PRODUK]],TBLKATALOG[],8,FALSE) -> 309.60965 | N22: =VLOOKUP(TBLPRODUKKELUARJULI[[#This Row],[NAMA PRODUK]],TBLKATALOG[],9,FALSE) -> 2188.5877 | O22: 1 | P22: 1 | Q22: =TBLPRODUKKELUARJULI[[#This Row],[MODAL]]*TBLPRODUKKELUARJULI[[#This Row],[JUMLAH TERJUAL]] -> 6192.193 | R22: =TBLPRODUKKELUARJULI[[#This Row],[BUDGET KOMISI]]*TBLPRODUKKELUARJULI[[#This Row],[JUMLAH TERJUAL]] -> 619.2193 | S22: =TBLPRODUKKELUARJULI[[#This Row],[MODAL DITAMBAH BUDGET KOMISI]]*TBLPRODUKKELUARJULI[[#This Row],[JUMLAH TERJUAL]] -> 6811.4123 | T22: =TBLPRODUKKELUARJULI[[#This Row],[HARGA JUAL]]*TBLPRODUKKELUARJULI[[#This Row],[JUMLAH TERJUAL]] -> 9000 | U22: =TBLPRODUKKELUARJULI[[#This Row],[SELISIH]]*TBLPRODUKKELUARJULI[[#This Row],[JUMLAH TERJUAL]] -> 2188.5877 | V22: =TBLPRODUKKELUARJULI[[#This Row],[LABA MITRA 8 %]]*TBLPRODUKKELUARJULI[[#This Row],[JUMLAH TERJUAL]] -> 309.60965 | W22: =TBLPRODUKKELUARJULI[[#This Row],[LABA KIRIM 8 %]]*TBLPRODUKKELUARJULI[[#This Row],[JUMLAH TERKIRIM]] -> 309.60965 | X22: =TBLPRODUKKELUARJULI[[#This Row],[TOTAL LABA MITRA 5%]]+TBLPRODUKKELUARJULI[[#This Row],[TOTAL LABA KIRIM 5%]] -> 619.2193 | Y22: =TBLPRODUKKELUARJULI[[#This Row],[LABA BERSIH TOKO]]*TBLPRODUKKELUARJULI[[#This Row],[JUMLAH TERJUAL]] -> 2188.5877
A23: 2026 | B23: JULI | C23: 46207 | D23: KEBAB AYAM + SOSIZ (MEDIUM) | E23: DENI | F23: =VLOOKUP(TBLPRODUKKELUARJULI[[#This Row],[NAMA CUSTOMER]],TBLDATACUSTOMER[],4,FALSE) -> DENI | G23: =VLOOKUP(TBLPRODUKKELUARJULI[[#This Row],[NAMA PRODUK]],TBLKATALOG[],2,FALSE) -> 8274.7193 | H23: =VLOOKUP(TBLPRODUKKELUARJULI[[#This Row],[NAMA PRODUK]],TBLKATALOG[],3,FALSE) -> 827.47193 | I23: =VLOOKUP(TBLPRODUKKELUARJULI[[#This Row],[NAMA PRODUK]],TBLKATALOG[],4,FALSE) -> 9102.1912 | J23: =VLOOKUP(TBLPRODUKKELUARJULI[[#This Row],[NAMA PRODUK]],TBLKATALOG[],5,FALSE) -> 12000 | K23: =VLOOKUP(TBLPRODUKKELUARJULI[[#This Row],[NAMA PRODUK]],TBLKATALOG[],6,FALSE) -> 2897.8088 | L23: =VLOOKUP(TBLPRODUKKELUARJULI[[#This Row],[NAMA PRODUK]],TBLKATALOG[],7,FALSE) -> 413.73596 | M23: =VLOOKUP(TBLPRODUKKELUARJULI[[#This Row],[NAMA PRODUK]],TBLKATALOG[],8,FALSE) -> 413.73596 | N23: =VLOOKUP(TBLPRODUKKELUARJULI[[#This Row],[NAMA PRODUK]],TBLKATALOG[],9,FALSE) -> 2897.8088 | O23: 1 | P23: 1 | Q23: =TBLPRODUKKELUARJULI[[#This Row],[MODAL]]*TBLPRODUKKELUARJULI[[#This Row],[JUMLAH TERJUAL]] -> 8274.7193 | R23: =TBLPRODUKKELUARJULI[[#This Row],[BUDGET KOMISI]]*TBLPRODUKKELUARJULI[[#This Row],[JUMLAH TERJUAL]] -> 827.47193 | S23: =TBLPRODUKKELUARJULI[[#This Row],[MODAL DITAMBAH BUDGET KOMISI]]*TBLPRODUKKELUARJULI[[#This Row],[JUMLAH TERJUAL]] -> 9102.1912 | T23: =TBLPRODUKKELUARJULI[[#This Row],[HARGA JUAL]]*TBLPRODUKKELUARJULI[[#This Row],[JUMLAH TERJUAL]] -> 12000 | U23: =TBLPRODUKKELUARJULI[[#This Row],[SELISIH]]*TBLPRODUKKELUARJULI[[#This Row],[JUMLAH TERJUAL]] -> 2897.8088 | V23: =TBLPRODUKKELUARJULI[[#This Row],[LABA MITRA 8 %]]*TBLPRODUKKELUARJULI[[#This Row],[JUMLAH TERJUAL]] -> 413.73596 | W23: =TBLPRODUKKELUARJULI[[#This Row],[LABA KIRIM 8 %]]*TBLPRODUKKELUARJULI[[#This Row],[JUMLAH TERKIRIM]] -> 413.73596 | X23: =TBLPRODUKKELUARJULI[[#This Row],[TOTAL LABA MITRA 5%]]+TBLPRODUKKELUARJULI[[#This Row],[TOTAL LABA KIRIM 5%]] -> 827.47193 | Y23: =TBLPRODUKKELUARJULI[[#This Row],[LABA BERSIH TOKO]]*TBLPRODUKKELUARJULI[[#This Row],[JUMLAH TERJUAL]] -> 2897.8088
A24: 2026 | B24: JULI | C24: 46208 | D24: KEBAB AYAM + SOSIZ (KECIL) PEDAS | E24: RIA NDU | F24: =VLOOKUP(TBLPRODUKKELUARJULI[[#This Row],[NAMA CUSTOMER]],TBLDATACUSTOMER[],4,FALSE) -> RIA | G24: =VLOOKUP(TBLPRODUKKELUARJULI[[#This Row],[NAMA PRODUK]],TBLKATALOG[],2,FALSE) -> 6192.193 | H24: =VLOOKUP(TBLPRODUKKELUARJULI[[#This Row],[NAMA PRODUK]],TBLKATALOG[],3,FALSE) -> 619.2193 | I24: =VLOOKUP(TBLPRODUKKELUARJULI[[#This Row],[NAMA PRODUK]],TBLKATALOG[],4,FALSE) -> 6811.4123 | J24: =VLOOKUP(TBLPRODUKKELUARJULI[[#This Row],[NAMA PRODUK]],TBLKATALOG[],5,FALSE) -> 9000 | K24: =VLOOKUP(TBLPRODUKKELUARJULI[[#This Row],[NAMA PRODUK]],TBLKATALOG[],6,FALSE) -> 2188.5877 | L24: =VLOOKUP(TBLPRODUKKELUARJULI[[#This Row],[NAMA PRODUK]],TBLKATALOG[],7,FALSE) -> 309.60965 | M24: =VLOOKUP(TBLPRODUKKELUARJULI[[#This Row],[NAMA PRODUK]],TBLKATALOG[],8,FALSE) -> 309.60965 | N24: =VLOOKUP(TBLPRODUKKELUARJULI[[#This Row],[NAMA PRODUK]],TBLKATALOG[],9,FALSE) -> 2188.5877 | O24: 2 | P24: 2 | Q24: =TBLPRODUKKELUARJULI[[#This Row],[MODAL]]*TBLPRODUKKELUARJULI[[#This Row],[JUMLAH TERJUAL]] -> 12384.386 | R24: =TBLPRODUKKELUARJULI[[#This Row],[BUDGET KOMISI]]*TBLPRODUKKELUARJULI[[#This Row],[JUMLAH TERJUAL]] -> 1238.4386 | S24: =TBLPRODUKKELUARJULI[[#This Row],[MODAL DITAMBAH BUDGET KOMISI]]*TBLPRODUKKELUARJULI[[#This Row],[JUMLAH TERJUAL]] -> 13622.825 | T24: =TBLPRODUKKELUARJULI[[#This Row],[HARGA JUAL]]*TBLPRODUKKELUARJULI[[#This Row],[JUMLAH TERJUAL]] -> 18000 | U24: =TBLPRODUKKELUARJULI[[#This Row],[SELISIH]]*TBLPRODUKKELUARJULI[[#This Row],[JUMLAH TERJUAL]] -> 4377.1754 | V24: =TBLPRODUKKELUARJULI[[#This Row],[LABA MITRA 8 %]]*TBLPRODUKKELUARJULI[[#This Row],[JUMLAH TERJUAL]] -> 619.2193 | W24: =TBLPRODUKKELUARJULI[[#This Row],[LABA KIRIM 8 %]]*TBLPRODUKKELUARJULI[[#This Row],[JUMLAH TERKIRIM]] -> 619.2193 | X24: =TBLPRODUKKELUARJULI[[#This Row],[TOTAL LABA MITRA 5%]]+TBLPRODUKKELUARJULI[[#This Row],[TOTAL LABA KIRIM 5%]] -> 1238.4386 | Y24: =TBLPRODUKKELUARJULI[[#This Row],[LABA BERSIH TOKO]]*TBLPRODUKKELUARJULI[[#This Row],[JUMLAH TERJUAL]] -> 4377.1754
A25: 2026 | B25: JULI | C25: 46208 | D25: KEBAB AYAM + SOSIZ (KECIL) | E25: RIA NDU | F25: =VLOOKUP(TBLPRODUKKELUARJULI[[#This Row],[NAMA CUSTOMER]],TBLDATACUSTOMER[],4,FALSE) -> RIA | G25: =VLOOKUP(TBLPRODUKKELUARJULI[[#This Row],[NAMA PRODUK]],TBLKATALOG[],2,FALSE) -> 6122.193 | H25: =VLOOKUP(TBLPRODUKKELUARJULI[[#This Row],[NAMA PRODUK]],TBLKATALOG[],3,FALSE) -> 612.2193 | I25: =VLOOKUP(TBLPRODUKKELUARJULI[[#This Row],[NAMA PRODUK]],TBLKATALOG[],4,FALSE) -> 6734.4123 | J25: =VLOOKUP(TBLPRODUKKELUARJULI[[#This Row],[NAMA PRODUK]],TBLKATALOG[],5,FALSE) -> 9000 | K25: =VLOOKUP(TBLPRODUKKELUARJULI[[#This Row],[NAMA PRODUK]],TBLKATALOG[],6,FALSE) -> 2265.5877 | L25: =VLOOKUP(TBLPRODUKKELUARJULI[[#This Row],[NAMA PRODUK]],TBLKATALOG[],7,FALSE) -> 306.10965 | M25: =VLOOKUP(TBLPRODUKKELUARJULI[[#This Row],[NAMA PRODUK]],TBLKATALOG[],8,FALSE) -> 306.10965 | N25: =VLOOKUP(TBLPRODUKKELUARJULI[[#This Row],[NAMA PRODUK]],TBLKATALOG[],9,FALSE) -> 2265.5877 | O25: 2 | P25: 2 | Q25: =TBLPRODUKKELUARJULI[[#This Row],[MODAL]]*TBLPRODUKKELUARJULI[[#This Row],[JUMLAH TERJUAL]] -> 12244.386 | R25: =TBLPRODUKKELUARJULI[[#This Row],[BUDGET KOMISI]]*TBLPRODUKKELUARJULI[[#This Row],[JUMLAH TERJUAL]] -> 1224.4386 | S25: =TBLPRODUKKELUARJULI[[#This Row],[MODAL DITAMBAH BUDGET KOMISI]]*TBLPRODUKKELUARJULI[[#This Row],[JUMLAH TERJUAL]] -> 13468.825 | T25: =TBLPRODUKKELUARJULI[[#This Row],[HARGA JUAL]]*TBLPRODUKKELUARJULI[[#This Row],[JUMLAH TERJUAL]] -> 18000 | U25: =TBLPRODUKKELUARJULI[[#This Row],[SELISIH]]*TBLPRODUKKELUARJULI[[#This Row],[JUMLAH TERJUAL]] -> 4531.1754 | V25: =TBLPRODUKKELUARJULI[[#This Row],[LABA MITRA 8 %]]*TBLPRODUKKELUARJULI[[#This Row],[JUMLAH TERJUAL]] -> 612.2193 | W25: =TBLPRODUKKELUARJULI[[#This Row],[LABA KIRIM 8 %]]*TBLPRODUKKELUARJULI[[#This Row],[JUMLAH TERKIRIM]] -> 612.2193 | X25: =TBLPRODUKKELUARJULI[[#This Row],[TOTAL LABA MITRA 5%]]+TBLPRODUKKELUARJULI[[#This Row],[TOTAL LABA KIRIM 5%]] -> 1224.4386 | Y25: =TBLPRODUKKELUARJULI[[#This Row],[LABA BERSIH TOKO]]*TBLPRODUKKELUARJULI[[#This Row],[JUMLAH TERJUAL]] -> 4531.1754
A26: 2026 | B26: JULI | C26: 46209 | D26: KEBAB AYAM + SOSIZ (KECIL) PEDAS | E26: RIA NDU | F26: =VLOOKUP(TBLPRODUKKELUARJULI[[#This Row],[NAMA CUSTOMER]],TBLDATACUSTOMER[],4,FALSE) -> RIA | G26: =VLOOKUP(TBLPRODUKKELUARJULI[[#This Row],[NAMA PRODUK]],TBLKATALOG[],2,FALSE) -> 6192.193 | H26: =VLOOKUP(TBLPRODUKKELUARJULI[[#This Row],[NAMA PRODUK]],TBLKATALOG[],3,FALSE) -> 619.2193 | I26: =VLOOKUP(TBLPRODUKKELUARJULI[[#This Row],[NAMA PRODUK]],TBLKATALOG[],4,FALSE) -> 6811.4123 | J26: =VLOOKUP(TBLPRODUKKELUARJULI[[#This Row],[NAMA PRODUK]],TBLKATALOG[],5,FALSE) -> 9000 | K26: =VLOOKUP(TBLPRODUKKELUARJULI[[#This Row],[NAMA PRODUK]],TBLKATALOG[],6,FALSE) -> 2188.5877 | L26: =VLOOKUP(TBLPRODUKKELUARJULI[[#This Row],[NAMA PRODUK]],TBLKATALOG[],7,FALSE) -> 309.60965 | M26: =VLOOKUP(TBLPRODUKKELUARJULI[[#This Row],[NAMA PRODUK]],TBLKATALOG[],8,FALSE) -> 309.60965 | N26: =VLOOKUP(TBLPRODUKKELUARJULI[[#This Row],[NAMA PRODUK]],TBLKATALOG[],9,FALSE) -> 2188.5877 | O26: 2 | P26: 2 | Q26: =TBLPRODUKKELUARJULI[[#This Row],[MODAL]]*TBLPRODUKKELUARJULI[[#This Row],[JUMLAH TERJUAL]] -> 12384.386 | R26: =TBLPRODUKKELUARJULI[[#This Row],[BUDGET KOMISI]]*TBLPRODUKKELUARJULI[[#This Row],[JUMLAH TERJUAL]] -> 1238.4386 | S26: =TBLPRODUKKELUARJULI[[#This Row],[MODAL DITAMBAH BUDGET KOMISI]]*TBLPRODUKKELUARJULI[[#This Row],[JUMLAH TERJUAL]] -> 13622.825 | T26: =TBLPRODUKKELUARJULI[[#This Row],[HARGA JUAL]]*TBLPRODUKKELUARJULI[[#This Row],[JUMLAH TERJUAL]] -> 18000 | U26: =TBLPRODUKKELUARJULI[[#This Row],[SELISIH]]*TBLPRODUKKELUARJULI[[#This Row],[JUMLAH TERJUAL]] -> 4377.1754 | V26: =TBLPRODUKKELUARJULI[[#This Row],[LABA MITRA 8 %]]*TBLPRODUKKELUARJULI[[#This Row],[JUMLAH TERJUAL]] -> 619.2193 | W26: =TBLPRODUKKELUARJULI[[#This Row],[LABA KIRIM 8 %]]*TBLPRODUKKELUARJULI[[#This Row],[JUMLAH TERKIRIM]] -> 619.2193 | X26: =TBLPRODUKKELUARJULI[[#This Row],[TOTAL LABA MITRA 5%]]+TBLPRODUKKELUARJULI[[#This Row],[TOTAL LABA KIRIM 5%]] -> 1238.4386 | Y26: =TBLPRODUKKELUARJULI[[#This Row],[LABA BERSIH TOKO]]*TBLPRODUKKELUARJULI[[#This Row],[JUMLAH TERJUAL]] -> 4377.1754
A27: 2026 | B27: JULI | C27: 46209 | D27: KEBAB AYAM + SOSIZ (KECIL) | E27: RIA NDU | F27: =VLOOKUP(TBLPRODUKKELUARJULI[[#This Row],[NAMA CUSTOMER]],TBLDATACUSTOMER[],4,FALSE) -> RIA | G27: =VLOOKUP(TBLPRODUKKELUARJULI[[#This Row],[NAMA PRODUK]],TBLKATALOG[],2,FALSE) -> 6122.193 | H27: =VLOOKUP(TBLPRODUKKELUARJULI[[#This Row],[NAMA PRODUK]],TBLKATALOG[],3,FALSE) -> 612.2193 | I27: =VLOOKUP(TBLPRODUKKELUARJULI[[#This Row],[NAMA PRODUK]],TBLKATALOG[],4,FALSE) -> 6734.4123 | J27: =VLOOKUP(TBLPRODUKKELUARJULI[[#This Row],[NAMA PRODUK]],TBLKATALOG[],5,FALSE) -> 9000 | K27: =VLOOKUP(TBLPRODUKKELUARJULI[[#This Row],[NAMA PRODUK]],TBLKATALOG[],6,FALSE) -> 2265.5877 | L27: =VLOOKUP(TBLPRODUKKELUARJULI[[#This Row],[NAMA PRODUK]],TBLKATALOG[],7,FALSE) -> 306.10965 | M27: =VLOOKUP(TBLPRODUKKELUARJULI[[#This Row],[NAMA PRODUK]],TBLKATALOG[],8,FALSE) -> 306.10965 | N27: =VLOOKUP(TBLPRODUKKELUARJULI[[#This Row],[NAMA PRODUK]],TBLKATALOG[],9,FALSE) -> 2265.5877 | O27: 2 | P27: 2 | Q27: =TBLPRODUKKELUARJULI[[#This Row],[MODAL]]*TBLPRODUKKELUARJULI[[#This Row],[JUMLAH TERJUAL]] -> 12244.386 | R27: =TBLPRODUKKELUARJULI[[#This Row],[BUDGET KOMISI]]*TBLPRODUKKELUARJULI[[#This Row],[JUMLAH TERJUAL]] -> 1224.4386 | S27: =TBLPRODUKKELUARJULI[[#This Row],[MODAL DITAMBAH BUDGET KOMISI]]*TBLPRODUKKELUARJULI[[#This Row],[JUMLAH TERJUAL]] -> 13468.825 | T27: =TBLPRODUKKELUARJULI[[#This Row],[HARGA JUAL]]*TBLPRODUKKELUARJULI[[#This Row],[JUMLAH TERJUAL]] -> 18000 | U27: =TBLPRODUKKELUARJULI[[#This Row],[SELISIH]]*TBLPRODUKKELUARJULI[[#This Row],[JUMLAH TERJUAL]] -> 4531.1754 | V27: =TBLPRODUKKELUARJULI[[#This Row],[LABA MITRA 8 %]]*TBLPRODUKKELUARJULI[[#This Row],[JUMLAH TERJUAL]] -> 612.2193 | W27: =TBLPRODUKKELUARJULI[[#This Row],[LABA KIRIM 8 %]]*TBLPRODUKKELUARJULI[[#This Row],[JUMLAH TERKIRIM]] -> 612.2193 | X27: =TBLPRODUKKELUARJULI[[#This Row],[TOTAL LABA MITRA 5%]]+TBLPRODUKKELUARJULI[[#This Row],[TOTAL LABA KIRIM 5%]] -> 1224.4386 | Y27: =TBLPRODUKKELUARJULI[[#This Row],[LABA BERSIH TOKO]]*TBLPRODUKKELUARJULI[[#This Row],[JUMLAH TERJUAL]] -> 4531.1754
... A87: 2026 | B87: JULI | C87: 46228 | D87: KEBAB AYAM + SOSIZ (KECIL) | E87: RIA NDU | F87: =VLOOKUP(TBLPRODUKKELUARJULI[[#This Row],[NAMA CUSTOMER]],TBLDATACUSTOMER[],4,FALSE) -> RIA | G87: =VLOOKUP(TBLPRODUKKELUARJULI[[#This Row],[NAMA PRODUK]],TBLKATALOG[],2,FALSE) -> 6122.193 | H87: =VLOOKUP(TBLPRODUKKELUARJULI[[#This Row],[NAMA PRODUK]],TBLKATALOG[],3,FALSE) -> 612.2193 | I87: =VLOOKUP(TBLPRODUKKELUARJULI[[#This Row],[NAMA PRODUK]],TBLKATALOG[],4,FALSE) -> 6734.4123 | J87: =VLOOKUP(TBLPRODUKKELUARJULI[[#This Row],[NAMA PRODUK]],TBLKATALOG[],5,FALSE) -> 9000 | K87: =VLOOKUP(TBLPRODUKKELUARJULI[[#This Row],[NAMA PRODUK]],TBLKATALOG[],6,FALSE) -> 2265.5877 | L87: =VLOOKUP(TBLPRODUKKELUARJULI[[#This Row],[NAMA PRODUK]],TBLKATALOG[],7,FALSE) -> 306.10965 | M87: =VLOOKUP(TBLPRODUKKELUARJULI[[#This Row],[NAMA PRODUK]],TBLKATALOG[],8,FALSE) -> 306.10965 | N87: =VLOOKUP(TBLPRODUKKELUARJULI[[#This Row],[NAMA PRODUK]],TBLKATALOG[],9,FALSE) -> 2265.5877 | O87: 1 | P87: 1 | Q87: =TBLPRODUKKELUARJULI[[#This Row],[MODAL]]*TBLPRODUKKELUARJULI[[#This Row],[JUMLAH TERJUAL]] -> 6122.193 | R87: =TBLPRODUKKELUARJULI[[#This Row],[BUDGET KOMISI]]*TBLPRODUKKELUARJULI[[#This Row],[JUMLAH TERJUAL]] -> 612.2193 | S87: =TBLPRODUKKELUARJULI[[#This Row],[MODAL DITAMBAH BUDGET KOMISI]]*TBLPRODUKKELUARJULI[[#This Row],[JUMLAH TERJUAL]] -> 6734.4123 | T87: =TBLPRODUKKELUARJULI[[#This Row],[HARGA JUAL]]*TBLPRODUKKELUARJULI[[#This Row],[JUMLAH TERJUAL]] -> 9000 | U87: =TBLPRODUKKELUARJULI[[#This Row],[SELISIH]]*TBLPRODUKKELUARJULI[[#This Row],[JUMLAH TERJUAL]] -> 2265.5877 | V87: =TBLPRODUKKELUARJULI[[#This Row],[LABA MITRA 8 %]]*TBLPRODUKKELUARJULI[[#This Row],[JUMLAH TERJUAL]] -> 306.10965 | W87: =TBLPRODUKKELUARJULI[[#This Row],[LABA KIRIM 8 %]]*TBLPRODUKKELUARJULI[[#This Row],[JUMLAH TERKIRIM]] -> 306.10965 | X87: =TBLPRODUKKELUARJULI[[#This Row],[TOTAL LABA MITRA 5%]]+TBLPRODUKKELUARJULI[[#This Row],[TOTAL LABA KIRIM 5%]] -> 612.2193 | Y87: =TBLPRODUKKELUARJULI[[#This Row],[LABA BERSIH TOKO]]*TBLPRODUKKELUARJULI[[#This Row],[JUMLAH TERJUAL]] -> 2265.5877

Sheet REKAP PENJUALAN
A1: CAHYA GALLERY FOOD AND BEVERAGE
A3: JUNI
A4: TAHUN | B4: BULAN | C4: TANGGAL | D4: TOTAL PENJUALAN | E4: TOTAL MODAL | F4: TOTAL KOMISI UTAMA | G4: LABA BERSIH TOKO | I4: OMZET JANUARI | J4: LABA BERSIH TOKO
A5: 2026 | B5: JUNI | C5: 46198 | D5: =SUMIF(TBLPRODUKKELUARJUNI[TANGGAL],TBLREKAPJUNI[TANGGAL],TBLPRODUKKELUARJUNI[TOTAL HARGA JUAL]) -> 129000 | E5: =SUMIF(TBLPRODUKKELUARJUNI[TANGGAL],TBLREKAPJUNI[TANGGAL],TBLPRODUKKELUARJUNI[TOTAL MODAL]) -> 89163.737 | F5: =SUMIF(TBLPRODUKKELUARJUNI[TANGGAL],TBLREKAPJUNI[TANGGAL],TBLPRODUKKELUARJUNI[TAKE HOME KOMISI UTAMA]) -> 8916.3737 | G5: =SUMIF(TBLPRODUKKELUARJUNI[TANGGAL],TBLREKAPJUNI[TANGGAL],TBLPRODUKKELUARJUNI[TOTAL LABA BERSIH TOKO]) -> 30919.889 | I5: =SUM(TBLREKAPJUNI[TOTAL PENJUALAN]) -> 129000 | J5: =SUM(TBLREKAPJUNI[LABA BERSIH TOKO]) -> 30919.889
A8: JULI
A9: TAHUN | B9: BULAN | C9: TANGGAL | D9: TOTAL PENJUALAN | E9: TOTAL MODAL | F9: TOTAL KOMISI UTAMA | G9: LABA BERSIH TOKO | I9: OMZET JANUARI | J9: LABA BERSIH TOKO
A10: 2026 | B10: JULI | C10: 46206 | D10: =SUMIF(TBLPRODUKKELUARJULI[TANGGAL],TBLREKAPJULI[[#This Row],[TANGGAL]],TBLPRODUKKELUARJULI[TOTAL HARGA JUAL]) -> 36000 | E10: =SUMIF(TBLPRODUKKELUARJULI[TANGGAL],TBLREKAPJULI[[#This Row],[TANGGAL]],TBLPRODUKKELUARJULI[TOTAL MODAL]) -> 24628.772 | F10: =SUMIF(TBLPRODUKKELUARJULI[TANGGAL],TBLREKAPJULI[[#This Row],[TANGGAL]],TBLPRODUKKELUARJULI[TAKE HOME KOMISI UTAMA]) -> 2462.8772 | G10: =SUMIF(TBLPRODUKKELUARJULI[TANGGAL],TBLREKAPJULI[[#This Row],[TANGGAL]],TBLPRODUKKELUARJULI[TOTAL LABA BERSIH TOKO]) -> 8908.3509 | I10: =SUM(TBLREKAPJULI[TOTAL PENJUALAN]) -> 1872000 | J10: =SUM(TBLREKAPJULI[LABA BERSIH TOKO]) -> 394666.07
A11: 2026 | B11: JULI | C11: 46207 | D11: =SUMIF(TBLPRODUKKELUARJULI[TANGGAL],TBLREKAPJULI[[#This Row],[TANGGAL]],TBLPRODUKKELUARJULI[TOTAL HARGA JUAL]) -> 150000 | E11: =SUMIF(TBLPRODUKKELUARJULI[TANGGAL],TBLREKAPJULI[[#This Row],[TANGGAL]],TBLPRODUKKELUARJULI[TOTAL MODAL]) -> 102640.91 | F11: =SUMIF(TBLPRODUKKELUARJULI[TANGGAL],TBLREKAPJULI[[#This Row],[TANGGAL]],TBLPRODUKKELUARJULI[TAKE HOME KOMISI UTAMA]) -> 10264.091 | G11: =SUMIF(TBLPRODUKKELUARJULI[TANGGAL],TBLREKAPJULI[[#This Row],[TANGGAL]],TBLPRODUKKELUARJULI[TOTAL LABA BERSIH TOKO]) -> 37094.996
A12: 2026 | B12: JULI | C12: 46208 | D12: =SUMIF(TBLPRODUKKELUARJULI[TANGGAL],TBLREKAPJULI[[#This Row],[TANGGAL]],TBLPRODUKKELUARJULI[TOTAL HARGA JUAL]) -> 36000 | E12: =SUMIF(TBLPRODUKKELUARJULI[TANGGAL],TBLREKAPJULI[[#This Row],[TANGGAL]],TBLPRODUKKELUARJULI[TOTAL MODAL]) -> 24628.772 | F12: =SUMIF(TBLPRODUKKELUARJULI[TANGGAL],TBLREKAPJULI[[#This Row],[TANGGAL]],TBLPRODUKKELUARJULI[TAKE HOME KOMISI UTAMA]) -> 2462.8772 | G12: =SUMIF(TBLPRODUKKELUARJULI[TANGGAL],TBLREKAPJULI[[#This Row],[TANGGAL]],TBLPRODUKKELUARJULI[TOTAL LABA BERSIH TOKO]) -> 8908.3509
A13: 2026 | B13: JULI | C13: 46209 | D13: =SUMIF(TBLPRODUKKELUARJULI[TANGGAL],TBLREKAPJULI[[#This Row],[TANGGAL]],TBLPRODUKKELUARJULI[TOTAL HARGA JUAL]) -> 151000 | E13: =SUMIF(TBLPRODUKKELUARJULI[TANGGAL],TBLREKAPJULI[[#This Row],[TANGGAL]],TBLPRODUKKELUARJULI[TOTAL MODAL]) -> 109927.22 | F13: =SUMIF(TBLPRODUKKELUARJULI[TANGGAL],TBLREKAPJULI[[#This Row],[TANGGAL]],TBLPRODUKKELUARJULI[TAKE HOME KOMISI UTAMA]) -> 10992.722 | G13: =SUMIF(TBLPRODUKKELUARJULI[TANGGAL],TBLREKAPJULI[[#This Row],[TANGGAL]],TBLPRODUKKELUARJULI[TOTAL LABA BERSIH TOKO]) -> 30080.056
A14: 2026 | B14: JULI | C14: 46210 | D14: =SUMIF(TBLPRODUKKELUARJULI[TANGGAL],TBLREKAPJULI[[#This Row],[TANGGAL]],TBLPRODUKKELUARJULI[TOTAL HARGA JUAL]) -> 63000 | E14: =SUMIF(TBLPRODUKKELUARJULI[TANGGAL],TBLREKAPJULI[[#This Row],[TANGGAL]],TBLPRODUKKELUARJULI[TOTAL MODAL]) -> 43090.737 | F14: =SUMIF(TBLPRODUKKELUARJULI[TANGGAL],TBLREKAPJULI[[#This Row],[TANGGAL]],TBLPRODUKKELUARJULI[TAKE HOME KOMISI UTAMA]) -> 4309.0737 | G14: =SUMIF(TBLPRODUKKELUARJULI[TANGGAL],TBLREKAPJULI[[#This Row],[TANGGAL]],TBLPRODUKKELUARJULI[TOTAL LABA BERSIH TOKO]) -> 15600.189
A15: 2026 | B15: JULI | C15: 46211 | D15: =SUMIF(TBLPRODUKKELUARJULI[TANGGAL],TBLREKAPJULI[[#This Row],[TANGGAL]],TBLPRODUKKELUARJULI[TOTAL HARGA JUAL]) -> 114000 | E15: =SUMIF(TBLPRODUKKELUARJULI[TANGGAL],TBLREKAPJULI[[#This Row],[TANGGAL]],TBLPRODUKKELUARJULI[TOTAL MODAL]) -> 84514.797 | F15: =SUMIF(TBLPRODUKKELUARJULI[TANGGAL],TBLREKAPJULI[[#This Row],[TANGGAL]],TBLPRODUKKELUARJULI[TAKE HOME KOMISI UTAMA]) -> 8451.4797 | G15: =SUMIF(TBLPRODUKKELUARJULI[TANGGAL],TBLREKAPJULI[[#This Row],[TANGGAL]],TBLPRODUKKELUARJULI[TOTAL LABA BERSIH TOKO]) -> 21033.723
A16: 2026 | B16: JULI | C16: 46212 | D16: =SUMIF(TBLPRODUKKELUARJULI[TANGGAL],TBLREKAPJULI[[#This Row],[TANGGAL]],TBLPRODUKKELUARJULI[TOTAL HARGA JUAL]) -> 183000 | E16: =SUMIF(TBLPRODUKKELUARJULI[TANGGAL],TBLREKAPJULI[[#This Row],[TANGGAL]],TBLPRODUKKELUARJULI[TOTAL MODAL]) -> 125933.93 | F16: =SUMIF(TBLPRODUKKELUARJULI[TANGGAL],TBLREKAPJULI[[#This Row],[TANGGAL]],TBLPRODUKKELUARJULI[TAKE HOME KOMISI UTAMA]) -> 12593.393 | G16: =SUMIF(TBLPRODUKKELUARJULI[TANGGAL],TBLREKAPJULI[[#This Row],[TANGGAL]],TBLPRODUKKELUARJULI[TOTAL LABA BERSIH TOKO]) -> 44472.677
A17: 2026 | B17: JULI | C17: 46213 | D17: =SUMIF(TBLPRODUKKELUARJULI[TANGGAL],TBLREKAPJULI[[#This Row],[TANGGAL]],TBLPRODUKKELUARJULI[TOTAL HARGA JUAL]) -> 63000 | E17: =SUMIF(TBLPRODUKKELUARJULI[TANGGAL],TBLREKAPJULI[[#This Row],[TANGGAL]],TBLPRODUKKELUARJULI[TOTAL MODAL]) -> 43135.351 | F17: =SUMIF(TBLPRODUKKELUARJULI[TANGGAL],TBLREKAPJULI[[#This Row],[TANGGAL]],TBLPRODUKKELUARJULI[TAKE HOME KOMISI UTAMA]) -> 4313.5351 | G17: =SUMIF(TBLPRODUKKELUARJULI[TANGGAL],TBLREKAPJULI[[#This Row],[TANGGAL]],TBLPRODUKKELUARJULI[TOTAL LABA BERSIH TOKO]) -> 15551.114
A18: 2026 | B18: JULI | C18: 46214 | D18: =SUMIF(TBLPRODUKKELUARJULI[TANGGAL],TBLREKAPJULI[[#This Row],[TANGGAL]],TBLPRODUKKELUARJULI[TOTAL HARGA JUAL]) -> 204000 | E18: =SUMIF(TBLPRODUKKELUARJULI[TANGGAL],TBLREKAPJULI[[#This Row],[TANGGAL]],TBLPRODUKKELUARJULI[TOTAL MODAL]) -> 154441.59 | F18: =SUMIF(TBLPRODUKKELUARJULI[TANGGAL],TBLREKAPJULI[[#This Row],[TANGGAL]],TBLPRODUKKELUARJULI[TAKE HOME KOMISI UTAMA]) -> 15444.159 | G18: =SUMIF(TBLPRODUKKELUARJULI[TANGGAL],TBLREKAPJULI[[#This Row],[TANGGAL]],TBLPRODUKKELUARJULI[TOTAL LABA BERSIH TOKO]) -> 34114.246
A19: 2026 | B19: JULI | C19: 46215 | D19: =SUMIF(TBLPRODUKKELUARJULI[TANGGAL],TBLREKAPJULI[[#This Row],[TANGGAL]],TBLPRODUKKELUARJULI[TOTAL HARGA JUAL]) -> 90000 | E19: =SUMIF(TBLPRODUKKELUARJULI[TANGGAL],TBLREKAPJULI[[#This Row],[TANGGAL]],TBLPRODUKKELUARJULI[TOTAL MODAL]) -> 61501.93 | F19: =SUMIF(TBLPRODUKKELUARJULI[TANGGAL],TBLREKAPJULI[[#This Row],[TANGGAL]],TBLPRODUKKELUARJULI[TAKE HOME KOMISI UTAMA]) -> 6150.193 | G19: =SUMIF(TBLPRODUKKELUARJULI[TANGGAL],TBLREKAPJULI[[#This Row],[TANGGAL]],TBLPRODUKKELUARJULI[TOTAL LABA BERSIH TOKO]) -> 22347.877
A20: 2026 | B20: JULI | C20: 46216 | D20: =SUMIF(TBLPRODUKKELUARJULI[TANGGAL],TBLREKAPJULI[[#This Row],[TANGGAL]],TBLPRODUKKELUARJULI[TOTAL HARGA JUAL]) -> 108000 | E20: =SUMIF(TBLPRODUKKELUARJULI[TANGGAL],TBLREKAPJULI[[#This Row],[TANGGAL]],TBLPRODUKKELUARJULI[TOTAL MODAL]) -> 73606.316 | F20: =SUMIF(TBLPRODUKKELUARJULI[TANGGAL],TBLREKAPJULI[[#This Row],[TANGGAL]],TBLPRODUKKELUARJULI[TAKE HOME KOMISI UTAMA]) -> 7360.6316 | G20: =SUMIF(TBLPRODUKKELUARJULI[TANGGAL],TBLREKAPJULI[[#This Row],[TANGGAL]],TBLPRODUKKELUARJULI[TOTAL LABA BERSIH TOKO]) -> 27033.053
A21: 2026 | B21: JULI | C21: 46217 | D21: =SUMIF(TBLPRODUKKELUARJULI[TANGGAL],TBLREKAPJULI[[#This Row],[TANGGAL]],TBLPRODUKKELUARJULI[TOTAL HARGA JUAL]) -> 36000 | E21: =SUMIF(TBLPRODUKKELUARJULI[TANGGAL],TBLREKAPJULI[[#This Row],[TANGGAL]],TBLPRODUKKELUARJULI[TOTAL MODAL]) -> 24628.772 | F21: =SUMIF(TBLPRODUKKELUARJULI[TANGGAL],TBLREKAPJULI[[#This Row],[TANGGAL]],TBLPRODUKKELUARJULI[TAKE HOME KOMISI UTAMA]) -> 2462.8772 | G21: =SUMIF(TBLPRODUKKELUARJULI[TANGGAL],TBLREKAPJULI[[#This Row],[TANGGAL]],TBLPRODUKKELUARJULI[TOTAL LABA BERSIH TOKO]) -> 8908.3509
A22: 2026 | B22: JULI | C22: 46218 | D22: =SUMIF(TBLPRODUKKELUARJULI[TANGGAL],TBLREKAPJULI[[#This Row],[TANGGAL]],TBLPRODUKKELUARJULI[TOTAL HARGA JUAL]) -> 54000 | E22: =SUMIF(TBLPRODUKKELUARJULI[TANGGAL],TBLREKAPJULI[[#This Row],[TANGGAL]],TBLPRODUKKELUARJULI[TOTAL MODAL]) -> 36943.158 | F22: =SUMIF(TBLPRODUKKELUARJULI[TANGGAL],TBLREKAPJULI[[#This Row],[TANGGAL]],TBLPRODUKKELUARJULI[TAKE HOME KOMISI UTAMA]) -> 3694.3158 | G22: =SUMIF(TBLPRODUKKELUARJULI[TANGGAL],TBLREKAPJULI[[#This Row],[TANGGAL]],TBLPRODUKKELUARJULI[TOTAL LABA BERSIH TOKO]) -> 13362.526
... A29: 2026 | B29: JULI | C29: 46228 | D29: =SUMIF(TBLPRODUKKELUARJULI[TANGGAL],TBLREKAPJULI[[#This Row],[TANGGAL]],TBLPRODUKKELUARJULI[TOTAL HARGA JUAL]) -> 36000 | E29: =SUMIF(TBLPRODUKKELUARJULI[TANGGAL],TBLREKAPJULI[[#This Row],[TANGGAL]],TBLPRODUKKELUARJULI[TOTAL MODAL]) -> 24698.772 | F29: =SUMIF(TBLPRODUKKELUARJULI[TANGGAL],TBLREKAPJULI[[#This Row],[TANGGAL]],TBLPRODUKKELUARJULI[TAKE HOME KOMISI UTAMA]) -> 2469.8772 | G29: =SUMIF(TBLPRODUKKELUARJULI[TANGGAL],TBLREKAPJULI[[#This Row],[TANGGAL]],TBLPRODUKKELUARJULI[TOTAL LABA BERSIH TOKO]) -> 8831.3509

Sheet KOMISI CAMPURAN
A1: KOMISI CAMPURAN
A2: JUNI
A3: TAHUN | B3: BULAN | C3: TANGGAL | D3: NAMA MITRA | E3: SISA KOMISI | F3: KOMISI LAIN LAIN | G3: NILAI SISA KOMISI | H3: NILAI KOMISI LAIN LAIN | I3: TOTAL KOMISI
A4: 2026 | B4: JUNI | C4: 46190 | D4: NURUL HIDAYATU SAMSIAH | F4: KOMISI BELANJA & OLAH AYAM SUWIR | G4: =TBLKOMISICAMPURANJUNI[[#This Row],[SISA KOMISI]] -> 0 | H4: =5000+6000 -> 11000 | I4: =TBLKOMISICAMPURANJUNI[[#This Row],[NILAI SISA KOMISI]]+TBLKOMISICAMPURANJUNI[[#This Row],[NILAI KOMISI LAIN LAIN]] -> 11000
A5: 2026 | B5: JUNI | C5: 46198 | D5: NURUL HIDAYATU SAMSIAH | F5: KOMISI ANTAR ORDERAN | G5: =TBLKOMISICAMPURANJUNI[[#This Row],[SISA KOMISI]] -> 0 | H5: 3000 | I5: =TBLKOMISICAMPURANJUNI[[#This Row],[NILAI SISA KOMISI]]+TBLKOMISICAMPURANJUNI[[#This Row],[NILAI KOMISI LAIN LAIN]] -> 3000
A8: JULI
A9: TAHUN | B9: BULAN | C9: TANGGAL | D9: NAMA MITRA | E9: SISA KOMISI | F9: KOMISI LAIN LAIN | G9: NILAI SISA KOMISI | H9: NILAI KOMISI LAIN LAIN | I9: TOTAL KOMISI
A10: 2026 | B10: JULI | C10: 46206 | D10: NURUL HIDAYATU SAMSIAH | F10: KOMISI ANTAR ORDERAN | G10: =TBLKOMISICAMPURANJULI[[#This Row],[SISA KOMISI]] -> 0 | H10: 3000 | I10: =TBLKOMISICAMPURANJULI[[#This Row],[NILAI SISA KOMISI]]+TBLKOMISICAMPURANJULI[[#This Row],[NILAI KOMISI LAIN LAIN]] -> 3000
A11: 2026 | B11: JULI | C11: 46207 | D11: NURUL HIDAYATU SAMSIAH | F11: KOMISI ANTAR ORDERAN & BELANJA & OLAH AYAM SUWIR | G11: =TBLKOMISICAMPURANJULI[[#This Row],[SISA KOMISI]] -> 0 | H11: =3000+3000+18000 -> 24000 | I11: =TBLKOMISICAMPURANJULI[[#This Row],[NILAI SISA KOMISI]]+TBLKOMISICAMPURANJULI[[#This Row],[NILAI KOMISI LAIN LAIN]] -> 24000
